Workbook

Sheet Jan 2023
E2: Jan 2023 Sales in Nutsell
E3: Grades | F3: Off Grade | G3: 1799 | H3: 2099 | I3: 2699 | J3: 588 | K3: 2088 | L3: 2488 | M3: 2688 | N3: TOTAL
E4: Qty | F4: ='Jan 2023'!$J$53 -> 6980 | G4: ='Jan 2023'!$K$53 -> 23100 | H4: ='Jan 2023'!$L$53 -> 950 | I4: ='Jan 2023'!$M$53 -> 1275 | J4: ='Jan 2023'!$N$53 -> 1100 | K4: ='Jan 2023'!$O$53 -> 0 | L4: ='Jan 2023'!$P$53 -> 600 | M4: ='Jan 2023'!$Q$53 -> 3950 | N4: =SUM(F4:M4) -> 37955
E5: Avg Sales PK
E6: Profit PK
E7: Total
D11: Srl No | E11: Date | F11: Inv No | G11: Party | H11: Qty | I11: Price | J11: Off Grade | K11: 1799 | L11: 2099 | M11: 2699 | N11: 588 | O11: 2088 | P11: 2488 | Q11: 2688
D12: 1 | E12: 44928 | F12: 258 | G12: Darshan | H12: 220 | I12: 160 | J12: 220
D13: 2 | E13: 44928 | F13: 259 | G13: Giriraj | H13: 1000 | I13: 228 | Q13: 1000
D14: 3 | E14: 44928 | F14: 260 | G14: Giriraj | H14: 3000 | I14: 150 | J14: 3000
D15: 4 | E15: 44928 | F15: 261 | G15: Chemicare | H15: 6200 | I15: 200 | K15: 6200
D16: 5 | E16: 44929 | F16: 58 GTC | G16: SKS Fine | H16: 250 | I16: 220 / 225 | M16: 50 | P16: 200
D17: 6 | E17: 44930 | F17: 263 | G17: Seamless | H17: 200 | I17: 230 | Q17: 200
D18: 7 | E18: 44935 | F18: RR | G18: Meet Sach | H18: 600 | I18: 204 / 216 | L18: 400 | M18: 200
D19: 8 | E19: 44935 | F19: RR | G19: Shri Ganpatye | H19: 500 | I19: 225 | Q19: 500
D20: 9 | E20: 44936 | F20: 60 GTC | G20: Veena | H20: 425 | I20: 227 / 220 | M20: 25 | P20: 400
D21: 10 | E21: 44939 | F21: 62 GTC | G21: Chandan Syn | H21: 500 | I21: 204 | L21: 500
D22: 11 | E22: 44939 | F22: 63 gtc | G22: Fortune | H22: 250 | I22: 230 | Q22: 250
D23: 12 | E23: 44944 | F23: RR | G23: Santosh | H23: 50 | I23: 240 | L23: 50
D24: 13 | E24: 44945 | F24: 268 | G24: Dhiren Enter | H24: 100 | I24: 235 | N24: 100
D25: 14 | E25: 44946 | F25: 269 | G25: Papyrus | H25: 500 | I25: 160 | J25: 500
D26: 15 | E26: 44947 | F26: 271 | G26: Indokem | H26: 5000 | I26: 205 | K26: 5000
D27: 16 | E27: 44949 | F27: RR | G27: Meet Sach | H27: 400 | I27: 204 | K27: 400
D28: 17 | E28: 44949 | F28: 64 GTC | G28: AP Bonding | H28: 1000 | I28: 216 | N28: 1000
D29: 18 | E29: 44953 | F29: 275 | G29: Surya | H29: 2000 | I29: 225 | Q29: 2000
D30: 19 | E30: 44953 | F30: RR | G30: Hareshji | H30: 500 | I30: 212 | M30: 500
D31: 20 | E31: 44953 | F31: 276 | G31: Chandan Syn | H31: 3000 | I31: 160 | J31: 3000
D32: 21 | E32: 44954 | F32: 277 | G32: Mangalam Dye | H32: 278 | I32: 160 | J32: 260
D33: 22 | E33: 44954 | F33: 279 | G33: Fortune | H33: 500 | I33: 220 | M33: 500
D34: 23 | E34: 44957 | F34: 280 | G34: Indokem | H34: 11500 | I34: 205 | K34: 11500
D53: TOTAL | H53: =SUM(H12:H52) -> 37973 | J53: =SUM('Jan 2023'!$J$12:$J$52) -> 6980 | K53: =SUM('Jan 2023'!$K$12:$K$52) -> 23100 | L53: =SUM('Jan 2023'!$L$12:$L$52) -> 950 | M53: =SUM('Jan 2023'!$M$12:$M$52) -> 1275 | N53: =SUM('Jan 2023'!$N$12:$N$52) -> 1100 | O53: =SUM('Jan 2023'!$O$12:$O$52) -> 0 | P53: =SUM('Jan 2023'!$P$12:$P$52) -> 600 | Q53: =SUM('Jan 2023'!$Q$12:$Q$52) -> 3950

Sheet Feb 2023
D3: Feb 2023 Sales in Nutsell
D4: Grades | E4: Off Grade | F4: 1799 | G4: 2099 | H4: 2699 | I4: 588 | J4: 2088 | K4: 2488 | L4: 2688 | M4: TOTAL
D5: Qty | E5: ='Feb 2023'!$I$54 -> 16330 | F5: ='Feb 2023'!$J$54 -> 1100 | G5: ='Feb 2023'!$K$54 -> 1300 | H5: ='Feb 2023'!$L$54 -> 4820 | I5: ='Feb 2023'!$M$54 -> 1000 | J5: ='Feb 2023'!$N$54 -> 8925 | K5: ='Feb 2023'!$O$54 -> 3660 | L5: ='Feb 2023'!$P$54 -> 600 | M5: =SUM(E5:L5) -> 37735
D6: Avg Sales PK
D7: Profit PK
D8: Total
C12: Srl No | D12: Date | E12: Inv No | F12: Party | G12: Qty | H12: Price | I12: Off Grade | J12: 1799 | K12: 2099 | L12: 2699 | M12: 588 | N12: 2088 | O12: 2488 | P12: 2688
C13: 1 | D13: 44958 | E13: 282 | F13: KDM | G13: 60 | H13: 160 | I13: 60
C14: 2 | D14: 44961 | E14: 283 | F14: Aditya | G14: 1500 | H14: 205 | L14: 1500
C15: 3 | D15: 44961 | E15: 284 | F15: Veena | G15: 400 | H15: 225 | O15: 400
C16: 4 | D16: 44596 | E16: RR | F16: Meet Sach | G16: 500 | H16: 205/206 | J16: 200 | K16: 300
C17: 5 | D17: 44964 | E17: 287 | F17: Can Image | G17: 500 | H17: 220 | N17: 500
C18: 6 | D18: 44966 | E18: 288 | F18: Paramount | G18: 10000 | H18: 150 | I18: 10000
C19: 7 | D19: 44966 | E19: 289 | F19: Can Image | G19: 1000 | H19: 225 / 230 | O19: 500 | P19: 500
C20: 8 | D20: 44966 | E20: RR | F20: Naveen Bhai | G20: 700 | H20: 155 | I20: 700
C21: 9 | D21: 44967 | E21: 291 | F21: Bhavya Enter | G21: 900 | H21: 201 | J21: 900
C22: 10 | D22: 44968 | E22: 292 | F22: Darshan | G22: 200 | H22: 160 | I22: 200
C23: 11 | D23: 44968 | E23: 295 | F23: Jay Organics | G23: 100 | H23: 160 | I23: 160
C24: 12 | D24: 44968 | E24: 296 | F24: Can Image | G24: 5000 | H24: 216 | N24: 5000
C25: 13 | D25: 44968 | E25: 297 | F25: Kanha Trading | G25: 200 | H25: 160 | I25: 200
C26: 14 | D26: 44970 | E26: 298 | F26: Keval Corp | G26: 50 | H26: 217 | O26: 50
C27: 15 | D27: 44970 | E27: RR | F27: Meet Sach | G27: 300 | H27: 155 | I27: 300
C28: 16 | D28: 44971 | E28: 67 GTC | F28: Veena | G28: 500 | H28: 225 | O28: 500
C29: 17 | D29: 44972 | E29: 299 | F29: Paresh Pure Chem | G29: 250 | H29: 150 | I29: 250
C30: 18 | D30: 44972 | E30: 301 | F30: Papyrus | G30: 500 | H30: 150 | I30: 500
C31: 19 | D31: 44972 | E31: 300 | F31: Suncol | G31: 760 | H31: 160 | I31: 760
C32: 20 | D32: 44972 | E32: 302 | F32: Paresh Pure Chem | G32: 200 | H32: 160 | I32: 200
C33: 21 | D33: 44972 | E33: 303, 304 | F33: BSB Inds | G33: 4000 | H33: 150, 204, 213 | I33: 2000 | K33: 500 | L33: 1500
C34: 22 | D34: 44977 | E34: 305 | F34: KDM | G34: 200 | H34: 160 | I34: 200
C35: 23 | D35: 44977 | E35: 306 | F35: Devankshi | G35: 1000 | H35: 215 | N35: 1000
C36: 24 | D36: 44977 | E36: 307 | F36: Devankshi | G36: 1200 | H36: 216 | N36: 1200
C37: 25 | D37: 44977 | E37: RR | F37: Meet Sach | G37: 100 | H37: 215 | L37: 100
C38: 26 | D38: 44977 | E38: 308 | F38: Aditya | G38: 1000 | H38: 220 | M38: 1000
C39: 27 | D39: 44979 | E39: 309 | F39: Neelam | G39: 500 | H39: 220 | O39: 220
C40: 28 | D40: 44981 | E40: 311 | F40: Can Image | G40: 3000 | H40: 216, 220 | N40: 1225 | O40: 1775
C41: 29 | D41: 44981 | E41: 68 GTC | F41: Fortune | G41: 250 | H41: 220 | L41: 220
C42: 30 | D42: 44984 | E42: 313 | F42: Paresh Pure Chem | G42: 500 | H42: 155 | I42: 500
C43: 31 | D43: 44984 | E43: 314 | F43: Seamless | G43: 100 | H43: 230 | P43: 100
C44: 32 | D44: 44984 | E44: RR | F44: Gurpreet | G44: 500 | H44: 210 | K44: 500
C45: 33 | D45: 44984 | E45: 69 GTC | F45: Aditya | G45: 1500 | H45: 214 | L45: 1500
C46: 34 | D46: 44985 | E46: RR | F46: Meet Sach | G46: 300 | H46: 155 | I46: 300
C47: 35 | D47: 44985 | E47: 317 | F47: Divysai | G47: 1000 | H47: 215 | O47: 215
C54: TOTAL | G54: =SUM(G13:G53) -> 38770 | I54: =SUM('Feb 2023'!$I$13:$I$53) -> 16330 | J54: =SUM('Feb 2023'!$J$13:$J$53) -> 1100 | K54: =SUM('Feb 2023'!$K$13:$K$53) -> 1300 | L54: =SUM('Feb 2023'!$L$13:$L$53) -> 4820 | M54: =SUM('Feb 2023'!$M$13:$M$53) -> 1000 | N54: =SUM('Feb 2023'!$N$13:$N$53) -> 8925 | O54: =SUM('Feb 2023'!$O$13:$O$53) -> 3660 | P54: =SUM('Feb 2023'!$P$13:$P$53) -> 600

Sheet March 2023
D2: March 2023 Sales in Nutsell
D3: Grades | E3: Off Grade | F3: 1799 | G3: 2099 | H3: 2699 | I3: 588 | J3: 2088 | K3: 2488 | L3: 2688 | M3: TOTAL
D4: Qty | E4: ='March 2023'!$I$53 -> 6525 | F4: ='March 2023'!$J$53 -> 11500 | G4: ='March 2023'!$K$53 -> 25 | H4: ='March 2023'!$L$53 -> 4600 | I4: ='March 2023'!$M$53 -> 50 | J4: ='March 2023'!$N$53 -> 7450 | K4: ='March 2023'!$O$53 -> 8000 | L4: ='March 2023'!$P$53 -> 2200 | M4: =SUM(E4:L4) -> 40350
D5: Avg Sales PK
D6: Profit PK
D7: Total
C11: Srl No | D11: Date | E11: Inv No | F11: Party | G11: Qty | H11: Price | I11: Off Grade | J11: 1799 | K11: 2099 | L11: 2699 | M11: 588 | N11: 2088 | O11: 2488 | P11: 2688
C12: 1 | D12: 44986 | E12: 319 | F12: Neelam | G12: 150 | H12: 214 | L12: 150
C13: 2 | D13: 44986 | E13: 321 | F13: Giriraj | G13: 3000 | H13: 155 | I13: 3000
C14: 3 | D14: 44987 | E14: RR | F14: Patidar | G14: 1000 | H14: 214 | L14: 1000
C15: 4 | D15: 44989 | E15: 70 GTC | F15: Veena | G15: 500 | H15: 225 | O15: 500
C16: 5 | D16: 44989 | E16: 71 GTC | F16: AP Bonding | G16: 2000 | H16: 213 | O16: 2000
C17: 6 | D17: 44989 | E17: 323 | F17: AP Enterprises | G17: 150 | H17: 225 | L17: 150
C18: 7 | D18: 44994 | E18: 325 | F18: Can Image | G18: 5000 | H18: 220 | O18: 5000
C19: 8 | D19: 44994 | E19: 73 GTC | F19: Fortune | G19: 250 | H19: 220 | L19: 250
C20: 9 | D20: 44995 | E20: 327 | F20: VijayRaj | G20: 225 | H20: 155 | I20: 225
C21: 10 | D21: 44996 | E21: 328 | F21: Paresh Pure Chem | G21: 500 | H21: 150 | I21: 500
C22: 11 | D22: 44998 | E22: RR | F22: Meet Sach | G22: 700 | H22: 155 | I22: 700
C23: 12 | D23: 44998 | E23: 74 GTC | F23: Aditya | G23: 1000 | H23: 218 | L23: 1000
C24: 13 | D24: 44996 | E24: 329 | F24: Kanha Trading | G24: 200 | H24: 150 | I24: 200
C25: 14 | D25: 44998 | E25: 331 | F25: Mine Chem | G25: 25 | H25: 210 | K25: 25
C26: 15 | D26: 45001 | E26: RR | F26: Meet Sach | G26: 300 | H26: 217 | L26: 300
C27: 16 | D27: 45002 | E27: 76 GTC | F27: Aditya | G27: 10000 | H27: 203 | J27: 11000
C28: 17 | D28: 45003 | E28: RR | F28: Shri Ganpatye | G28: 200 | H28: 230 | P28: 200
C29: 18 | D29: 45003 | E29: 332 | F29: Surya | G29: 2000 | H29: 220 | P29: 2000
C30: 19 | D30: 45000 | E30: 333 | F30: Divysai | G30: 250 | H30: 212 | N30: 250
C31: 20 | D31: 45005 | E31: 334 | F31: Papyrus | G31: 1250 | H31: 153 | I31: 1250
C32: 21 | D32: 45006 | E32: 335 | F32: Chemie Care | G32: 2000 | H32: 210 | N32: 2000
C33: 22 | D33: 45008 | E33: 339 | F33: Superbond | G33: 500 | H33: 200 | J33: 500
C34: 23 | D34: 45008 | E34: 340 | F34: Can Image | G34: 5000 | H34: 216 | N34: 5000
C35: 24 | D35: 45008 | E35: 78 GTC | F35: Fortune | G35: 250 | H35: 220 | L35: 250
C36: 25 | D36: 45012 | E36: 360 | F36: Paresh Pure Chem | G36: 260 | H36: 150 | I36: 250
C37: 26 | D37: 45012 | E37: 361 | F37: SKS Fine | G37: 200 | H37: 218 | N37: 200
C38: 27 | D38: 45012 | E38: 362 | F38: KDM | G38: 400 | H38: 155 | I38: 400
C39: 28 | D39: 45012 | E39: 90 GTC | F39: Aditya | G39: 1500 | H39: 215 | L39: 1500
C40: 29 | D40: 45012 | E40: 68 GTC | F40: Veena | G40: 550 | H40: 220 | M40: 50 | O40: 500
C41: 30 | F41: Paresh Pure Chem
C42: 31 | F42: Seamless
C43: 32 | F43: Gurpreet
C44: 33 | F44: Aditya
C45: 34 | F45: Meet Sach
C46: 35 | F46: Divysai
C53: TOTAL | G53: =SUM(G12:G52) -> 39360 | I53: =SUM('March 2023'!$I$12:$I$52) -> 6525 | J53: =SUM('March 2023'!$J$12:$J$52) -> 11500 | K53: =SUM('March 2023'!$K$12:$K$52) -> 25 | L53: =SUM('March 2023'!$L$12:$L$52) -> 4600 | M53: =SUM('March 2023'!$M$12:$M$52) -> 50 | N53: =SUM('March 2023'!$N$12:$N$52) -> 7450 | O53: =SUM('March 2023'!$O$12:$O$52) -> 8000 | P53: =SUM('March 2023'!$P$12:$P$52) -> 2200

Sheet April 2023
D2: April 2023 Sales in Nutsell | O2: Prime
D3: Grades | E3: Off Grade | F3: 1799 | G3: 2099 | H3: 2699 | I3: 588 | J3: 2088 | K3: 2488 | L3: 2688 | M3: TOTAL
D4: Qty | E4: ='April 2023'!$I$65 -> 86300 | F4: ='April 2023'!$J$65 -> 39475 | G4: ='April 2023'!$K$65 -> 325 | H4: ='April 2023'!$L$65 -> 3250 | I4: ='April 2023'!$M$65 -> 0 | J4: ='April 2023'!$N$65 -> 10550 | K4: ='April 2023'!$O$65 -> 5650 | L4: ='April 2023'!$P$65 -> 8000 | M4: =SUM(E4:L4) -> 153550 | O4: =SUM(F4:L4) -> 67250
D5: Avg Sales PK
D6: Profit PK
D7: Total
C11: Srl No | D11: Date | E11: Inv No | F11: Party | G11: Qty | H11: Price | I11: Off Grade | J11: 1799 | K11: 2099 | L11: 2699 | M11: 588 | N11: 2088 | O11: 2488 | P11: 2688
C12: 1 | D12: 45017 | E12: 1 | F12: SKS Fine | G12: 500 | H12: 150 | I12: 500
C13: 2 | D13: 45017 | E13: 2 | F13: Sagar Corp | G13: 1500 | H13: 145 | I13: 1500
C14: 3 | D14: 45017 | E14: 3 | F14: BSB Indus | G14: 1000 | H14: 208 | L14: 1000
C15: 4 | D15: 45017 | E15: RR | F15: Gurpreet | G15: 500 | H15: 210, 215 | K15: 250 | L15: 250
C16: 5 | D16: 45017 | E16: 1 GTC | F16: Aditya | G16: 7000 | H16: 202, 204 | J16: 5000 | O16: 2000
C17: 6 | D17: 45017 | E17: 2 GTC | F17: AP Bond | G17: 3000 | H17: 202 | J17: 3000
C18: 7 | D18: 45018 | E18: 5 | F18: Siva Chem | G18: 10000 | H18: 140 | I18: 10000
C19: 8 | D19: 45019 | E19: 6 | F19: Paresh Pure Chem | G19: 200 | H19: 148 | I19: 200
C20: 9 | D20: 45020 | E20: 8 | F20: Deepak Enterprise | G20: 1500 | H20: 208 | P20: 1500
C21: 10 | D21: 45021 | E21: 10 | F21: Seamless | G21: 100 | H21: 225 | P21: 100
C22: 11 | D22: 45021 | E22: RR | F22: Meet Sach | G22: 700 | H22: 203, 155 | I22: 300 | J22: 400
C23: 12 | D23: 45021 | E23: 11 | F23: SKS Fine | G23: 700 | H23: 150, 210 | I23: 500 | L23: 200
C24: 13 | D24: 45021 | E24: 13 | F24: Ankush Enterprise | G24: 1000 | H24: 208 | L24: 1000
C25: 14 | D25: 45021 | E25: 15 | F25: Jai Aravali | G25: 5000 | H25: 201 | J25: 5000
C26: 15 | D26: 45021 | E26: 16 | F26: Fortune | G26: 500 | H26: 220 | L26: 500
C27: 16 | D27: 45022 | E27: 18 | F27: Divysai | G27: 200 | H27: 204 | O27: 200
C28: 17 | D28: 45022 | E28: 19 | F28: Rajasthan Det | G28: 1000 | H28: 135 | I28: 1000
C29: 18 | D29: 45022 | E29: 21 | F29: Jai Aravali | G29: 5000 | H29: 201 | J29: 5000
C30: 19 | D30: 45023 | E30: 3 GTC | F30: Aditya | G30: 5000 | H30: 203 | N30: 3000 | O30: 2000
C31: 20 | D31: 45023 | E31: 22 | F31: BSB Indus | G31: 3000 | H31: 130 | I31: 3000
C32: 21 | D32: 45023 | E32: 23 | F32: BSB Indus | G32: 1000 | H32: 230 | P32: 1000
C33: 22 | D33: 45024 | E33: 24 | F33: Paresh Pure Chem | G33: 460 | H33: 148 | I33: 460
C34: 23 | D34: 45024 | E34: 25 | F34: Mangalam | G34: 200 | H34: 150 | I34: 200
C35: 24 | D35: 45024 | E35: 26 | F35: BSB Indus | G35: 500 | H35: 140 | I35: 500
C36: 25 | D36: 45024 | E36: 27 | F36: Fortune | G36: 100 | H36: 230 | P36: 100
C37: 26 | D37: 45026 | E37: 29 | F37: Alpha Resources | G37: 500 | H37: 202 | J37: 500
C38: 27 | D38: 45027 | E38: 31 | F38: Siva Chem | G38: 10000 | H38: 140 | I38: 10000
C39: 28 | D39: 45030 | E39: 33 | F39: Divysai | G39: 200 | H39: 206 | O39: 200
C40: 29 | D40: 45030 | E40: RR | F40: Shri Ganpatye | G40: 200 | H40: 230 | P40: 200
C41: 30 | D41: 45027 | E41: 7 | F41: Rudolf | G41: 26000 | H41: 180.4 | I41: 26000
C42: 31 | D42: 45031 | E42: 34 | F42: Sagar Corp | G42: 200 | H42: 145 | I42: 200
C43: 32 | D43: 45031 | E43: RR | F43: Meet Sach | G43: 300 | H43: 213 | L43: 300
C44: 33 | D44: 45031 | E44: 35 | F44: Paramount | G44: 11300 | H44: 140 | I44: 11300
C45: 34 | D45: 45033 | E45: 36 | F45: Indokem | G45: 5000 | H45: 205 | J45: 5000
C46: 35 | D46: 45033 | E46: 37 | F46: Giriraj | G46: 100 | H46: 136 | I46: 100
C47: 36 | D47: 45033 | E47: 38 | F47: Giriraj | G47: 100 | H47: 220 | P47: 100
C48: 37 | D48: 45033 | E48: 5 GTC | F48: Veena | G48: 625 | H48: 204, 215, 218 | J48: 75 | K48: 50 | O48: 500
C49: 38 | D49: 45034 | E49: 6 GTC | F49: AP Bond | G49: 2000 | H49: 200 | J49: 2000
C50: 39 | D50: 45034 | E50: 7 GTC | F50: Aditya | G50: 2000 | H50: 202 | N50: 2000
C51: 40 | D51: 45034 | E51: 40 | F51: Indokem | G51: 25 | H51: 215 | K51: 25
C52: 41 | D52: 45034 | E52: 41 | F52: Can Image | G52: 5000 | H52: 216 | N52: 5000
C53: 42 | D53: 45035 | E53: 42 | F53: Divysai | G53: 500 | H53: 206 | O53: 500
C54: 43 | D54: 45035 | E54: RR | F54: Meet Sach | G54: 500 | H54: 150 | I54: 500
C55: 44 | D55: 45037 | E55: 43 | F55: Chandan | G55: 3000 | H55: 150 | I55: 3000
C56: 45 | D56: 45040 | E56: 45 | F56: Rally Chem | G56: 8000 | H56: 132 | I56: 8000
C57: 46 | D57: 45040 | E57: 47 | F57: Surya | G57: 500 | H57: 205 | J57: 500
C58: 47 | D58: 45043 | E58: 48 | F58: Can Image | G58: 550 | H58: 216 | N58: 550
C59: 48 | D59: 45043 | E59: 49 | F59: Mine Chem | G59: 40 | H59: 150 | I59: 40
C60: 49 | D60: 45043 | E60: 50 | F60: Siva Chem | G60: 1000 | H60: 145 | I60: 1000
C61: 50 | D61: 45043 | E61: 51 | F61: Indokem | G61: 10000 | H61: 204 | J61: 10000
C62: 51 | D62: 45044 | E62: 52 | F62: Dhawan | G62: 13000 | H62: 132, 203 | I62: 8000 | P62: 5000
C63: 52 | D63: 45044 | E63: 53 | F63: Divysai | G63: 250 | H63: 199 | O63: 250
C64: 53 | D64: 45045 | E64: 11 GTC | F64: Aditya | G64: 3000 | H64: 193 | J64: 3000
C65: TOTAL | G65: =SUM(G12:G64) -> 153550 | I65: =SUM('April 2023'!$I$12:$I$64) -> 86300 | J65: =SUM('April 2023'!$J$12:$J$64) -> 39475 | K65: =SUM('April 2023'!$K$12:$K$64) -> 325 | L65: =SUM('April 2023'!$L$12:$L$64) -> 3250 | M65: =SUM('April 2023'!$M$12:$M$64) -> 0 | N65: =SUM('April 2023'!$N$12:$N$64) -> 10550 | O65: =SUM('April 2023'!$O$12:$O$64) -> 5650 | P65: =SUM('April 2023'!$P$12:$P$64) -> 8000

Sheet May 2023
D3: May 2023 Sales in Nutsell | O3: Prime | P3: Off Grade | Q3: Total
D4: Grades | E4: Off Grade | F4: 1799 | G4: 2099 | H4: 2699 | I4: 588 | J4: 2088 | K4: 2488 | L4: 2688 | M4: TOTAL
D5: Qty | E5: ='May 2023'!$I$69 -> 33780 | F5: ='May 2023'!$J$69 -> 10000 | G5: ='May 2023'!$K$69 -> 0 | H5: ='May 2023'!$L$69 -> 8800 | I5: ='May 2023'!$M$69 -> 3500 | J5: ='May 2023'!$N$69 -> 13475 | K5: ='May 2023'!$O$69 -> 14550 | L5: ='May 2023'!$P$69 -> 5100 | M5: =SUM(E5:L5) -> 89205 | O5: =SUM(F5:L5) -> 55425 | P5: =E5 -> 33780 | Q5: =SUM(O5,P5) -> 89205
D6: Avg Sales PK
D7: Profit PK
D8: Total
C12: Srl No | D12: Date | E12: Inv No | F12: Party | G12: Qty | H12: Price | I12: Off Grade | J12: 1799 | K12: 2099 | L12: 2699 | M12: 588 | N12: 2088 | O12: 2488 | P12: 2688 | S12: Off Grade Stocks And Sales
C13: 1 | D13: 45049 | E13: 13 GTC | F13: Doshi | G13: 1500 | H13: 196 | P13: 1500 | S13: Srl No. | T13: Date | U13: Details | V13: Qty | W13: New Stock | X13: Qty | Y13: Total | Z13: Date Sales | AA13: Party | AB13: Qty | AC13: Product | AD13: Bal Stock
C14: 2 | D14: 45048 | E14: 57 | F14: Doshi | G14: 1500 | H14: 135 | I14: 1500 | S14: 1 | T14: 45060 | U14: Lot of 50 MT | V14: 500 | Z14: 45064 | AA14: Siva Chem | AB14: 8500 | AC14: Siva Chem | AD14: nil
C15: 3 | D15: 45049 | E15: 59 | F15: Papyrus | G15: 500 | H15: 145 | I15: 500 | S15: 2 | T15: 45060 | U15: Eco Ind | V15: 2500 | Z15: 45064 | AA15: Siva Chem | AB15: 1000 | AC15: 325 usa | AD15: 27000
C16: 4 | D16: 45049 | E16: 60,61 | F16: Chandan | G16: 200 | H16: 150, 206 | I16: 100 | P16: 100 | S16: 3 | T16: 45060 | U16: Germany | V16: 52000 | Z16: 45064 | AA16: Siva Chem | AB16: 1000 | AC16: Germany | AD16: 51000
C17: 5 | D17: 45049 | E17: 62 | F17: Fortune | G17: 250 | H17: 210 | L17: 250 | S17: 4 | T17: 45060 | U17: Japan Crab | V17: 8000 | Z17: 45064 | AA17: Siva Chem | AB17: 3500 | AC17: Japan | AD17: 4500
C18: 6 | D18: 45050 | E18: 64 | F18: Vrinda | G18: 2000 | H18: 140 | I18: 2000 | S18: 5 | T18: 45060 | U18: Siva Chem | V18: 8500 | Z18: 45065 | AA18: Sagar Corp | AB18: 1000 | AC18: 13/5 USA | AD18: 36500
C19: 7 | D19: 45050 | E19: RR | F19: Meet Sach | G19: 500 | H19: 197 | J19: 500 | S19: 6 | T19: 45060 | U19: 523 USA | V19: 5000 | Z19: 45065 | AA19: Paresh Pure | AB19: 1200 | AC19: 13/5 USA | AD19: 35300
C20: 8 | D20: 45050 | E20: 65 | F20: Kanha | G20: 200 | H20: 135 | I20: 200 | S20: 7 | T20: 45060 | U20: 325 USA | V20: 27000 | Z20: 45065 | AA20: KDM | AB20: 700 | AC20: 13/5 USA | AD20: 34600
C21: 9 | D21: 45051 | E21: 66 | F21: Sagar Dye | G21: 1000 | H21: 193 | O21: 1000 | S21: 8 | T21: 45060 | U21: 13/5 USA | V21: 37500 | Z21: 45066 | AA21: Paresh Pure | AB21: 500 | AC21: Germany | AD21: 50500
C22: 10 | D22: 45051 | E22: 67 | F22: Raj Chem | G22: 2000 | H22: 200 | L22: 2000 | S22: 9 | T22: 45077 | U22: USA Crystal | V22: 16293 | Z22: 45077 | AA22: Jay, SKR, Mine | AB22: 480 | AC22: Misc
C23: 11 | D23: 45051 | E23: 14 GTC | F23: Aditya | G23: 1500 | H23: 206 | M23: 1500
C24: 12 | D24: 45051 | E24: 68 | F24: PCL | G24: 1000 | H24: 205 | P24: 1000
C25: 13 | D25: 45051 | E25: 15 GTC | F25: Surya | G25: 2000 | H25: 220 | P25: 2000
C26: 14 | D26: 45051 | E26: 69 | F26: Siva Chem | G26: 10000 | H26: 140 | I26: 10000
C27: 15 | D27: 45054 | E27: 71 | F27: Ankush | G27: 1000 | H27: 203 | M27: 1000
C28: 16 | D28: 45054 | E28: 72 | F28: Mine Chem | G28: 600 | H28: 137 | I28: 600
C29: 17 | D29: 45054 | E29: 73 | F29: SKS Fine | G29: 700 | H29: 140, 204 | I29: 500 | O29: 200
C30: 18 | D30: 45055 | E30: GTC 18 | F30: AP Bond | G30: 4000 | H30: 196 | O30: 4000
C31: 19 | D31: 45055 | E31: GTC 19 | F31: Aditya | G31: 5000 | H31: 198, 202, 203 | L31: 2000 | N31: 2000 | O31: 1000
C32: 20 | D32: 45057 | E32: RR | F32: Shri Ganpatye | G32: 250 | H32: 215, 210 | L32: 50 | P32: 200
C33: 21 | D33: 45057 | E33: GTC 20 | F33: Veena | G33: 500 | H33: 204 | O33: 500
C34: 22 | D34: 45054 | E34: 74 | F34: AP Enterprise | G34: 200 | H34: 220 | P34: 200
C35: 23 | D35: 45057 | E35: 75 | F35: Indokem | G35: 5000 | H35: 204 | J35: 5000
C36: 24 | D36: 45057 | E36: RR | F36: Meet Sach | G36: 500 | H36: 144 | I36: 500 | V36: =SUM(V14:V35) -> 157293 | AB36: =SUM(AB14:AB35) -> 17880 | AD36: =SUM(V36-AB36) -> 139413
C37: 25 | D37: 45061 | E37: 76 | F37: Divysai | G37: 200 | H37: 195 | O37: 200
C38: 26 | D38: 45062 | E38: 77 | F38: Sagar Dye | G38: 100 | H38: 197 | O38: 100
C39: 27 | D39: 45063 | E39: 79 | F39: Fortune | G39: 500 | H39: 210 | L39: 500
C40: 28 | D40: 45064 | E40: 81 | F40: Sagar Dye | G40: 500 | H40: 193 | O40: 500
C41: 29 | D41: 45064 | E41: 82 | F41: Siva Chem | G41: 8500 | H41: 140 | I41: 8500
C42: 30 | D42: 45064 | E42: 83 | F42: Siva Chem | G42: 1000 | H42: 145 | I42: 1000
C43: 31 | D43: 45064 | E43: 84 | F43: Siva Chem | G43: 4500 | H43: 140 | I43: 4500
C44: 32 | D44: 45065 | E44: 86 | F44: Seamless | G44: 100 | H44: 225 | P44: 100
C45: 33 | D45: 45065 | E45: 87 | F45: Sagar Corp | G45: 1000 | H45: 135 | I45: 1000
C46: 34 | D46: 45065 | E46: 88 | F46: Paresh Pure | G46: 1200 | H46: 143 | I46: 1200
C47: 35 | D47: 45065 | E47: RR | F47: Meet Sach | G47: 525 | H47: 195, 205 | J47: 500 | N47: 25
C48: 36 | D48: 45065 | E48: RR | F48: Patidar | G48: 1000 | H48: 203 | L48: 1000
C49: 37 | D49: 45065 | E49: 90 | F49: KDM | G49: 700 | H49: 138 | I49: 700
C50: 38 | D50: 45066 | E50: 96 | F50: Mine Chem | G50: 100 | H50: 200 | N50: 100
C51: 39 | D51: 45066 | E51: 97 | F51: Paresh Pure | G51: 500 | H51: 138 | I51: 500
C52: 40 | D52: 44979 | E52: GTC 24 | F52: Aditya | G52: 2000 | H52: 190 192 | L52: 1000 | O52: 1000
C53: 41 | D53: 45068 | E53: 99 | F53: Jay Organics | G53: 100 | H53: 140 | I53: 100
C54: 42 | D54: 45070 | E54: 100 | F54: KDM | G54: 250 | H54: 194 | O54: 250
C55: 43 | D55: 45070 | E55: 101 | F55: Chandan | G55: 500 | H55: 192, 198 | J55: 250 | N55: 250
C56: 44 | D56: 45070 | E56: 102 | F56: SKR | G56: 40 | H56: 136 | I56: 40
C57: 45 | D57: 45071 | E57: 103 | F57: Sagar Dye | G57: 800 | H57: 190 | O57: 800
C58: 46 | D58: 45071 | E58: 106 | F58: Popular Chemical | G58: 250 | H58: 194 | J58: 250
C59: 47 | D59: 45072 | E59: 107 | F59: Divysai | G59: 500 | H59: 190 | O59: 500
C60: 48 | D60: 45072 | E60: 108 | F60: Mine Chem | G60: 300 | H60: 137 | I60: 300
C61: 49 | D61: 45072 | E61: 109 | F61: Mine Chem | G61: 1000 | H61: 192 | N61: 1000
C62: 50 | D62: 45074 | E62: 110 | F62: CanImage | G62: 5000 | H62: 212 | N62: 5000
C63: 51 | D63: 45075 | E63: 111 | F63: Aditya | G63: 5000 | H63: 178, 190 | J63: 3000 | L63: 2000
C64: 52 | D64: 45075 | E64: GTC 25 | F64: AP Bond | G64: 9000 | H64: 187, 188, 199 | M64: 1000 | N64: 4000 | O64: 4000
C65: 53 | D65: 45076 | E65: 112 | F65: Aadeshwar | G65: 500 | H65: 173 | J65: 500
C66: 54 | D66: 45076 | E66: GTC 26 | F66: Veena | G66: 500 | H66: 199 | O66: 500
C67: 55 | D67: 45077 | E67: 113, 114 | F67: Mine Chem | G67: 1140 | H67: 137, 188 | I67: 40 | N67: 1100
C69: TOTAL | G69: =SUM(G13:G68) -> 89205 | I69: =SUM('May 2023'!$I$13:$I$68) -> 33780 | J69: =SUM('May 2023'!$J$13:$J$68) -> 10000 | K69: =SUM('May 2023'!$K$13:$K$68) -> 0 | L69: =SUM('May 2023'!$L$13:$L$68) -> 8800 | M69: =SUM('May 2023'!$M$13:$M$68) -> 3500 | N69: =SUM('May 2023'!$N$13:$N$68) -> 13475 | O69: =SUM('May 2023'!$O$13:$O$68) -> 14550 | P69: =SUM('May 2023'!$P$13:$P$68) -> 5100
I71: =SUM('May 2023'!$I$69:'May 2023'!$P$69) -> 89205

Sheet June 2023
D4: May 2023 Sales in Nutsell | O4: Prime | P4: Off Grade | Q4: Total
D5: Grades | E5: Off Grade | F5: 1799 | G5: 2099 | H5: 2699 | I5: 588 | J5: 2088 | K5: 2488 | L5: 2688 | M5: TOTAL
D6: Qty | E6: ='June 2023'!$I$84 -> 37820 | F6: ='June 2023'!$J$84 -> 12975 | G6: ='June 2023'!$K$84 -> 0 | H6: ='June 2023'!$L$84 -> 6875 | I6: ='June 2023'!$M$84 -> 1050 | J6: ='June 2023'!$N$84 -> 3025 | K6: ='June 2023'!$O$84 -> 4400 | L6: ='June 2023'!$P$84 -> 10350 | M6: =SUM(E6:L6) -> 76495 | O6: =SUM(F6:L6) -> 38675 | P6: =E6 -> 37820 | Q6: =SUM(O6,P6) -> 76495
D7: Avg Sales PK
D8: Profit PK
D9: Total
C13: Srl No | D13: Date | E13: Inv No | F13: Party | G13: Qty | H13: Price | I13: Off Grade | J13: 1799 | K13: 2099 | L13: 2699 | M13: 588 | N13: 2088 | O13: 2488 | P13: 2688 | S13: Off Grade Stocks And Sales
C14: 1 | D14: 45078 | E14: 116 | F14: Popular Chemical | G14: 500 | H14: 189 | J14: 500 | S14: New Input
C15: 2 | D15: 45078 | E15: 118 | F15: SKS Fine | G15: 200 | H15: 201 | O15: 200 | S15: Srl No. | T15: Date | U15: Details | V15: Qty
C16: 3 | D16: 45078 | E16: 119 | F16: Divysai | G16: 400 | H16: 189 | O16: 400 | S16: 1 | T16: 45122 | U16: Return From Dhawan | V16: 7200
C17: 4 | D17: 45079 | E17: 120 | F17: Surya | G17: 2000 | H17: 215 | P17: 2000 | S17: 2
C18: 5 | D18: 45079 | E18: 121 | F18: Mangalam | G18: 245 | H18: 135, 190 | I18: 120 | O18: 125 | S18: 3
C19: 6 | D19: 45079 | E19: 122 | F19: Akshat | G19: 145 | H19: 135, 200 | I19: 120 | L19: 25 | S19: 4
C20: 7 | D20: 45079 | E20: 124 | F20: Uma Agencies | G20: 1000 | H20: 176 | J20: 1000 | S20: 5
C21: 8 | D21: 45079 | E21: 125 | F21: A to Z | G21: 1000 | H21: 174 | J21: 1000 | S21: 6
C22: 9 | D22: 45079 | E22: 126 | F22: Shubham Corp | G22: 500 | H22: 197 | P22: 500 | S22: 7
C23: 10 | D23: 45079 | E23: RR | F23: Meet Sach | G23: 300 | H23: 135 | I23: 300 | S23: 8
C24: 11 | D24: 45079 | E24: RR | F24: Shri Ganpatye | G24: 250 | H24: 206 | O24: 50 | P24: 200
C25: 12 | D25: 45080 | E25: 132 | F25: Pappyrus | G25: 460 | H25: 140, 204 | I25: 360 | L25: 100 | S25: Total New Input:- | V25: =SUM(V16:V23) -> 7200
C26: 13 | D26: 45082 | E26: 134 | F26: Bio Chem | G26: 200 | H26: 199 | N26: 200 | S26: Old Stock C/F:- | V26: 139413
C27: 14 | D27: 45082 | E27: 135 | F27: Paramount | G27: 5000 | H27: 125 | I27: 5000 | S27: Total Stocks New & Old :- | V27: =SUM(V25,V26) -> 146613
C28: 15 | D28: 45083 | E28: 136 | F28: Fortune | G28: 625 | H28: 205, 220 | L28: 500 | P28: 125 | S28: LESS SALES: (as per sales sheet) | V28: ='June 2023'!$I$84 -> 37820
C29: 16 | D29: 45083 | E29: 137 | F29: Dipali | G29: 2000 | H29: 187 | P29: 2000
C30: 17 | D30: 45083 | E30: 138 | F30: Siva Chem | G30: 1000 | H30: 144 | I30: 1000 | S30: NET QTY AVAILABLE: | V30: =SUM(V27-V28) -> 108793
C31: 18 | D31: 45083 | E31: 139 | F31: Giriraj | G31: 1000 | H31: 192, 202 | O31: 600 | P31: 400
C32: 19 | D32: 45083 | E32: 140 | F32: Guruji | G32: 1000 | H32: 132, 192 | I32: 1000 | P32: 500
C33: 20 | D33: 45083 | E33: 141 | F33: Popular Chemical | G33: 50 | H33: 180 | J33: 50
C34: 21 | D34: 45083 | E34: 142 | F34: Pearl | G34: 1000 | H34: 182 | O34: 1000
C35: 22 | D35: 45083 | E35: 143 | F35: Chandan | G35: 5000 | H35: 132 | I35: 5000
C36: 23 | D36: 45085 | E36: 144 | F36: Mine Chem | G36: 2000 | H36: 171.5 | J36: 2000
C37: 24 | D37: 45085 | E37: 145 | F37: Om Shakti | G37: 500 | H37: 169 | J37: 500
C38: 25 | D38: 45085 | E38: 146 | F38: Om Shakti | G38: 125 | H38: 135, 195 | I38: 100 | L38: 25
C39: 26 | D39: 45085 | E39: GTC 27 | F39: AP Bond | G39: 1000 | H39: 197 | M39: 1000
C40: 27 | D40: 45086 | E40: 148 | F40: Target | G40: 300 | H40: 130 | I40: 300
C41: 28 | D41: 45086 | E41: 149 | F41: Siva Chem | G41: 500 | H41: 188 | O41: 500
C42: 29 | D42: 45087 | E42: 150 | F42: Mine Chem | G42: 100 | H42: 137 | I42: 100
C43: 30 | D43: 45089 | E43: 152 | F43: SKR | G43: 3000 | H43: 125 | I43: 3000
C44: 31 | D44: 45089 | E44: 153 | F44: Kanha | G44: 300 | H44: 135 | I44: 300
C45: 32 | D45: 45089 | E45: 154 | F45: Mine Chem | G45: 25 | H45: 185 | O45: 25
C46: 33 | D46: 45090 | E46: 155 | F46: Deepak Enterprise | G46: 2000 | H46: 189 | P46: 2000
C47: 34 | D47: 45090 | E47: 156 | F47: Sagar Dye | G47: 300 | H47: 181 | O47: 300
C48: 35 | D48: 45091 | E48: 159 | F48: Sagar Corp | G48: 2000 | H48: 132 | I48: 2000
C49: 36 | D49: 45091 | E49: RR | F49: Meet Sach | G49: 1000 | H49: 132, 182 | I49: 500 | J49: 500
C50: 37 | D50: 45093 | E50: 164 | F50: Divysai | G50: 500 | H50: 180 | O50: 500
C51: 38 | D51: 45094 | E51: 30 GTC | F51: Veena | G51: 500 | H51: 196 | O51: 500
C52: 39 | D52: 45094 | E52: 165 | F52: Akshat | G52: 145 | H52: 135, 200 | I52: 120 | L52: 25
C53: 40 | D53: 45096 | E53: 166 | F53: Om Shakti | G53: 500 | H53: 128 | I53: 500
C54: 41 | D54: 45097 | E54: 168 | F54: Gaywala | G54: 50 | H54: 189 | M54: 50
C55: 42 | D55: 45097 | E55: 169 | F55: Aditya | G55: 2000 | H55: 178.5 | N55: 2000
C56: 43 | D56: 45097 | E56: 171 | F56: Paresh Pure | G56: 500 | H56: 135 | I56: 500
C57: 44 | D57: 45098 | E57: 172 | F57: Suncol | G57: 600 | H57: 183 | L57: 600
C58: 45 | D58: 45098 | E58: 173 | F58: Mine Chem | G58: 125 | H58: 168 | J58: 125
C59: 46 | D59: 45099 | E59: 174 | F59: Siva Chem | G59: 5000 | H59: 135 | I59: 5000
C60: 47 | D60: 45099 | E60: 175 | F60: Siva Chem | G60: 100 | H60: 120
C61: 48 | D61: 45099 | E61: 176 | F61: Mine Chem | G61: 1000 | H61: 164 | J61: 1000
C62: 49 | D62: 45100 | E62: 177 | F62: BSB Indus | G62: 5000 | H62: 122 | I62: 5000
C63: 50 | D63: 45100 | E63: 178 | F63: BSB Indus | G63: 2000 | H63: 180 | J63: 300 | L63: 500 | N63: 700 | P63: 500
C64: 51 | D64: 45100 | E64: 179 | F64: SKS Fine | G64: 500 | H64: 130 | I64: 500
C65: 52 | D65: 45101 | E65: 180 | F65: Popular Chemical | G65: 25 | H65: 182 | N65: 25
C66: 53 | D66: 45101 | E66: RR | F66: Shri Ganpatye | G66: 100 | H66: 200 | N66: 100
C67: 54 | D67: 45103 | E67: 181 | F67: Siva Chem | G67: 5000 | H67: 135 | I67: 5000
C68: 55 | D68: 45103 | E68: 182 | F68: Vasudha Colors | G68: 1000 | H68: 189 | P68: 1000
C69: 56 | D69: 45103 | E69: RR | F69: Meet Sach | G69: 100 | H69: 195 | L69: 100
C70: 57 | D70: 45103 | E70: 183 | F70: Fortune | G70: 500 | H70: 195 | L70: 500
C71: 58 | D71: 45104 | E71: 184 | F71: Surya | G71: 1000 | H71: 175 | J71: 1000
C72: 59 | D72: 45104 | E72: 185 | F72: Aditya | G72: 7000 | H72: 155, 176 | J72: 5000 | L72: 2000
C73: 60 | D73: 45105 | E73: 186 | F73: Seamless | G73: 125 | H73: 205 | P73: 125
C74: 61 | D74: 45105 | E74: 187 | F74: SKS Fine | G74: 200 | H74: 185 | O74: 200
C75: 62 | D75: 45105 | E75: 188 | F75: PCL | G75: 1000 | H75: 184 | P75: 1000
C76: 63 | D76: 44985 | E76: 189 | F76: Guruji | G76: 2000 | H76: 125 | I76: 2000
C77: 64 | D77: 45106 | E77: 190 | F77: Veekay | G77: 2500 | H77: 179 | L77: 2500
C78: 5
C79: 66
C80: 67
C81: 68
C82: 69
C83: 70
C84: TOTAL | G84: =SUM(G14:G83) -> 76095 | I84: =SUM('June 2023'!$I$14:$I$83) -> 37820 | J84: =SUM('June 2023'!$J$14:$J$83) -> 12975 | K84: =SUM('June 2023'!$K$14:$K$83) -> 0 | L84: =SUM('June 2023'!$L$14:$L$83) -> 6875 | M84: =SUM('June 2023'!$M$14:$M$83) -> 1050 | N84: =SUM('June 2023'!$N$14:$N$83) -> 3025 | O84: =SUM('June 2023'!$O$14:$O$83) -> 4400 | P84: =SUM('June 2023'!$P$14:$P$83) -> 10350
I86: =SUM('June 2023'!$I$84:'June 2023'!$P$84) -> 76495

Sheet July 2023
D4: July 2023 Sales in Nutsell | O4: Prime | P4: Off Grade | Q4: Total
D5: Grades | E5: Off Grade | F5: 1799 | G5: 2099 | H5: 2699 | I5: 588 | J5: 2088 | K5: 2488 | L5: 2688 | M5: 3099 | N5: TOTAL
D6: Qty | E6: ='July 2023'!$I$84 -> 22880 | F6: ='July 2023'!$J$84 -> 16775 | G6: ='July 2023'!$K$84 -> 0 | H6: ='July 2023'!$L$84 -> 12675 | I6: ='July 2023'!$M$84 -> 1125 | J6: ='July 2023'!$N$84 -> 18225 | K6: ='July 2023'!$O$84 -> 15925 | L6: ='July 2023'!$P$84 -> 8150 | M6: ='July 2023'!$Q$84 -> 1650 | N6: =SUM(E6:M6) -> 97405 | O6: =SUM(F6:M6) -> 74525 | P6: =E6 -> 22880 | Q6: =SUM(O6,P6) -> 97405
D7: Avg Sales PK
D8: Profit PK
D9: Total
C13: Srl No | D13: Date | E13: Inv No | F13: Party | G13: Qty | H13: Price | I13: Off Grade | J13: 1799 | K13: 2099 | L13: 2699 | M13: 588 | N13: 2088 | O13: 2488 | P13: 2688 | Q13: 3099 | T13: Off Grade Stocks And Sales
C14: 1 | D14: 45108 | E14: 195 | F14: Divysai | G14: 250 | H14: 169 | O14: 250 | T14: New Input
C15: 2 | D15: 45108 | E15: 196 | F15: Vrinda Chem | G15: 3000 | H15: 167 | O15: 3000 | T15: Srl No. | U15: Date | V15: Details | W15: Qty
C16: 3 | D16: 45108 | E16: RR | F16: Patidar Adh | G16: 1000 | H16: 179 | L16: 500 | P16: 500 | T16: 1 | U16: 45122 | V16: JP Impex | W16: 17001
C17: 4 | D17: 45110 | E17: 197 | F17: Mine Chem | G17: 1000 | H17: 151 | J17: 1000 | T17: 2 | U17: 45135 | V17: JP Impex | W17: 18607
C18: 5 | D18: 45112 | E18: 200 | F18: Sagar Dye | G18: 650 | H18: 172 | O18: 650 | T18: 3
C19: 6 | D19: 45112 | E19: RR | F19: Meet Sach | G19: 200 | H19: 162 | J19: 200 | T19: 4
C20: 7 | D20: 45113 | E20: 202 | F20: Kanha | G20: 1000 | H20: 168 | N20: 1000 | T20: 5
C21: 8 | D21: 45113 | E21: 203 | F21: Aditya | G21: 3125 | H21: 167, 162 | M21: 1125 | O21: 2000 | T21: 6
C22: 9 | D22: 45113 | E22: 204 | F22: Akshat | G22: 145 | H22: 130, 185 | I22: 120 | L22: 25 | T22: 7
C23: 10 | D23: 45113 | E23: 205 | F23: KDM | G23: 100 | H23: 128 | I23: 100 | T23: 8
C24: 11 | D24: 45114 | E24: 206 | F24: Popular Chemical | G24: 150 | H24: 172 | P24: 150
C25: 12 | D25: 45114 | E25: 207 | F25: Kanha | G25: 300 | H25: 130 | I25: 300 | T25: Total New Input:- | W25: =SUM(W16:W23) -> 35608
C26: 13 | D26: 45115 | E26: 208 | F26: Mine Chem | G26: 20 | H26: 135 | I26: 20 | T26: Old Stock C/F:- | W26: 108793
C27: 14 | D27: 45115 | E27: GTC 31 | F27: Veena | G27: 625 | H27: 170 | O27: 625 | T27: Total Stocks New & Old :- | W27: =SUM(W25,W26) -> 144401
C28: 15 | D28: 45116 | E28: 209 | F28: Can Image | G28: 5000 | H28: 192 | N28: 5000 | T28: LESS SALES: (as per sales sheet) | W28: ='July 2023'!$I$84 -> 22880
C29: 16 | D29: 45117 | E29: 210 | F29: Fortune | G29: 500 | H29: 190 | L29: 500
C30: 17 | D30: 45117 | E30: 211 | F30: Aditya | G30: 5000 | H30: 148 | J30: 5000 | T30: NET QTY AVAILABLE: | W30: =SUM(W27-W28) -> 121521
C31: 18 | D31: 45118 | E31: 212 | F31: Chandan | G31: 2000 | H31: 158 | O31: 2000
C32: 19 | D32: 45118 | E32: 213 | F32: Mangalam | G32: 340 | H32: 125, 157, 170 | I32: 140 | L32: 150 | O32: 50
C33: 20 | D33: 45119 | E33: 214 | F33: Akshat Chem | G33: 1000 | H33: 162 | P33: 1000
C34: 21 | D34: 45120 | E34: 215 | F34: Paresh Pure | G34: 1025 | H34: 159 | N34: 1025
C35: 22 | D35: 45122 | E35: 218 | F35: Surya | G35: 2000 | H35: 185 | P35: 2000
C36: 23 | D36: 45124 | E36: 219 | F36: Jupiter | G36: 300 | H36: 154 | O36: 300
C37: 24 | D37: 45124 | E37: 220 | F37: Mine Chem | G37: 200 | H37: 122 | I37: 200
C38: 25 | D38: 45125 | E38: 221 | F38: Siva Chem | G38: 25 | H38: 150 | J38: 25
C39: 26 | D39: 45125 | E39: 222 | F39: Guruji | G39: 2500 | H39: 120, 165 | I39: 2000 | P39: 500
C40: 27 | D40: 45125 | E40: 223 | F40: Mine Chem | G40: 1000 | H40: 147.5 | J40: 1000
C41: 28 | D41: 45125 | E41: 224 | F41: Aditya | G41: 9000 | H41: 144, 155, 154 | J41: 5000 | N41: 2000 | O41: 2000
C42: 29 | D42: 45128 | E42: 227 | F42: Kanha | G42: 500 | H42: 158 | N42: 500
C43: 30 | D43: 45128 | E43: 228 | F43: Vasudha Colors | G43: 1000 | H43: 175 | P43: 1000
C44: 31 | D44: 45128 | E44: 229 | F44: Aditya | G44: 3000 | H44: 154 | L44: 3000
C45: 32 | D45: 45128 | E45: 230 | F45: Siva Chem | G45: 10000 | H45: 119 | I45: 10000
C46: 33 | D46: 45128 | E46: 231 | F46: Pearl | G46: 500 | H46: 150 | N46: 500
C47: 34 | D47: 45128 | E47: RR | F47: Meet Sach | G47: 250 | H47: 154 | J47: 250
C48: 35 | D48: 45131 | E48: 234 | F48: Sagar Corp | G48: 2700 | H48: 151 | N48: 2700
C49: 36 | D49: 45131 | E49: 235 | F49: Sagar Dye | G49: 350 | H49: 155 | O49: 350
C50: 37 | D50: 45131 | E50: 237 | F50: Kunal Dye | G50: 1500 | H50: 155 | L50: 1500
C51: 38 | D51: 45131 | E51: 238 | F51: KDM | G51: 1000 | H51: 157 | O51: 1000
C52: 39 | D52: 45131 | E52: 239 | F52: Siva Chem | G52: 500 | H52: 154 | O52: 500
C53: 40 | D53: 45132 | E53: 240 | F53: Divysai | G53: 500 | H53: 156 | N53: 500
C54: 41 | D54: 45132 | E54: RR | F54: Patidar Adh | G54: 1000 | H54: 159 | L54: 1000
C55: 42 | D55: 45132 | E55: 241 | F55: Mine Chem | G55: 300 | H55: 152 | O55: 300
C56: 43 | D56: 45134 | E56: 243 | F56: Paresh Pure | G56: 1000 | H56: 123, 159 | I56: 500 | N56: 500
C57: 44 | D57: 45134 | E57: 244 | F57: Fortune | G57: 500 | H57: 165 | P57: 500
C58: 45 | D58: 45134 | E58: 246 | F58: A2Z | G58: 1000 | H58: 146 | J58: 1000
C59: 46 | D59: 45134 | E59: 247 | F59: Chandan | G59: 1000 | H59: 147 | J59: 1000
C60: 47 | D60: 45134 | E60: 249 | F60: SKS Fine | G60: 500 | H60: 124 | I60: 500
C61: 48 | D61: 45134 | E61: 250 | F61: Doshi | G61: 800 | H61: 146, 166 | J61: 300 | P61: 500
C62: 49 | D62: 45134 | E62: RR | F62: Shri Ganpatye | G62: 200 | H62: 190 | O62: 200
C63: 50 | D63: 45135 | E63: 253 | F63: Chemi Care | G63: 2500 | H63: 154 | N63: 2500
C64: 51 | D64: 45135 | E64: 254 | F64: Veekay | G64: 2500 | H64: 160, 165, 180 | O64: 1000 | P64: 1000 | Q64: 500
C65: 52 | D65: 45135 | E65: GTC 35 | F65: Aditya | G65: 2000 | H65: 154 | N65: 2000
C66: 53 | D66: 45135 | E66: 255 | F66: Guruji | G66: 500 | H66: 170 | Q66: 500
C67: 54 | D67: 45135 | E67: 256 | F67: Mine Chem | G67: 1150 | H67: 120, 148, 158 | I67: 100 | J67: 1000 | O67: 50
C68: 55 | D68: 45136 | E68: 257 | F68: Om Shakhi | G68: 1000 | H68: 115 | I68: 1000
C69: 56 | D69: 45136 | E69: 258 | F69: Doshi | G69: 500 | O69: 500
C70: 57 | D70: 45136 | E70: 259 | F70: Mine Chem | G70: 1600 | H70: 120 | I70: 1600
C71: 58 | D71: 45136 | E71: 260 | F71: Vrinda Chem | G71: 6000 | H71: 155 | L71: 6000
C72: 59 | D72: 45138 | E72: 262 | F72: Om Shakhi | G72: 1500 | H72: 145, 170 | J72: 1000 | Q72: 500
C73: 60 | D73: 45138 | E73: 263 | F73: Chandan | G73: 300 | H73: 162, 176 | O73: 150 | Q73: 150
C74: 61 | D74: 45138 | E74: 264 | F74: Mine Chem | G74: 300 | H74: 120 | I74: 300
C75: 62 | D75: 45138 | E75: 265 | F75: Siva Chem | G75: 6000 | H75: 119 | I75: 6000
C76: 63 | D76: 45138 | E76: 266 | F76: Sagar Corp | G76: 1000 | H76: 157 | O76: 1000
C77: 64 | D77: 45138 | E77: 268 | F77: Swastik | G77: 1000 | H77: 156 | P77: 1000
C78: 65
C79: 66
C80: 67
C81: 68
C82: 69
C83: 70
C84: TOTAL | G84: =SUM(G14:G83) -> 97405 | I84: =SUM('July 2023'!$I$14:$I$83) -> 22880 | J84: =SUM('July 2023'!$J$14:$J$83) -> 16775 | K84: =SUM('July 2023'!$K$14:$K$83) -> 0 | L84: =SUM('July 2023'!$L$14:$L$83) -> 12675 | M84: =SUM('July 2023'!$M$14:$M$83) -> 1125 | N84: =SUM('July 2023'!$N$14:$N$83) -> 18225 | O84: =SUM('July 2023'!$O$14:$O$83) -> 15925 | P84: =SUM('July 2023'!$P$14:$P$83) -> 8150 | Q84: =SUM('July 2023'!$Q$14:$Q$83) -> 1650
I86: =SUM('July 2023'!$I$84:'July 2023'!$P$84) -> 95755

Sheet Aug 2023
D6: August 2023 Sales in Nutsell | O6: Prime | P6: Off Grade | Q6: Total
D7: Grades | E7: Off Grade | F7: 1799 | G7: 2099 | H7: 2699 | I7: 588 | J7: 2088 | K7: 2488 | L7: 2688 | M7: 3099 | N7: TOTAL
D8: Qty | E8: ='Aug 2023'!$I$87 -> 16920 | F8: ='Aug 2023'!$J$87 -> 20325 | G8: ='Aug 2023'!$K$87 -> 0 | H8: ='Aug 2023'!$L$87 -> 14400 | I8: ='Aug 2023'!$M$87 -> 500 | J8: ='Aug 2023'!$N$87 -> 8525 | K8: ='Aug 2023'!$O$87 -> 10650 | L8: ='Aug 2023'!$P$87 -> 11075 | M8: ='Aug 2023'!$Q$87 -> 3375 | N8: =SUM(E8:M8) -> 85770 | O8: =SUM(F8:M8) -> 68850 | P8: =E8 -> 16920 | Q8: =SUM(O8,P8) -> 85770
D9: Avg Sales PK
D10: Profit PK
D11: Total
C15: Srl No | D15: Date | E15: Inv No | F15: Party | G15: Qty | H15: Price | I15: Off Grade | J15: 1799 | K15: 2099 | L15: 2699 | M15: 588 | N15: 2088 | O15: 2488 | P15: 2688 | Q15: 3099 | T15: Off Grade Stocks And Sales
C16: 1 | D16: 45139 | E16: 269 | F16: Ankush | G16: 1000 | H16: 154 | N16: 1000 | T16: New Input
C17: 2 | D17: 45139 | E17: 270 | F17: Agarwal | G17: 500 | H17: 153 | O17: 500 | T17: Srl No. | U17: Date | V17: Details | W17: Qty
C18: 3 | D18: 45139 | E18: 271 | F18: Kunal Dye | G18: 1500 | H18: 156 | L18: 1500 | T18: 1 | U18: 45149 | V18: IMP 19 - 2117 | W18: 20444
C19: 4 | D19: 45139 | E19: 272 | F19: Popular Chemical | G19: 1000 | H19: 159 | P19: 1000 | T19: 2
C20: 5 | D20: 45139 | E20: 273 | F20: Divysai | G20: 200 | H20: 156 | O20: 200 | T20: 3
C21: 6 | D21: 45140 | E21: 276 | F21: Popular Chemical | G21: 3000 | H21: 157 | L21: 3000 | T21: 4
C22: 7 | D22: 45140 | E22: 277 | F22: Sagar Corp | G22: 500 | H22: 157 | O22: 500 | T22: 5
C23: 8 | D23: 45141 | E23: 278 | F23: Uma Agen | G23: 2000 | H23: 145 | J23: 2000 | T23: 6
C24: 9 | D24: 45141 | E24: 279 | F24: Aadinath | G24: 500 | H24: 155 | O24: 500 | T24: 7
C25: 10 | D25: 45141 | E25: 280 | F25: Kanha | G25: 300 | H25: 125 | I25: 300 | T25: 8
C26: 11 | D26: 45142 | E26: 283 | F26: BSB Indus | G26: 1000 | H26: 148, 162, 162 | J26: 300 | N26: 500 | O26: 200
C27: 12 | D27: 45142 | E27: 284 | F27: Mine Chem | G27: 1000 | H27: 147 | J27: 1000 | T27: Total New Input:- | W27: =SUM(W18:W25) -> 20444
C28: 13 | D28: 45143 | E28: 285 | F28: Kunal Dye | G28: 2400 | H28: 158 | L28: 2400 | T28: Old Stock C/F:- | W28: 121521
C29: 14 | D29: 45143 | E29: 286 | F29: Soham | G29: 500 | H29: 160 | N29: 500 | T29: Total Stocks New & Old :- | W29: =SUM(W27,W28) -> 141965
C30: 15 | D30: 45143 | E30: 287 | F30: Fortune | G30: 500 | H30: 170 | P30: 500 | T30: LESS SALES: (as per sales sheet) | W30: ='Aug 2023'!$I$87 -> 16920
C31: 16 | D31: 45143 | E31: 288 | F31: Jay Organics | G31: 100 | H31: 130 | I31: 100
C32: 17 | D32: 45145 | E32: 289 | F32: KDM | G32: 250 | H32: 100, 165 | I32: 200 | P32: 50 | T32: NET QTY AVAILABLE: | W32: =SUM(W29-W30) -> 125045
C33: 18 | D33: 45148 | E33: 293 | F33: AP Enterprise | G33: 300 | H33: 185, 180 | P33: 275 | Q33: 75
C34: 19 | D34: 45148 | E34: 294 | F34: Mine Chem | G34: 100 | H34: 172 | P34: 100
C35: 20 | D35: 45148 | E35: 295 | F35: Pearl | G35: 2000 | H35: 153 | N35: 2000
C36: 21 | D36: 45149 | E36: 37 GTC | F36: Aditya | G36: 5000 | H36: 148.5 | J36: 5000
C37: 22 | D37: 45152 | E37: 297 | F37: Fortune | G37: 500 | H37: 170 | P37: 500
C38: 23 | D38: 45152 | E38: 298 | F38: Seamless | G38: 150 | H38: 185 | P38: 150
C39: 24 | D39: 45152 | E39: RR | F39: Shri Ganpatye | G39: 200 | H39: 190 | O39: 200
C40: 25 | D40: 45155 | E40: 38 GTC | F40: Veena | G40: 500 | H40: 170 | O40: 500
C41: 26 | D41: 45156 | E41: 300 | F41: Mine Chem | G41: 100 | H41: 152 | J41: 100
C42: 27 | D42: 45156 | E42: 301 | F42: Guruji | G42: 1000 | H42: 169 | Q42: 1000
C43: 28 | D43: 45156 | E43: 302 | F43: Giriraj | G43: 1000 | H43: 124 | I43: 1000
C44: 29 | D44: 45156 | E44: 307 | F44: Surya | G44: 4250 | H44: 185 | P44: 4250
C45: 30 | D45: 45156 | E45: 308 | F45: SKS Fine | G45: 200 | H45: 164 | N45: 200
C46: 31 | D46: 45157 | E46: 312 | F46: Jai Aravali | G46: 4500 | H46: 150 | J46: 4500
C47: 32 | D47: 45160 | E47: 315 | F47: Divysai | G47: 500 | H47: 158 | N47: 500
C48: 33 | D48: 45160 | E48: 316 | F48: Darshan | G48: 220 | H48: 125 | I48: 220
C49: 34 | D49: 45160 | E49: 318 | F49: Om Shakhi | G49: 2500 | H49: 147, 169 | J49: 1500 | Q49: 1000
C50: 35 | D50: 45161 | E50: 319 | F50: Fortune | G50: 500 | H50: 162, 170 | O50: 450 | P50: 50
C51: 35 | D51: 45161 | E51: 320 | F51: BSB Indus | G51: 1000 | H51: 152, 160, 162 | J51: 200 | N51: 600 | O51: 200
C52: 36 | D52: 45162 | E52: 321 | F52: Aditya | G52: 100 | H52: 325 | I52: 100
C53: 37 | D53: 45162 | E53: 322 | F53: KDM | G53: 1000 | H53: 159 | O53: 1000
C54: 38 | D54: 45162 | E54: 39 GTC | F54: Vrinda Chem | G54: 5000 | H54: 160 | O54: 5000
C55: 39 | D55: 45163 | E55: 323 | F55: Jai Mata Di | G55: 5000 | H55: 150.5 | J55: 5000
C56: 40 | D56: 45163 | E56: 324 | F56: SKS Fine | G56: 500 | H56: 125 | I56: 500
C57: 41 | D57: 45164 | E57: 325 | F57: Mine Chem | G57: 250 | H57: 151 | J57: 250
C58: 42 | D58: 45164 | E58: 313 | F58: Standard Chemicals | G58: 50 | H58: 155, 165 | J58: 25 | N58: 25
C59: 43 | D59: 45165 | E59: 326 | F59: Siva Chem | G59: 5000 | H59: 117 | I59: 5000
C60: 44 | D60: 45166 | E60: 327 | F60: Paresh Pure | G60: 4000 | H60: 122, 159 | I60: 1000 | N60: 3000
C61: 45 | D61: 45166 | E61: 328 | F61: Paramount | G61: 4000 | H61: 120, 172 | I61: 3200 | Q61: 800
C62: 46 | D62: 45167 | E62: 329 | F62: Reliable | G62: 1250 | H62: 152, 162, 172 | J62: 250 | O62: 500 | Q62: 500
C63: 47 | D63: 45168 | E63: 330 | F63: Doshi | G63: 1000 | H63: 120 | I63: 1000
C64: 48 | D64: 45169 | E64: 333 / 4 | F64: Rally Chem | G64: 9500 | H64: 155, 160 | L64: 7500 | P64: 2500
B65: 335 CANC | C65: 49 | D65: 45169 | E65: 340 | F65: Rally Chem | G65: 3800 | H65: 110 | I65: 3800
B66: 336 CANC | C66: 50 | D66: 45169 | E66: 339 | F66: Veekay | G66: 2000 | H66: 165, 168 | O66: 900 | P66: 1100
C67: 51 | D67: 45169 | E67: 337 | F67: Om Shakhi | G67: 500 | H67: 163 | M67: 500
C68: 52 | D68: 45169 | E68: RR | F68: Meet Products | G68: 400 | H68: 125, 158 | I68: 200 | J68: 200
C69: 53 | D69: 45169 | E69: 338 | F69: BSB Indus | G69: 800 | H69: 160, 165 | N69: 200 | P69: 600
C70: 54 | D70: 45169 | E70: 341 | F70: Kanha | G70: 300 | H70: 125 | I70: 300
C71: 55 | F71: Om Shakhi
C72: 56 | F72: Doshi
C73: 57 | F73: Mine Chem
C74: 58 | F74: Vrinda Chem
C75: 59 | F75: Om Shakhi
C76: 60 | F76: Chandan
C77: 61 | F77: Mine Chem
C78: 62 | F78: Siva Chem
C79: 63 | F79: Sagar Corp
C80: 64 | F80: Swastik
C81: 65
C82: 66
C83: 67
C84: 68
C85: 69
C86: 70
C87: TOTAL | G87: =SUM(G16:G86) -> 85220 | I87: =SUM(I16:I86) -> 16920 | J87: =SUM(J16:J86) -> 20325 | K87: =SUM(K16:K86) -> 0 | L87: =SUM(L16:L86) -> 14400 | M87: =SUM(M16:M86) -> 500 | N87: =SUM(N16:N86) -> 8525 | O87: =SUM(O16:O86) -> 10650 | P87: =SUM(P16:P86) -> 11075 | Q87: =SUM(Q16:Q86) -> 3375
I89: =SUM('Aug 2023'!$I$87:'Aug 2023'!$P$87) -> 82395

Sheet Sept 2023
D7: September 2023 Sales in Nutsell | O7: Prime | P7: Off Grade | Q7: Total
D8: Grades | E8: Off Grade | F8: 1799 | G8: 2099 | H8: 2699 | I8: 588 | J8: 2088 | K8: 2488 | L8: 2688 | M8: 3099 | N8: TOTAL
D9: Qty | E9: ='Sept 2023'!$I$88 -> 42020 | F9: ='Sept 2023'!$J$88 -> 10100 | G9: ='Sept 2023'!$K$88 -> 0 | H9: ='Sept 2023'!$L$88 -> 500 | I9: ='Sept 2023'!$M$88 -> 8500 | J9: ='Sept 2023'!$N$88 -> 25100 | K9: ='Sept 2023'!$O$88 -> 13875 | L9: ='Sept 2023'!$P$88 -> 4525 | M9: ='Sept 2023'!$Q$88 -> 5000 | N9: =SUM(E9:M9) -> 109620 | O9: =SUM(F9:M9) -> 67600 | P9: =E9 -> 42020 | Q9: =SUM(O9,P9) -> 109620
D10: Old Stck CF | E10: 125045 | F10: 17475 | G10: 0 | H10: 500 | I10: 8500 | J10: 13250 | K10: 225 | L10: 4300 | M10: 5000 | N10: =SUM(E10:M10) -> 174295 | O10: =SUM(F10:M10) -> 49250 | P10: =E10 -> 125045 | Q10: =SUM(O10,P10) -> 174295
D11: New Input In Sept | E11: =W28 -> 97643 | J11: 18000 | K11: 18000 | N11: =SUM(E11:M11) -> 133643 | O11: =SUM(F11:M11) -> 36000 | P11: =E11 -> 97643 | Q11: =SUM(O11,P11) -> 133643
D12: Net Stocks CF | E12: =SUM(E10+E11-E9) -> 180668 | F12: =SUM(F10+F11-F9) -> 7375 | G12: =SUM(G10+G11-G9) -> 0 | H12: =SUM(H10+H11-H9) -> 0 | I12: =SUM(I10+I11-I9) -> 0 | J12: =SUM(J10+J11-J9) -> 6150 | K12: =SUM(K10+K11-K9) -> 4350 | L12: =SUM(L10+L11-L9) -> -225 | M12: =SUM(M10+M11-M9) -> 0 | N12: =SUM(E12:M12) -> 198318 | O12: =SUM(F12:M12) -> 17650 | P12: =E12 -> 180668 | Q12: =SUM(O12,P12) -> 198318
C16: Srl No | D16: Date | E16: Inv No | F16: Party | G16: Qty | H16: Price | I16: Off Grade | J16: 1799 | K16: 2099 | L16: 2699 | M16: 588 | N16: 2088 | O16: 2488 | P16: 2688 | Q16: 3099 | T16: Off Grade Stocks And Sales
C17: 1 | D17: 45170 | E17: 342 | F17: Ankush | G17: 1500 | H17: 169 | Q17: 1500 | T17: New Input
C18: 2 | D18: 45170 | E18: 343 | F18: Chemicare | G18: 3500 | H18: 171 | Q18: 3500 | T18: Srl No. | U18: Date | V18: Details | W18: Qty
C19: 3 | D19: 45170 | E19: 344 | F19: Siva Chem | G19: 500 | H19: 163 | P19: 500 | T19: 1 | U19: 45188 | V19: Crab Legs | W19: 12672
C20: 4 | D20: 45170 | E20: 345 | F20: Reliable | G20: 500 | H20: 164 | L20: 500 | T20: 2 | U20: 45190 | V20: Powder | W20: 18439
C21: 5 | D21: 45170 | E21: 346 | F21: Can Image | G21: 5000 | H21: 192 | N21: 5000 | T21: 3 | U21: 45191 | V21: Powder + Crystal | W21: 17513
C22: 6 | D22: 45171 | E22: 347 | F22: AP Bonding | G22: 3000 | H22: 325 | I22: 3000 | T22: 4 | U22: 45192 | V22: grade 325 | W22: 15513
C23: 7 | D23: 44961 | E23: 348 | F23: Guruji | G23: 1000 | H23: 161 | P23: 1000 | T23: 5 | U23: 45194 | V23: p+c | W23: 15987
C24: 8 | D24: 45020 | E24: 349 | F24: Om Shakhi | G24: 2000 | H24: 147 | J24: 2000 | T24: 6 | U24: 45194 | V24: p+c | W24: 17519
C25: 9 | D25: 45174 | E25: 351 | F25: Siva Chem | G25: 10000 | H25: 117 | I25: 10000 | T25: 7
C26: 10 | D26: 45174 | E26: 352 | F26: Fortune | G26: 520 | H26: 125, 185 | I26: 20 | P26: 500 | T26: 8
C27: 11 | D27: 45175 | E27: 354 | F27: Paresh Pure | G27: 1000 | H27: 160 | N27: 1000
C28: 12 | D28: 45177 | E28: 358 | F28: Growmore | G28: 400 | H28: 155 | J28: 400 | T28: Total New Input:- | W28: =SUM(W19:W26) -> 97643
C29: 13 | D29: 45177 | E29: 359 | F29: Divysai | G29: 500 | H29: 165 | N29: 500 | T29: Old Stock C/F:- | W29: 125045
C30: 14 | D30: 45178 | E30: 360 | F30: Popular | G30: 375 | H30: 158, 178 | J30: 250 | M30: 125 | T30: Total Stocks New & Old :- | W30: =SUM(W28,W29) -> 222688
C31: 15 | D31: 45178 | E31: RR | F31: Shri Ganpatye | G31: 225 | H31: 190 | P31: 225 | T31: LESS SALES: (as per sales sheet) | W31: ='Sept 2023'!$I$88 -> 42020
C32: 16 | D32: 45177 | E32: GTC 43 | F32: AP Bonding | G32: 2000 | H32: 157 | O32: 2000
C33: 17 | D33: 45177 | E33: 361 | F33: BSB Indus | G33: 5150 | H33: 115, 165 | I33: 4000 | N33: 1150 | T33: NET QTY AVAILABLE: | W33: =SUM(W30-W31) -> 180668
C34: 18 | D34: 45180 | E34: 363 | F34: Devanski | G34: 500 | H34: 165, 175 | M34: 250 | N34: 250
C35: 19 | D35: 45180 | E35: GTC 46 | F35: Veena | G35: 500 | H35: 170 | O35: 500
C36: 20 | D36: 45180 | E36: 364 | F36: Mine Chem | G36: 2500 | H36: 148.5 | J36: 2500
C37: 21 | D37: 45181 | E37: 365 | F37: Popular | G37: 3000 | H37: 178 | M37: 3000
C38: 22 | D38: 45181 | E38: 366 | F38: Popular | G38: 500 | H38: 158 | J38: 500
C39: 23 | D39: 45181 | E39: 367 | F39: Raj Chem | G39: 125 | H39: 180 | M39: 125
C40: 24 | D40: 45182 | E40: 368 | F40: Om Shakhi | G40: 1600 | H40: 114 | I40: 1600
C41: 25 | D41: 45182 | E41: 369 | F41: Growmore | G41: 400 | H41: 172 | O41: 400
C42: 26 | D42: 45183 | E42: 371 | F42: Popular | G42: 3000 | H42: 167 | N42: 3000
C43: 27 | D43: 45183 | E43: 372 | F43: Popular | G43: 500 | H43: 120 | I43: 500
C44: 28 | D44: 45184 | E44: 373 | F44: Siva Chem | G44: 10000 | H44: 117 | I44: 10000
C45: 29 | D45: 45184 | E45: 374 | F45: Fortune | G45: 500 | H45: 125 | I45: 500
C46: 30 | D46: 45184 | E46: 375 | F46: Mine Chem | G46: 250 | H46: 148.5 | J46: 250
C47: 31 | D47: 45184 | E47: 376 | F47: Kraft | G47: 500 | H47: 105 | I47: 500
C48: 32 | D48: 45184 | E48: GTC 47 | F48: Aditya | G48: 2000 | H48: 178 | M48: 2000
C49: 33 | D49: 45185 | E49: 379 | F49: KDM | G49: 1000 | H49: 170 | O49: 1000
C50: 34 | D50: 45185 | E50: 380 | F50: Swastik | G50: 1000 | H50: 171 | P50: 1000
C51: 35 | D51: 45186 | E51: 381 | F51: Can Image | G51: 5000 | H51: 192 | N51: 5000
C52: 35 | D52: 45187 | E52: 382 | F52: Eco Industries | G52: 100 | H52: 130 | I52: 100
C53: 36 | D53: 45187 | E53: 383 | F53: Mine Chem | G53: 100 | H53: 120 | I53: 100
C54: 37 | D54: 45189 | E54: 384 | F54: Mangalam | G54: 250 | H54: 120, 178 | I54: 200 | O54: 50
C55: 38 | D55: 45189 | E55: GTC 48 | F55: Mine Chem | G55: 5000 | H55: 168, 159 | M55: 2000 | N55: 3000
C56: 39 | D56: 45190 | E56: GTC 49 | F56: Aditya | G56: 1000 | H56: 178 | M56: 1000
C57: 40 | D57: 45190 | E57: 385 | F57: Siva Chem | G57: 500 | H57: 169 | O57: 500
C58: 41 | D58: 45190 | E58: 386 | F58: Divysai | G58: 500 | H58: 163 | N58: 500
C59: 42 | D59: 45190 | E59: 387 | F59: Kanha | G59: 300 | H59: 125 | I59: 300
C60: 43 | D60: 45190 | E60: 388 | F60: Sunil Dye | G60: 300 | H60: 177 | P60: 300
C61: 44 | D61: 45191 | E61: 389 | F61: SKS Fine | G61: 500 | H61: 125 | I61: 500
C62: 45 | D62: 45192 | E62: 392 | F62: Vasudha | G62: 1500 | H62: 120, 180 | I62: 500 | P62: 1000
C63: 46 | D63: 45192 | E63: 393 | F63: Devysai | G63: 200 | H63: 163 | N63: 200
C64: 47 | D64: 45192 | E64: RR | F64: Meet Products | G64: 200 | H64: 120 | I64: 200
C65: 48 | D65: 45194 | E65: 395 | F65: Siva Chem | G65: 10000 | H65: 115 | I65: 10000
C66: 49 | D66: 45194 | E66: GTC 50 | F66: Aditya | G66: 2000 | H66: 163 | N66: 2000
C67: 50 | D67: 45196 | E67: 397 | F67: Kanha | G67: 1000 | H67: 163 | N67: 1000
C68: 51 | D68: 45196 | E68: 398 | F68: Mine Chem | G68: 25 | H68: 175 | O68: 25
C69: 52 | D69: 45196 | E69: 399 | F69: Growmore | G69: 1100 | H69: 157, 172 | J69: 500 | O69: 600
C70: 53 | D70: 45198 | E70: RR | F70: Meet Products | G70: 200 | H70: 154 | J70: 200
C71: 54 | D71: 45198 | E71: 401 | F71: Fortune | G71: 100 | H71: 172 | O71: 100
C72: 55 | D72: 45198 | E72: 402 | F72: Reliable | G72: 500 | H72: 152 | J72: 500
C73: 56 | D73: 45198 | E73: GTC 51 | F73: Mine Chem | G73: 3000 | H73: 167 | O73: 3000
C74: 57 | D74: 45199 | E74: GTC 52 | F74: Aditya | G74: 6500 | H74: 163.5, 150 | J74: 3000 | N74: 2000 | O74: 1500
C75: 58 | D75: 45199 | E75: RR | F75: Shri Ganpatye | G75: 200 | H75: 190 | O75: 200
C76: 59 | D76: 45199 | E76: 404 | F76: Aditya | G76: 2000 | H76: 163.5 | O76: 2000
C77: 60 | D77: 45199 | E77: 405 | F77: AP Bonding | G77: 2000 | H77: 163.5 | O77: 2000
C78: 61 | D78: cf mistake | F78: soham | G78: 500 | H78: 160 | N78: 500
C79: 62 | F79: Siva Chem
C80: 63 | F80: Sagar Corp
C81: 64 | F81: Swastik
C82: 65
C83: 66
C84: 67
C85: 68
C86: 69
C87: 70
C88: TOTAL | G88: =SUM(G17:G87) -> 109620 | I88: =SUM(I17:I87) -> 42020 | J88: =SUM(J17:J87) -> 10100 | K88: =SUM(K17:K87) -> 0 | L88: =SUM(L17:L87) -> 500 | M88: =SUM(M17:M87) -> 8500 | N88: =SUM(N17:N87) -> 25100 | O88: =SUM(O17:O87) -> 13875 | P88: =SUM(P17:P87) -> 4525 | Q88: =SUM(Q17:Q87) -> 5000
I90: =SUM('Sept 2023'!$I$88:'Sept 2023'!$P$88) -> 104620

Sheet Oct 2023
D5: October 2023 Sales in Nutsell | O5: Prime | P5: Off Grade | Q5: Total
D6: Grades | E6: Off Grade | F6: 1799 | G6: DENKA | H6: 2699 | I6: 588 | J6: 2088 | K6: 2488 | L6: 2688 | M6: 3099 | N6: TOTAL
D7: Qty | E7: ='Oct 2023'!$I$95 -> 66140 | F7: ='Oct 2023'!$J$95 -> 8450 | G7: ='Oct 2023'!$R$95 -> 5180 | H7: ='Oct 2023'!$L$95 -> 33725 | I7: ='Oct 2023'!$M$95 -> 0 | J7: ='Oct 2023'!$N$95 -> 20600 | K7: ='Oct 2023'!$O$95 -> 4150 | L7: ='Oct 2023'!$P$95 -> 2350 | M7: ='Oct 2023'!$Q$95 -> 9000 | N7: =SUM(E7:M7) -> 149595 | O7: =SUM(F7:M7) -> 83455 | P7: =E7 -> 66140 | Q7: =SUM(O7,P7) -> 149595
D8: Old Stck CF | E8: 180668 | F8: 7375 | G8: 0 | H8: 0 | I8: 0 | J8: 6150 | K8: 4150 | N8: =SUM(E8:M8) -> 198343 | O8: =SUM(F8:M8) -> 17675 | P8: =E8 -> 180668 | Q8: =SUM(O8,P8) -> 198343
D9: New Input In Oct | E9: =X26 -> 94665 | F9: 45000 | G9: 19000 | H9: 36000 | J9: 18000 | L9: 7500 | M9: 9000 | N9: =SUM(E9:M9) -> 229165 | O9: =SUM(F9:M9) -> 134500 | P9: =E9 -> 94665 | Q9: =SUM(O9,P9) -> 229165
D10: Net Stocks CF | E10: =SUM(E8+E9-E7) -> 209193 | F10: =SUM(F8+F9-F7) -> 43925 | G10: =SUM(G8+G9-G7) -> 13820 | H10: =SUM(H8+H9-H7) -> 2275 | I10: =SUM(I8+I9-I7) -> 0 | J10: =SUM(J8+J9-J7) -> 3550 | K10: =SUM(K8+K9-K7) -> 0 | L10: =SUM(L8+L9-L7) -> 5150 | M10: =SUM(M8+M9-M7) -> 0 | N10: =SUM(E10:M10) -> 277913 | O10: =SUM(F10:M10) -> 68720 | P10: =E10 -> 209193 | Q10: =SUM(O10,P10) -> 277913
C14: Srl No | D14: Date | E14: Inv No | F14: Party | G14: Qty | H14: Price | I14: Off Grade | J14: 1799 | K14: 2099 | L14: 2699 | M14: 588 | N14: 2088 | O14: 2488 | P14: 2688 | Q14: 3099 | R14: DENKA | U14: Off Grade Stocks And Sales
C15: 1 | D15: 45201 | E15: 406 | F15: Mine Chem | G15: 500 | H15: 120 | I15: 500 | U15: New Input
C16: 2 | D16: 45201 | E16: 408 | F16: Guruji | G16: 500 | H16: 119 | I16: 500 | U16: Srl No. | V16: Date | W16: Details | X16: Qty
C17: 3 | D17: 45201 | E17: 409 | F17: Chandan | G17: 3000 | H17: 123 | I17: 3000 | U17: 1 | V17: 45198 | W17: Superbond | X17: 8512
C18: 4 | D18: 45201 | E18: 410 | F18: Patel Adhesives | G18: 500 | H18: 117 | I18: 500 | U18: 2 | V18: 45198 | W18: Superbond | X18: 8582
C19: 5 | D19: 45202 | E19: 411 | F19: Swastik | G19: 600 | H19: 171 | O19: 600 | U19: 3 | V19: 45202 | W19: Powder | X19: 17447
C20: 6 | D20: 45202 | E20: 412 | F20: Swastik | G20: 1000 | H20: 171 | P20: 1000 | U20: 4 | V20: 45206 | W20: Powder | X20: 17944
C21: 7 | D21: 45202 | E21: 413 | F21: Fortune | G21: 500 | H21: 185 | P21: 500 | U21: 5 | V21: 45207 | W21: 80-35 | X21: 20997
C22: 8 | D22: 45203 | E22: 414 | F22: Popular | G22: 1300 | H22: 169 | N22: 1300 | U22: 6 | V22: 45230 | W22: 30-99 | X22: 21183
C23: 9 | D23: 45203 | E23: 415 | F23: Divysai | G23: 300 | H23: 163 | N23: 300 | U23: 7
C24: 10 | D24: 45203 | E24: RR | F24: Patidar | G24: 1000 | H24: 170 | L24: 1000 | U24: 8
C25: 11 | D25: 45203 | E25: 417 | F25: BSB Indus | G25: 1000 | H25: 154, 170, 172 | J25: 500 | L25: 300 | O25: 200
C26: 12 | D26: 45203 | E26: 418 | F26: Gautam Kabdhir | G26: 1000 | H26: 165 | N26: 1000 | U26: Total New Input:- | X26: =SUM(X17:X24) -> 94665
C27: 13 | D27: 45204 | E27: 419 | F27: Vrinda | G27: 15000 | H27: 113 | I27: 15000 | U27: Old Stock C/F:- | X27: 180668
C28: 14 | D28: 45204 | E28: 421 | F28: Surya | G28: 500 | H28: 159 | J28: 500 | U28: Total Stocks New & Old :- | X28: =SUM(X26,X27) -> 275333
C29: 15 | D29: 45204 | E29: 422 | F29: KDM | G29: 1000 | H29: 171 | O29: 1000 | U29: LESS SALES: (as per sales sheet) | X29: ='Oct 2023'!$I$95 -> 66140
C30: 16 | D30: 45204 | E30: 423 | F30: Raj Chem | G30: 1000 | H30: 164 | L30: 1000
C31: 17 | D31: 45204 | E31: GTC 53 | F31: Vrinda | G31: 4000 | H31: 162 | L31: 4000 | U31: NET QTY AVAILABLE: | X31: =SUM(X28-X29) -> 209193
C32: 18 | D32: 45204 | E32: GTC 54 | F32: Mine Chem | G32: 250 | H32: 150 | J32: 250
C33: 19 | D33: 45204 | E33: 424 | F33: Paresh Pure | G33: 500 | H33: 168 | N33: 500
C34: 20 | D34: 45205 | E34: 425 | F34: Paramount | G34: 15000 | H34: 112 | I34: 15000
C35: 21 | D35: 45205 | E35: 426 | F35: Reliable | G35: 1500 | H35: 170 | L35: 1500
C36: 22 | D36: 45206 | E36: 428 | F36: Raj Chem | G36: 1000 | H36: 158 | N36: 1000
C37: 23 | D37: 45206 | E37: GTC 55 | F37: Vrinda | G37: 5000 | H37: 178 | Q37: 5000
C38: 24 | D38: 45206 | E38: 429 | F38: Chemi Range | G38: 3000 | H38: 182 | Q38: 3000
C39: 26 | D39: 45206 | E39: 451 | F39: soham | G39: 500 | H39: 172 | O39: 500
C40: 27 | D40: 45208 | E40: GTC 56 | F40: AP Bonding | G40: 1000 | H40: 163.5 | L40: 1000
C41: 28 | D41: 45208 | E41: GTC 57 | F41: Veekay | G41: 3000 | H41: 170 | L41: 3000
C42: 29 | D42: 45208 | E42: GTC 58 | F42: Paresh Pure | G42: 3500 | H42: 162 | N42: 3500
C43: 30 | D43: 45208 | E43: GTC 59 | F43: Paresh Pure | G43: 500 | H43: 166 | N43: 500
C44: 31 | D44: 45208 | E44: 430 | F44: Seamless | G44: 150 | H44: 185 | P44: 150
C45: 32 | D45: 45208 | E45: 431 | F45: Vasudha | G45: 500 | H45: 120 | I45: 500
C46: 33 | D46: 45208 | E46: 432 | F46: KDM | G46: 600 | H46: 118 | I46: 600
C47: 34 | D47: 45208 | E47: 433 | F47: Raj Indus | G47: 1150 | H47: 164, 182 | L47: 1000 | Q47: 150
C48: 35 | D48: 45208 | E48: 434 | F48: Vinit | G48: 10000 | H48: 115 | I48: 10000
C49: 36 | D49: 45208 | E49: 435 | F49: Paresh Pure | G49: 20 | H49: 125 | I49: 20
C50: 37 | D50: 45209 | E50: 437 | F50: Popular | G50: 3000 | H50: 170 | N50: 3000
C51: 38 | D51: 45209 | E51: 439 | F51: Popular | G51: 500 | H51: 175 | O51: 500
C52: 39 | D52: 45209 | E52: GTC 61 | F52: Veena | G52: 500 | H52: 172 | O52: 500
C53: 40 | D53: 45209 | E53: GTC 62 | F53: Aditya | G53: 3000 | H53: 146 | J53: 3000
C54: 41 | D54: 45209 | E54: GTC 63 | F54: Mine Chem | G54: 2000 | H54: 161 | N54: 2000
C55: 42 | D55: 45210 | E55: 441 | F55: BSB Indus | G55: 4800 | H55: 120, 165 | I55: 4000 | N55: 800
C56: 43 | D56: 45211 | E56: 442 | F56: Growmore | G56: 500 | H56: 158 | J56: 500
C57: 44 | D57: 45212 | E57: 443 | F57: Kanha | G57: 320 | H57: 125 | I57: 320
C58: 45 | D58: 45212 | E58: 447 | F58: Growmore | G58: 500 | H58: 178 | O58: 500
C59: 46 | D59: 45212 | E59: 448 | F59: SKS Fine | G59: 200 | H59: 175 | N59: 200
C60: 47 | D60: 45214 | E60: 449 | F60: Can Image | G60: 5000 | H60: 192 | N60: 5000
C61: 48 | D61: 45214 | E61: 450 | F61: Fortune | G61: 500 | H61: 125 | I61: 500
C62: 49 | D62: 45216 | E62: 452 | F62: Giriraj Polymers | G62: 1000 | H62: 120 | I62: 1000
C63: 50 | D63: 45216 | E63: 453 | F63: Darshan | G63: 220 | H63: 115 | I63: 220
C64: 51 | D64: 45215 | E64: GTC 63 | F64: Mine Chem | G64: 1000 | H64: 149 | J64: 1000
C65: 52 | D65: 45217 | E65: 454 | F65: Mine Chem | G65: 100 | H65: 125 | I65: 100
C66: 53 | D66: 45218 | E66: 455 | F66: Popular | G66: 350 | H66: 175 | O66: 350
C67: 54 | D67: 45218 | E67: 456 | F67: Akshat Corp | G67: 245 | H67: 125, 180 | I67: 220 | L67: 25
C68: 55 | D68: 45218 | E68: 457 | F68: AP Bonding | G68: 6680 | H68: 325 | I68: 6680
C69: 56 | D69: 45218 | E69: 458 | F69: AP Bonding | G69: 200 | H69: 120 | I69: 200
C70: 57 | D70: 45217 | E70: GTC 64 | F70: Mine Chem | G70: 500 | H70: 150 | J70: 500
C71: 58 | D71: 45219 | E71: 459 | F71: Vasudha | G71: 700 | H71: 159 | J71: 700
C72: 59 | D72: 45219 | E72: 460 | F72: Divysai | G72: 500 | H72: 166 | N72: 500
C73: 60 | D73: 45219 | E73: 461 | F73: Rally Chem | G73: 10000 | H73: 162 | L73: 10000
C74: 61 | D74: 45219 | E74: 462 | F74: Guruji | G74: 1500 | H74: 164 | L74: 1500
C75: 62 | D75: 45219 | E75: 463 | F75: Papyrus | G75: 300 | H75: 168 | L75: 300
C76: 63 | D76: 45220 | E76: 464 | F76: Fortune | G76: 500 | H76: 125 | I76: 500
C77: 64 | D77: 45222 | E77: 465 | F77: Om Shakti | G77: 1600 | H77: 120 | I77: 1600
C78: 65 | D78: 45224 | E78: GTC 67 | F78: Aditya | G78: 2000 | H78: 165 | L78: 2000
C79: 66 | D79: 45225 | E79: 468 | F79: Reliable | G79: 1510 | H79: 180, 120 | I79: 660 | Q79: 850
C80: 67 | D80: 45225 | E80: GTC 69 | F80: Growmore | G80: 500 | H80: 158 | J80: 500
C81: 68 | D81: 45225 | E81: GTC 71 | F81: Veena | G81: 700 | H81: 200 | R81: 700
C82: 69 | D82: 45226 | E82: 469 | F82: Rally Chem | G82: 8000 | H82: 162, 206 | L82: 6000 | R82: 2000
C83: 70 | D83: 45226 | E83: 470 | F83: KK Dye | G83: 500 | H83: 209 | R83: 500
C84: 71 | D84: 45226 | E84: 472 | F84: Vasudha | G84: 520 | H84: 119, 199 | I84: 20 | R84: 500
C85: 72 | D85: 45226 | E85: GTC 72 | F85: AP Bonding | G85: 1000 | H85: 162 | L85: 1000
C86: 73 | D86: 45227 | E86: GTC 73 | F86: Growmore | G86: 500 | H86: 200 | R86: 500
C87: 74 | D87: 45227 | E87: RR | F87: Shri Ganpatye | G87: 300 | H87: 180, 190 | L87: 100 | P87: 200
C88: 75 | D88: 45229 | E88: 475 | F88: Guruji | G88: 1100 | H88: 162, 200 | P88: 500 | R88: 600
C89: 76 | D89: 45229 | E89: 477 | F89: Purvi Enterprise | G89: 40 | H89: 195 | R89: 40
C90: 77 | D90: 45229 | E90: RR | F90: Gurpreet | G90: 340 | H90: 205 | R90: 340
C91: 78 | D91: 45229 | E91: 479 | F91: Paramount | G91: 4000 | H91: 117, 325 | I91: 4000
C92: 79 | D92: 45229 | E92: 480 | F92: Fortune | G92: 500 | H92: 125 | I92: 500
C93: 80 | D93: 45229 | E93: 481 | F93: Chemi Care | G93: 1000 | H93: 163 | N93: 1000
C94: 81 | D94: 45230 | E94: 482 | F94: Shree Mahalaxmi | G94: 1000 | H94: 147 | J94: 1000
C95: TOTAL | G95: =SUM(G15:G94) -> 149595 | I95: =SUM(I15:I94) -> 66140 | J95: =SUM(J15:J94) -> 8450 | K95: =SUM(K15:K94) -> 0 | L95: =SUM(L15:L94) -> 33725 | M95: =SUM(M15:M94) -> 0 | N95: =SUM(N15:N94) -> 20600 | O95: =SUM(O15:O94) -> 4150 | P95: =SUM(P15:P94) -> 2350 | ... R95: =SUM(R15:R94) -> 5180

Sheet Nov 2023
D3: November 2023 Sales in Nutsell | O3: Prime | P3: Off Grade | Q3: Total
D4: Grades | E4: Off Grade | F4: 1799 | G4: 2699 | H4: 588 | I4: 2088 | J4: 2488 | K4: 2688 | L4: 3099 | M4: DENKA | N4: TOTAL
D5: Old Stck CF | E5: 209193 | F5: 43925 | G5: 2275 | H5: 0 | I5: 3550 | J5: 0 | K5: 5850 | L5: 0 | M5: 13820 | N5: =SUM(E5:M5) -> 278613 | O5: =SUM(F5:M5) -> 69420 | P5: =E5 -> 209193 | Q5: =O5+P5 -> 278613
D6: New Input In Oct | E6: =W24 -> 0 | G6: 18000 | H6: 8000 | J6: 18000 | K6: 10000 | L6: 18000 | N6: =SUM(E6:M6) -> 72000 | O6: =SUM(F6:M6) -> 72000 | P6: =E6 -> 0 | Q6: =O6+P6 -> 72000
D7: Sales In Nov | E7: ='Nov 2023'!$I$93 -> 14440 | F7: ='Nov 2023'!$J$93 -> 5850 | G7: ='Nov 2023'!$K$93 -> 4275 | H7: ='Nov 2023'!$L$93 -> 2800 | I7: ='Nov 2023'!$M$93 -> 3800 | J7: ='Nov 2023'!$N$93 -> 6275 | K7: ='Nov 2023'!$O$93 -> 6600 | L7: ='Nov 2023'!$P$93 -> 1600 | M7: ='Nov 2023'!$Q$93 -> 3300 | N7: =SUM(E7:M7) -> 48940 | O7: =SUM(F7:M7) -> 34500 | P7: =E7 -> 14440 | Q7: =SUM(O7,P7) -> 48940
D8: Net Stocks CF | E8: =SUM(E5,E6-E7) -> 194753 | F8: =SUM(F5,F6-F7) -> 38075 | G8: =SUM(G5,G6-G7) -> 16000 | H8: =SUM(H5,H6-H7) -> 5200 | I8: =SUM(I5,I6-I7) -> -250 | J8: =SUM(J5,J6-J7) -> 11725 | K8: =SUM(K5,K6-K7) -> 9250 | L8: =SUM(L5,L6-L7) -> 16400 | ... N8: =SUM(N5,N6-N7) -> 301673 | O8: =SUM(F8:M8) -> 106920 | P8: =E8 -> 194753 | Q8: =SUM(O8,P8) -> 301673
C12: Srl No | D12: Date | E12: Inv No | F12: Party | G12: Qty | H12: Price | I12: Off Grade | J12: 1799 | K12: 2699 | L12: 588 | M12: 2088 | N12: 2488 | O12: 2688 | P12: 3099 | Q12: DENKA | T12: Off Grade Stocks And Sales
C13: 1 | D13: 45231 | E13: 483 | F13: Paradise | G13: 2000 | H13: 163 | M13: 2000 | T13: New Input
C14: 2 | D14: 45231 | E14: 484 | F14: Surya | G14: 3000 | H14: 170 | O14: 3000 | T14: Srl No. | U14: Date | V14: Details | W14: Qty
C15: 3 | D15: 45231 | E15: RR | F15: Gurpreet | G15: 500 | H15: 119 | I15: 500 | T15: 1
C16: 4 | D16: 45231 | E16: 486 | F16: Divysai | G16: 350 | H16: 163 | M16: 350 | T16: 2
C17: 5 | D17: 45231 | E17: 487 | F17: KDM | G17: 720 | H17: 169, 117 | I17: 20 | N17: 700 | T17: 3
C18: 6 | D18: 45232 | E18: 488 | F18: Divysai | G18: 500 | H18: 163 | M18: 500 | T18: 4
C19: 7 | D19: 45232 | E19: RR | F19: Patidar | G19: 275 | H19: 169 | K19: 275 | T19: 5
C20: 8 | D20: 45232 | E20: GTC 77 78 | F20: Aditya | G20: 3000 | H20: 168, 178 | K20: 2000 | L20: 1000 | T20: 6
C21: 9 | D21: 45232 | E21: GTC 79 | F21: Mine Chem | G21: 1400 | H21: 147, 168 | J21: 1050 | N21: 350 | T21: 7
C22: 10 | D22: 45233 | E22: 491 | F22: Kanha | G22: 300 | H22: 125 | I22: 300 | T22: 8
C23: 11 | D23: 45234 | E23: 493 | F23: SKR | G23: 1200 | H23: 113 | I23: 1200
C24: 12 | D24: 45234 | E24: 494 | F24: Vasudha | G24: 1000 | H24: 184 | L24: 1000 | T24: Total New Input:- | W24: =SUM(W15:W22) -> 0
C25: 13 | D25: 45234 | E25: 495 | F25: KDM | G25: 600 | H25: 118, 205 | I25: 300 | Q25: 300 | T25: Old Stock C/F:- | W25: 209193
C26: 14 | D26: 45234 | E26: RR | F26: Meet Products | G26: 800 | H26: 118, 193, 150 | I26: 400 | J26: 300 | Q26: 100 | T26: Total Stocks New & Old :- | W26: =SUM(W24,W25) -> 209193
C27: 15 | D27: 45236 | E27: GTC 80 | F27: Veena | G27: 500 | H27: 173 | N27: 500 | T27: LESS SALES: (as per sales sheet) | W27: ='Nov 2023'!$I$93 -> 14440
C28: 16 | D28: 45236 | E28: GTC 82 | F28: Growmore | G28: 1000 | H28: 158, 200 | J28: 500 | Q28: 500
C29: 17 | D29: 45237 | E29: 497 | F29: Shree Mahalaxmi | G29: 160 | H29: 115 | I29: 160 | T29: NET QTY AVAILABLE: | W29: =SUM(W26-W27) -> 194753
C30: 18 | D30: 45237 | E30: 497 | F30: Mangalam Dye Chem | G30: 300 | H30: 120, 150 | I30: 200 | J30: 100
C31: 19 | D31: 45237 | E31: 499 | F31: Vasudha | G31: 3000 | H31: 120 | I31: 3000
C32: 20 | D32: 45238 | E32: 502 | F32: Fortune | G32: 500 | H32: 125 | I32: 500
C33: 21 | D33: 45241 | E33: 505 | F33: BSB Indus | G33: 4000 | H33: 115, 150, 175, 165, | I33: 3000 | J33: 400 | N33: 200 | O33: 400
C34: 22 | D34: 45237 | E34: GTC 83 | F34: Paresh Pure | G34: 700 | H34: 169 | M34: 700
C35: 23 | D35: 45245 | E35: 506 | F35: Popular | G35: 2000 | H35: 174 | N35: 2000
C36: 24 | D36: 45246 | E36: 508 | F36: Sagar Corp | G36: 1000 | H36: 116 | I36: 1000
C37: 26 | D37: 45247 | E37: 509 | F37: Shree Mahalaxmi | G37: 160 | H37: 115 | I37: 160
C38: 27 | D38: 45247 | E38: 511 | F38: KDM | G38: 1000 | H38: 170 | N38: 1000
C39: 28 | D39: 45247 | E39: 512 | F39: Popular | G39: 1000 | H39: 151 | J39: 1000
C40: 29 | D40: 45251 | E40: RR | F40: Patidar | G40: 500 | H40: 170 | P40: 500
C41: 30 | D41: 45251 | E41: 515 | F41: Divysai | G41: 500 | H41: 163 | N41: 500
C42: 31 | D42: 45251 | E42: GTC 84 | F42: Mine Chem | G42: 25 | H42: 168 | N42: 25
C43: 32 | D43: 45251 | E43: GTC 85 | F43: Growmore | G43: 1000 | H43: 158, 200 | J43: 500 | Q43: 500
C44: 33 | D44: 45251 | E44: 516 | F44: Fortune | G44: 500 | H44: 125 | I44: 500
C45: 34 | D45: 45251 | E45: GTC 86 | F45: Veekay | G45: 1000 | H45: 171 | N45: 1000
C46: 35 | D46: 45251 | E46: 517 | F46: Vasudha | G46: 1800 | H46: 185, 180, 200 | L46: 600 | O46: 500 | Q46: 700
C47: 36 | D47: 45252 | E47: 519 | F47: Empowera | G47: 1000 | H47: 185 | Q47: 1000
C48: 37 | D48: 45252 | E48: 520 | F48: Shree Mahalaxmi | G48: 200 | H48: 115 | I48: 200
C49: 38 | D49: 45253 | E49: 521 | F49: Surya | G49: 2800 | H49: 150, 170 | J49: 500 | O49: 2300
C50: 39 | D50: 45253 | E50: 522 | F50: Om Shakti | G50: 2000 | H50: 120 | I50: 2000
C51: 40 | D51: 45253 | E51: GTC 87 | F51: Growmore | G51: 500 | H51: 158 | J51: 500
C52: 41 | D52: 45254 | E52: 523 | F52: Om Neelkhant | G52: 500 | H52: 167 | P52: 500
C53: 42 | D53: 45254 | E53: 525 | F53: Bhavya | G53: 200 | H53: 174 | L53: 200
C54: 43 | D54: 45254 | E54: 526 | F54: Surya | G54: 150 | H54: 170 | O54: 150
C55: 44 | D55: 45254 | E55: GTC 88 | F55: Mine Chem | G55: 1250 | H55: 144, 165 | J55: 1000 | M55: 250
C56: 45 | D56: 45255 | E56: 527 | F56: AP Enterprises | G56: 250 | H56: 184 | O56: 250
C57: 46 | D57: 45257 | E57: 528 | F57: Raj Inds | G57: 600 | H57: 162 | P57: 600
C58: 47 | D58: 45257 | E58: 529 | F58: Fortune | G58: 1000 | H58: 125 | I58: 1000
C59: 48 | D59: 45258 | E59: RR | F59: Meet Products | G59: 200 | H59: 188 | Q59: 200
C60: 49 | D60: 45260 | E60: RR | F60: Patidar | G60: 1000 | H60: 164 | K60: 1000
C61: 50 | D61: 45260 | E61: GTC 89 | F61: Veekay | G61: 1000 | H61: 166 | K61: 1000
C62: 51 | F62: Mine Chem | G62: 1000 | H62: 149
C63: 52 | F63: Mine Chem | G63: 100 | H63: 125
C64: 53 | F64: Popular | G64: 350 | H64: 175
C65: 54 | F65: Akshat Corp | G65: 245 | H65: 125, 180
C66: 55 | F66: AP Bonding | G66: 6680 | H66: 325
C67: 56 | F67: AP Bonding | G67: 200 | H67: 120
C68: 57 | F68: Mine Chem | G68: 500 | H68: 150
C69: 58 | F69: Vasudha | G69: 700 | H69: 159
C70: 59 | F70: Divysai | G70: 500 | H70: 166
C71: 60 | F71: Rally Chem | G71: 10000 | H71: 162
C72: 61 | F72: Guruji | G72: 1500 | H72: 164
C73: 62 | F73: Papyrus | G73: 300 | H73: 168
C74: 63 | F74: Fortune | G74: 500 | H74: 125
C75: 64 | F75: Om Shakti | G75: 1600 | H75: 120
C76: 65 | F76: Aditya | G76: 2000 | H76: 165
C77: 66 | F77: Reliable | G77: 1510 | H77: 180, 120
C78: 67 | F78: Growmore | G78: 500 | H78: 158
C79: 68 | F79: Veena | G79: 700 | H79: 200
C80: 69 | F80: Rally Chem | G80: 8000 | H80: 162, 206
C81: 70 | F81: KK Dye | G81: 500 | H81: 209
C82: 71 | F82: Vasudha | G82: 520 | H82: 119, 199
C83: 72 | F83: AP Bonding | G83: 1000 | H83: 162
C84: 73 | F84: Growmore | G84: 500 | H84: 200
C85: 74 | F85: Shri Ganpatye | G85: 300 | H85: 180, 190
C86: 75 | F86: Guruji | G86: 1100 | H86: 162, 200
C87: 76 | F87: Purvi Enterprise | G87: 40 | H87: 195
C88: 77 | F88: Gurpreet | G88: 340 | H88: 205
C89: 78 | F89: Paramount | G89: 4000 | H89: 117, 325
C90: 79 | F90: Fortune | G90: 500 | H90: 125
C91: 80 | F91: Chemi Care | G91: 1000 | H91: 163
C92: 81 | F92: Shree Mahalaxmi | G92: 1000 | H92: 147
C93: TOTAL | G93: =SUM(G13:G92) -> 96625 | I93: =SUM(I13:I92) -> 14440 | J93: =SUM(J13:J92) -> 5850 | K93: =SUM(K13:K92) -> 4275 | L93: =SUM(L13:L92) -> 2800 | M93: =SUM(M13:M92) -> 3800 | N93: =SUM(N13:N92) -> 6275 | O93: =SUM(O13:O92) -> 6600 | P93: =SUM(P13:P92) -> 1600 | Q93: =SUM(Q13:Q92) -> 3300
I95: =SUM('Nov 2023'!$I$93:'Nov 2023'!$Q$93) -> 48940

Sheet Dec 2023
D4: December 2023 Sales in Nutsell | O4: Prime | P4: Off Grade | Q4: Total
D5: Grades | E5: Off Grade | F5: 1799 | G5: 2699 | H5: 588 | I5: 2088 | J5: 2488 | K5: 2688 | L5: 3099 | M5: DENKA | N5: TOTAL
D6: Old Stck CF | E6: 194753 | F6: 38075 | G6: 16000 | H6: 5200 | I6: 0 | J6: 11725 | K6: 9250 | L6: 16400 | M6: 10520 | N6: =SUM(E6:M6) -> 301923 | O6: =SUM(F6:M6) -> 107170 | P6: =E6 -> 194753 | Q6: =O6+P6 -> 301923
D7: New Input In Dec | E7: =W32 -> 60360 | F7: =F18 -> 0 | G7: =G18 -> 9000 | H7: =H18 -> 27000 | I7: =I18 -> 36000 | J7: =J18 -> 36000 | K7: =K18 -> 18000 | L7: =L18 -> 18000 | M7: =M18 -> 19000 | N7: =N18 -> 163000 | O7: =SUM(F7:M7) -> 163000 | P7: =E7 -> 60360 | Q7: =O7+P7 -> 223360
D8: Sales In Dec | E8: ='Dec 2023'!$I$101 -> 69540 | F8: ='Dec 2023'!$J$101 -> 21450 | G8: ='Dec 2023'!$K$101 -> 12625 | H8: ='Dec 2023'!$L$101 -> 6120 | I8: ='Dec 2023'!$M$101 -> 22500 | J8: ='Dec 2023'!$N$101 -> 12025 | K8: ='Dec 2023'!$O$101 -> 4650 | L8: ='Dec 2023'!$P$101 -> 1000 | M8: ='Dec 2023'!$Q$101 -> 3560 | N8: =SUM(E8:M8) -> 153470 | O8: =SUM(F8:M8) -> 83930 | P8: =E8 -> 69540 | Q8: =SUM(O8,P8) -> 153470
D9: Net Stocks CF | E9: =SUM(E6,E7-E8) -> 185573 | F9: =SUM(F6,F7-F8) -> 16625 | G9: =SUM(G6,G7-G8) -> 12375 | H9: =SUM(H6,H7-H8) -> 26080 | I9: =SUM(I6,I7-I8) -> 13500 | J9: =SUM(J6,J7-J8) -> 35700 | K9: =SUM(K6,K7-K8) -> 22600 | L9: =SUM(L6,L7-L8) -> 33400 | ... N9: =SUM(N6,N7-N8) -> 311453 | O9: =SUM(F9:M9) -> 186240 | P9: =E9 -> 185573 | Q9: =SUM(O9,P9) -> 371813
C11: PRIME INPUT DETAILS | E11: GRADES | F11: 1799 | G11: 2699 | H11: 588 | I11: 2088 | J11: 2488 | K11: 2688 | L11: 3099 | M11: DENKA | N11: TOTAL | O11: FROM | P11: IMP NO
C12: SRL NO | D12: MAKE | E12: DATE | N12: =SUM(F12:M12) -> 0
C13: 1 | D13: Wanwei | E13: 45261 | I13: 18000 | N13: =SUM(F13:M13) -> 18000 | O13: GTC | P13: 12
C14: 2 | D14: IM | E14: 45268 | G14: 9000 | H14: 9000 | I14: 9000 | J14: 18000 | K14: 9000 | N14: =SUM(F14:M14) -> 54000 | O14: GTC | P14: 10
C15: 3 | D15: IM | E15: 45282 | H15: 18000 | I15: 9000 | J15: 18000 | K15: 9000 | N15: =SUM(F15:M15) -> 54000 | O15: GTC | P15: 13
C16: 4 | D16: Wanwei | E16: 45282 | L16: 18000 | N16: =SUM(F16:M16) -> 18000 | O16: SST | P16: 45
C17: 5 | D17: Denka | E17: 45269 | M17: 19000 | N17: =SUM(F17:M17) -> 19000 | O17: SST | P17: 47
C18: TOTAL | F18: =SUM(F12:F17) -> 0 | G18: =SUM(G12:G17) -> 9000 | H18: =SUM(H12:H17) -> 27000 | I18: =SUM(I12:I17) -> 36000 | J18: =SUM(J12:J17) -> 36000 | K18: =SUM(K12:K17) -> 18000 | L18: =SUM(L12:L17) -> 18000 | M18: =SUM(M12:M17) -> 19000 | N18: =SUM(F18:M18) -> 163000
C20: Srl No | D20: Date | E20: Inv No | F20: Party | G20: Qty | H20: Price | I20: Off Grade | J20: 1799 | K20: 2699 | L20: 588 | M20: 2088 | N20: 2488 | O20: 2688 | P20: 3099 | Q20: DENKA | T20: Off Grade Stocks And Sales
C21: 1 | D21: 45261 | E21: 533 | F21: Darshan | G21: 240 | H21: 115 | I21: 240 | T21: New Input
C22: 2 | D22: 45261 | E22: 534 | F22: Popular | G22: 300 | H22: 169 | N22: 300 | T22: Srl No. | U22: Date | V22: Details | W22: Qty
C23: 3 | D23: 45262 | E23: 535 | F23: Popular | G23: 6000 | H23: 172 | M23: 6000 | T23: 1 | U23: 45265 | V23: mix | W23: 17810
C24: 4 | D24: 45262 | E24: 536 | F24: KDM | G24: 1000 | H24: 171 | N24: 1000 | T24: 2 | U24: 45266 | V24: mix | W24: 15590
C25: 5 | D25: 45262 | E25: RR | F25: Meet Products | G25: 500 | H25: 117 | I25: 500 | T25: 3 | U25: 45274 | V25: superbond | W25: 10000
C26: 6 | D26: 45262 | E26: GTC 90 | F26: Growmore | G26: 880 | H26: 158, 200 | J26: 500 | Q26: 380 | T26: 4 | U26: 45291 | V26: mix - JP | W26: 16960
C27: 7 | D27: 45264 | E27: GTC 91 | F27: Aditya | G27: 6000 | H27: 140, 160 | J27: 4000 | K27: 2000 | T27: 5
C28: 8 | D28: 45264 | E28: GTC 92 | F28: Veena | G28: 1340 | H28: 172, 200 | N28: 500 | Q28: 840 | T28: 6
C29: 9 | D29: 45264 | E29: RR | F29: Gurpreet | G29: 1000 | H29: 120, 195 | I29: 700 | Q29: 300 | T29: 7
C30: 10 | D30: 45264 | E30: 539 | F30: Seamless | G30: 200 | H30: 185 | O30: 200 | T30: 8
C31: 11 | D31: 45264 | E31: 540 | F31: Reliable | G31: 1000 | H31: 165 | K31: 1000
C32: 12 | D32: 37961 | E32: RR | F32: Shri Ganpatye | G32: 100 | H32: 200 | Q32: 100 | T32: Total New Input:- | W32: =SUM(W23:W30) -> 60360
C33: 13 | D33: 45265 | E33: GTC 93 | F33: Aditya | G33: 5500 | H33: 156, 160 | M33: 3000 | N33: 2000 | O33: 500 | T33: Old Stock C/F:- | W33: 194753
C34: 14 | D34: 45267 | E34: 544 | F34: Mine Chem | G34: 1000 | H34: 143, 163 | J34: 500 | N34: 500 | T34: Total Stocks New & Old :- | W34: =SUM(W32,W33) -> 255113
C35: 15 | D35: 45267 | E35: 545 | F35: Chandan Synthetic | G35: 6000 | H35: 115, 139 | I35: 4000 | J35: 2000 | T35: LESS SALES: (as per sales sheet) | W35: ='Dec 2023'!$I$101 -> 69540
C36: 16 | D36: 45268 | E36: 546 | F36: Raj Inds | G36: 1000 | H36: 160 | P36: 1000
C37: 17 | D37: 45268 | E37: 547 | F37: Paradise | G37: 3000 | H37: 163 | L37: 3000 | T37: NET QTY AVAILABLE: | W37: =SUM(W34-W35) -> 185573
C38: 18 | D38: 45269 | E38: GTC 95 | F38: Paresh Pure | G38: 2000 | H38: 169 | M38: 2000
C39: 19 | D39: 45269 | E39: 548 | F39: Divysai | G39: 500 | H39: 161 | N39: 500
C40: 20 | D40: 45269 | E40: 550 | F40: Growmore | G40: 100 | H40: 172 | N40: 100
C41: 21 | D41: 45269 | E41: 551 | F41: Bhavya | G41: 3000 | H41: 157 | K41: 3000
C42: 22 | D42: 45269 | E42: 552 | F42: Siva | G42: 10000 | H42: 104 | I42: 10000
C43: 23 | D43: 45271 | E43: GTC 96 | F43: Veekay | G43: 1000 | H43: 161 | K43: 1000
C44: 24 | D44: 45271 | E44: GTC 97 | F44: Growmore | G44: 1000 | H44: 200 | Q44: 1000
C45: 26 | D45: 45271 | E45: 553 | F45: Vasudha | G45: 1500 | H45: 175, 172, 180 | L45: 500 | M45: 500 | O45: 500
C46: 27 | D46: 45271 | E46: 554 | F46: Popular | G46: 600 | H46: 164, 166, 190 | N46: 200 | O46: 200 | Q46: 200
C47: 28 | D47: 45241 | E47: 555 | F47: Bhavya | G47: 2000 | H47: 139 | J47: 2000
C48: 29 | D48: 45241 | E48: 556 / 557 | F48: Chemi Care | G48: 4000 | H48: 139 | J48: 4000
C49: 30 | D49: 45241 | E49: 558 | F49: SKR | G49: 3000 | H49: 159 | K49: 3000
C50: 31 | D50: 45241 | E50: 559 | F50: Shree Mahalaxmi | G50: 420 | H50: 115 | I50: 420
C51: 32 | D51: 45272 | E51: 560 | F51: Shree Mahalaxmi | G51: 1000 | H51: 141 | J51: 1000
C52: 33 | D52: 45272 | E52: 562 | F52: Shree Mahalaxmi | G52: 960 | H52: 115 | I52: 960
C53: 34 | D53: 45272 | E53: GTC 98 | F53: Paresh Pure | G53: 275 | H53: 146 | J53: 275
C54: 35 | D54: 45274 | E54: 564 | F54: Reliable | G54: 1040 | H54: 120, 40 | I54: 1000 | Q54: 40
C55: 36 | D55: 45274 | E55: 565 | F55: Mahalaxmi Chemicals | G55: 120 | H55: 164 | L55: 120
C56: 37 | D56: 45274 | E56: 566 | F56: Fortune | G56: 1000 | H56: 125 | I56: 1000
C57: 38 | D57: 45275 | E57: 568 | F57: Akshat Corp | G57: 165 | H57: 120, 180 | I57: 120 | K57: 25
C58: 39 | D58: 45275 | E58: RR | F58: Meet Products | G58: 300 | H58: 147 | J58: 300
C59: 40 | D59: 45275 | E59: 570 | F59: Aditya | G59: 4500 | H59: 320 | I59: 4500
C60: 41 | D60: 45276 | E60: 571 | F60: Mangalam | G60: 300 | H60: 120, 147 | I60: 200 | J60: 100
C61: 42 | D61: 45277 | E61: 573 | F61: Siva | G61: 10000 | H61: 104 | I61: 10000
C62: 43 | D62: 45275 | E62: GTC 101 | F62: Popular | G62: 2000 | H62: 164 | O62: 2000
C63: 44 | D63: 45278 | E63: GTC 102 | F63: Popular | G63: 6000 | H63: 170 | M63: 6000
C64: 45 | D64: 45278 | E64: 574 | F64: Om Neelkhant | G64: 2000 | H64: 155 | N64: 2000
C65: 46 | D65: 45278 | E65: 575 | F65: Yash Corp | G65: 2000 | H65: 155 | N65: 2000
C66: 47 | D66: 45278 | E66: 576 | F66: Shree Gayatri | G66: 2400 | H66: 155 | N66: 2400
C67: 48 | D67: 45279 | E67: 577 | F67: Paramount | G67: 16500 | H67: 112, 100 | I67: 16500
C68: 49 | D68: 45279 | E68: 578 | F68: Surya Poly | G68: 200 | H68: 320 | I68: 200
C69: 50 | D69: 45280 | E69: GTC 103 | F69: AP Bonding | G69: 7000 | H69: 139, 165 | J69: 6000 | L69: 1000
C70: 51 | D70: 45280 | E70: GTC 104 | F70: Aditya | G70: 1500 | H70: 165 | L70: 1500
C71: 52 | D71: 45280 | E71: GTC 105 | F71: Aditya | G71: 1500 | H71: 158 | K71: 1500
C72: 53 | D72: 45280 | E72: GTC 106 | F72: Mine Chem | G72: 25 | H72: 145 | J72: 25
C73: 54 | D73: 45280 | E73: GTC 107 | F73: Growmore | G73: 500 | H73: 152 | J73: 500
C74: 55 | D74: 45281 | E74: 579 | F74: Divysai | G74: 25 | H74: 162 | N74: 25
C75: 56 | D75: 45282 | E75: 584 | F75: Vasudha | G75: 1200 | H75: 172, 120 | I75: 200 | O75: 1000
C76: 57 | D76: 45283 | E76: 585 | F76: Divysai | G76: 500 | H76: 162 | N76: 500
C77: 58 | D77: 45284 | E77: 587 | F77: Can Image | G77: 5000 | H77: 170 | M77: 5000
C78: 59 | D78: 45285 | E78: 588 | F78: Raj Inds | G78: 1000 | H78: 156 | K78: 1000
C79: 60 | D79: 45285 | E79: 589 | F79: Om Shakti | G79: 2000 | H79: 119 | I79: 2000
C80: 61 | D80: 45285 | E80: 592 | F80: BSB Indus | G80: 4500 | H80: 113 | I80: 4500
C81: 62 | D81: 45286 | E81: 593 | F81: Siva | G81: 10000 | H81: 104 | I81: 10000
C82: 63 | D82: 45286 | E82: RR | F82: Shri Ganpatye | G82: 300 | H82: 180, 200 | K82: 100 | Q82: 200
C83: 64 | D83: 45285 | E83: GTC - 111 | F83: Mine Chem | G83: 250 | H83: 144 | J83: 250
C84: 65 | D84: 45287 | E84: 595 | F84: Paresh Pure | G84: 1000 | H84: 117 | I84: 1000
C85: 66 | D85: 45289 | E85: 596 | F85: Meet Products | G85: 800 | H85: 117, 189 | I85: 500 | Q85: 300
C86: 67 | D86: 45289 | E86: GTC - 112 | F86: Popular | G86: 450 | H86: 169, 189 | O86: 250 | Q86: 200
C87: 68 | D87: 45290 | E87: 597 | F87: Fortune | G87: 597 | H87: 125 | I87: 1000
C88: 69 | F88: Rally Chem | G88: 8000 | H88: 162, 206
C89: 70 | F89: KK Dye | G89: 500 | H89: 209
C90: 71 | F90: Vasudha | G90: 520 | H90: 119, 199
C91: 72 | F91: AP Bonding | G91: 1000 | H91: 162
C92: 73 | F92: Growmore | G92: 500 | H92: 200
C93: 74 | F93: Shri Ganpatye | G93: 300 | H93: 180, 190
C94: 75 | F94: Guruji | G94: 1100 | H94: 162, 200
C95: 76 | F95: Purvi Enterprise | G95: 40 | H95: 195
C96: 77 | F96: Gurpreet | G96: 340 | H96: 205
C97: 78 | F97: Paramount | G97: 4000 | H97: 117, 325
C98: 79 | F98: Fortune | G98: 500 | H98: 125
C99: 80 | F99: Chemi Care | G99: 1000 | H99: 163
C100: 81 | F100: Shree Mahalaxmi | G100: 1000 | H100: 147
C101: TOTAL | G101: =SUM(G21:G100) -> 171887 | I101: =SUM(I21:I100) -> 69540 | J101: =SUM(J21:J100) -> 21450 | K101: =SUM(K21:K100) -> 12625 | L101: =SUM(L21:L100) -> 6120 | M101: =SUM(M21:M100) -> 22500 | N101: =SUM(N21:N100) -> 12025 | O101: =SUM(O21:O100) -> 4650 | P101: =SUM(P21:P100) -> 1000 | Q101: =SUM(Q21:Q100) -> 3560
I103: =SUM('Dec 2023'!$I$101:'Dec 2023'!$Q$101) -> 153470

Sheet Jan 2024
D4: Jan 2024 Sales in Nutsell | O4: Prime | P4: Off Grade | Q4: Total
D5: Grades | E5: Off Grade | F5: 1799 | G5: 2699 | H5: 588 | I5: 2088 | J5: 2488 | K5: 2688 | L5: 3099 | M5: DENKA | N5: TOTAL
D6: Old Stck CF | E6: 185573 | F6: 16625 | G6: 12375 | H6: 26080 | I6: 13500 | J6: 35700 | K6: 22600 | L6: 33400 | M6: 25960 | N6: =SUM(E6:M6) -> 371813 | O6: =SUM(F6:M6) -> 186240 | P6: =E6 -> 185573 | Q6: =O6+P6 -> 371813
D7: New Input In Dec | E7: =W32 -> 58678 | I7: 18000 | O7: =SUM(F7:M7) -> 18000 | P7: =E7 -> 58678 | Q7: =O7+P7 -> 76678
D8: Sales In Jan | E8: ='Jan 2024'!$I$101 -> 24780 | F8: ='Jan 2024'!$J$101 -> 11025 | G8: ='Jan 2024'!$K$101 -> 2950 | H8: ='Jan 2024'!$L$101 -> 4500 | I8: ='Jan 2024'!$M$101 -> 5500 | J8: ='Jan 2024'!$N$101 -> 5415 | K8: ='Jan 2024'!$O$101 -> 2550 | L8: ='Jan 2024'!$P$101 -> 0 | M8: ='Jan 2024'!$Q$101 -> 4580 | N8: =SUM(E8:M8) -> 61300 | O8: =SUM(F8:M8) -> 36520 | P8: =E8 -> 24780 | Q8: =SUM(O8,P8) -> 61300
D9: Net Stocks CF | E9: =SUM(E6,E7-E8) -> 219471 | F9: =SUM(F6,F7-F8) -> 5600 | G9: =SUM(G6,G7-G8) -> 9425 | H9: =SUM(H6,H7-H8) -> 21580 | I9: =SUM(I6,I7-I8) -> 26000 | J9: =SUM(J6,J7-J8) -> 30285 | K9: =SUM(K6,K7-K8) -> 20050 | L9: =SUM(L6,L7-L8) -> 33400 | M9: =SUM(M6,M7-M8) -> 21380 | N9: =SUM(N6+N7-N8) -> 310513 | O9: =SUM(F9:M9) -> 167720 | P9: =E9 -> 219471 | Q9: =SUM(O9,P9) -> 387191
C11: PRIME INPUT DETAILS | E11: GRADES | F11: 1799 | G11: 2699 | H11: 588 | I11: 2088 | J11: 2488 | K11: 2688 | L11: 3099 | M11: DENKA | N11: TOTAL | O11: FROM | P11: IMP NO
C12: SRL NO | D12: MAKE | E12: DATE | N12: =SUM(F12:M12) -> 0
C13: 1 | D13: Wanwei | E13: 45310 | I13: 18000
C14: 2 | D14: IM
C15: 3 | D15: IM
C16: 4 | D16: Wanwei
C17: 5 | D17: Denka
C18: TOTAL | F18: =SUM(F12:F17) -> 0 | G18: =SUM(G12:G17) -> 0 | H18: =SUM(H12:H17) -> 0 | I18: =SUM(I12:I17) -> 18000 | J18: =SUM(J12:J17) -> 0 | K18: =SUM(K12:K17) -> 0 | L18: =SUM(L12:L17) -> 0 | M18: =SUM(M12:M17) -> 0 | N18: =SUM(F18:M18) -> 18000
C20: Srl No | D20: Date | E20: Inv No | F20: Party | G20: Qty | H20: Price | I20: Off Grade | J20: 1799 | K20: 2699 | L20: 588 | M20: 2088 | N20: 2488 | O20: 2688 | P20: 3099 | Q20: DENKA | T20: Off Grade Stocks And Sales
C21: 1 | D21: 45292 | E21: 598 | F21: Mine Chem | G21: 1000 | H21: 146 | J21: 1000 | T21: New Input
C22: 2 | D22: 45292 | E22: 599 | F22: Akshat Corp | G22: 165 | H22: 120, 180 | I22: 140 | K22: 25 | T22: Srl No. | U22: Date | V22: Details | W22: Qty
C23: 3 | D23: 45293 | E23: GTC 114 | F23: Growmore | G23: 2500 | H23: 155, 200 | J23: 1500 | Q23: 1000 | T23: 1 | U23: 45296 | V23: mix JP | W23: 19115
C24: 4 | D24: 45294 | E24: RR | F24: Gurpreet | G24: 500 | H24: 120, 200 | I24: 300 | Q24: 200 | T24: 2 | U24: 45296 | V24: mix JP | W24: 20661
C25: 5 | D25: 45294 | E25: GTC 115 | F25: Veena | G25: 500 | H25: 171 | N25: 500 | T25: 3 | U25: 45301 | V25: mix JP | W25: 18902
C26: 6 | D26: 45294 | E26: GTC 116 | F26: Mine Chem | G26: 250 | H26: 151 | J26: 250 | T26: 4
C27: 7 | D27: 45295 | E27: 600 | F27: Vasudha | G27: 500 | H27: 180 | L27: 500 | T27: 5
C28: 8 | D28: 45295 | E28: 601 | F28: Surya Poly | G28: 2500 | H28: 152, 170, 200 | J28: 500 | O28: 1000 | Q28: 1000 | T28: 6
C29: 9 | D29: 45297 | E29: 603 | F29: Meet Products | G29: 200 | H29: 150 | J29: 200 | T29: 7
C30: 10 | D30: 45297 | E30: 604 | F30: KDM | G30: 700 | H30: 114 | I30: 700 | T30: 8
C31: 11 | D31: 45299 | E31: 605 | F31: Paresh Pure | G31: 1000 | H31: 116 | I31: 1000
C32: 12 | D32: 45299 | E32: 606 | F32: Akshat Corp | G32: 205 | H32: 120, 180 | I32: 180 | K32: 25 | T32: Total New Input:- | W32: =SUM(W23:W30) -> 58678
C33: 13 | D33: 45299 | E33: 607 | F33: BSB Indus | G33: 1000 | H33: 145 | J33: 1000 | T33: Old Stock C/F:- | W33: 185573
C34: 14 | D34: 45299 | E34: 608 | F34: Doshi Chem | G34: 300 | H34: 162 | K34: 300 | T34: Total Stocks New & Old :- | W34: =SUM(W32,W33) -> 244251
C35: 15 | D35: 45299 | E35: 609 | F35: Darshan | G35: 140 | H35: 115 | I35: 140 | T35: LESS SALES: (as per sales sheet) | W35: ='Jan 2024'!$I$101 -> 24780
C36: 16 | D36: 45299 | E36: GTC 117 | F36: Popular | G36: 1000 | H36: 145 | J36: 1000
C37: 17 | D37: 45301 | E37: 610 | F37: Shree Mahalaxmi | G37: 2000 | H37: 115 | I37: 2000 | T37: NET QTY AVAILABLE: | W37: =SUM(W34-W35) -> 219471
C38: 18 | D38: 45301 | E38: 611 | F38: Siva | G38: 10000 | H38: 105 | I38: 10000
C39: 19 | D39: 45302 | E39: 612 | F39: Can Image | G39: 3000 | H39: 170 | M39: 3000
C40: 20 | D40: 45303 | E40: RR | F40: Patidar | G40: 1000 | H40: 164 | K40: 1000
C41: 21 | D41: 45303 | E41: GTC 118 | F41: Popular | G41: 1000 | H41: 170, 194 | N41: 175 | O41: 525 | Q41: 300
C42: 22 | D42: 45304 | E42: 615 | F42: Fortune | G42: 1000 | H42: 120 | I42: 1000
C43: 23 | D43: 45306 | E43: 616 | F43: Anmol | G43: 25 | H43: 145 | J43: 25
C44: 24 | D44: 45306 | E44: 617 | F44: Empowera | G44: 1480 | H44: 188, 192 | Q44: 1480
C45: 26 | D45: 45306 | E45: 618 | F45: Guruji | G45: 1000 | H45: 115 | I45: 1000
C46: 27 | D46: 45306 | E46: 619 | F46: Mine Chem | G46: 200 | H46: 127 | I46: 200
C47: 28 | D47: 45306 | E47: GTC 120 | F47: Aditya | G47: 500 | H47: 164 | K47: 500
C48: 29 | D48: 45306 | E48: GTC 121 | F48: AP Bonding | G48: 3000 | H48: 169 | L48: 3000
C49: 30 | D49: 45308 | E49: 620 | F49: SKS Fine | G49: 2000 | H49: 119 | I49: 2000
C50: 31 | D50: 45309 | E50: 622 | F50: Shree Mahalaxmi | G50: 1000 | H50: 165 | L50: 1000
C51: 32 | D51: 45309 | E51: 625 | F51: Vasudha | G51: 1600 | H51: 169, 170 | K51: 600 | O51: 1000
C52: 33 | D52: 45303 | E52: 613 | F52: Prime Chem | G52: 100 | H52: 118 | I52: 100
C53: 34 | D53: 45309 | E53: GTC 123 | F53: Veena | G53: 500 | H53: 172 | K53: 500 | Q53: 200
C54: 35 | D54: 45311 | E54: GTC 125 | F54: AP Bonding | G54: 500 | H54: 157 | M54: 2000 | N54: 3000
C55: 36 | D55: 45311 | E55: 626 | F55: Abeer Ente | G55: 20 | H55: 120 | I55: 20
C56: 37 | D56: 45314 | E56: 627 | F56: SKS Fine | G56: 200 | H56: 195 | Q56: 200
C57: 38 | D57: 45314 | E57: 628 | F57: Chandan | G57: 4000 | H57: 115 | I57: 4000
C58: 39 | D58: 45314 | E58: 629 | F58: Divysai | G58: 500 | H58: 157 | M58: 500
C59: 40 | D59: 45315 | E59: 630 | F59: Chemi Care | G59: 2000 | H59: 144 | J59: 2000
C60: 41 | D60: 45315 | E60: 631 | F60: Durga Chem | G60: 200 | H60: 185 | Q60: 200
C61: 42 | D61: 45315 | E61: 632 | F61: Mine Chem | G61: 250 | H61: 148 | J61: 250
C62: 43 | D62: 45315 | E62: GTC 127 | F62: Veena | G62: 500 | H62: 171 | N62: 500
C63: 44 | D63: 45316 | E63: 635 | F63: Fortune | G63: 1000 | H63: 125 | I63: 1000
C64: 45 | D64: 45316 | E64: 636 | F64: Aggarwal Tiles | G64: 1000 | H64: 110 | I64: 1000
C65: 46 | D65: 45316 | E65: 638 | F65: Shree Mahalaxmi | G65: 25 | H65: 170 | O65: 25
C66: 47 | D66: 45320 | E66: 640 | F66: Papyrus | G66: 200 | H66: 165 | N66: 200
C67: 48 | D67: 45320 | E67: 641 | F67: Papfibre | G67: 40 | H67: 165 | N67: 40
C68: 49 | D68: 45320 | E68: 642 | F68: Growmore | G68: 642 | H68: 1000 | N68: 1000
C69: 50 | D69: 45321 | E69: 645 | F69: S K International | G69: 300 | H69: 145 | J69: 300
C70: 51 | D70: 45322 | E70: GTC 129 | F70: Aditya | G70: 3000 | H70: 145 | J70: 3000
C71: 52 | F71: Aditya | G71: 1500 | H71: 158
C72: 53 | F72: Mine Chem | G72: 25 | H72: 145
C73: 54 | F73: Growmore | G73: 500 | H73: 152
C74: 55 | F74: Divysai | G74: 25 | H74: 162
C75: 56 | F75: Vasudha | G75: 1200 | H75: 172, 120
C76: 57 | F76: Divysai | G76: 500 | H76: 162
C77: 58 | F77: Can Image | G77: 5000 | H77: 170
C78: 59 | F78: Raj Inds | G78: 1000 | H78: 156
C79: 60 | F79: Om Shakti | G79: 2000 | H79: 119
C80: 61 | F80: BSB Indus | G80: 4500 | H80: 113
C81: 62 | F81: Siva | G81: 10000 | H81: 104
C82: 63 | F82: Shri Ganpatye | G82: 300 | H82: 180, 200
C83: 64 | F83: Mine Chem | G83: 250 | H83: 144
C84: 65 | F84: Paresh Pure | G84: 1000 | H84: 117
C85: 66 | F85: Meet Products | G85: 800 | H85: 117, 189
C86: 67 | F86: Popular | G86: 450 | H86: 169, 189
C87: 68 | F87: Fortune | G87: 597 | H87: 125
C88: 69 | F88: Rally Chem | G88: 8000 | H88: 162, 206
C89: 70 | F89: KK Dye | G89: 500 | H89: 209
C90: 71 | F90: Vasudha | G90: 520 | H90: 119, 199
C91: 72 | F91: AP Bonding | G91: 1000 | H91: 162
C92: 73 | F92: Growmore | G92: 500 | H92: 200
C93: 74 | F93: Shri Ganpatye | G93: 300 | H93: 180, 190
C94: 75 | F94: Guruji | G94: 1100 | H94: 162, 200
C95: 76 | F95: Purvi Enterprise | G95: 40 | H95: 195
C96: 77 | F96: Gurpreet | G96: 340 | H96: 205
C97: 78 | F97: Paramount | G97: 4000 | H97: 117, 325
C98: 79 | F98: Fortune | G98: 500 | H98: 125
C99: 80 | F99: Chemi Care | G99: 1000 | H99: 163
C100: 81 | F100: Shree Mahalaxmi | G100: 1000 | H100: 147
C101: TOTAL | G101: =SUM(G21:G100) -> 104689 | I101: =SUM(I21:I100) -> 24780 | J101: =SUM(J21:J100) -> 11025 | K101: =SUM(K21:K100) -> 2950 | L101: =SUM(L21:L100) -> 4500 | M101: =SUM(M21:M100) -> 5500 | N101: =SUM(N21:N100) -> 5415 | O101: =SUM(O21:O100) -> 2550 | P101: =SUM(P21:P100) -> 0 | Q101: =SUM(Q21:Q100) -> 4580
I103: =SUM('Jan 2024'!$I$101:'Jan 2024'!$Q$101) -> 61300

Sheet Feb 24
D4: Feb 2024 Sales in Nutsell | O4: Prime | P4: Off Grade | Q4: Total
D5: Grades | E5: Off Grade | F5: 1799 | G5: 2699 | H5: 588 | I5: 2088 | J5: 2488 | K5: 2688 | L5: 3099 | M5: DENKA | N5: TOTAL
D6: Old Stck CF | E6: 219471 | F6: 5600 | G6: 9425 | H6: 21580 | I6: 26000 | J6: 30285 | K6: 20050 | L6: 33400 | M6: 21380 | N6: =SUM(E6:M6) -> 387191 | O6: =SUM(F6:M6) -> 167720 | P6: 219471 | Q6: =O6+P6 -> 387191
D7: New Input In Dec | E7: =W32 -> 0 | O7: =SUM(F7:M7) -> 0 | P7: =E7 -> 0 | Q7: =O7+P7 -> 0
D8: Sales In Feb | E8: ='Feb 24'!$I$101 -> 33780 | F8: ='Feb 24'!$J$101 -> 5575 | G8: ='Feb 24'!$K$101 -> 5500 | H8: ='Feb 24'!$L$101 -> 11460 | I8: ='Feb 24'!$M$101 -> 13025 | J8: ='Feb 24'!$N$101 -> 3300 | K8: ='Feb 24'!$O$101 -> 3500 | L8: ='Feb 24'!$P$101 -> 14975 | M8: ='Feb 24'!$Q$101 -> 6980 | N8: =SUM(E8:M8) -> 98095 | O8: =SUM(F8:M8) -> 64315 | P8: =E8 -> 33780 | Q8: =SUM(O8,P8) -> 98095
D9: Net Stocks CF | E9: =SUM(E6,E7-E8) -> 185691 | F9: =SUM(F6,F7-F8) -> 25 | G9: =SUM(G6,G7-G8) -> 3925 | H9: =SUM(H6,H7-H8) -> 10120 | I9: =SUM(I6,I7-I8) -> 12975 | J9: =SUM(J6,J7-J8) -> 26985 | K9: =SUM(K6,K7-K8) -> 16550 | L9: =SUM(L6,L7-L8) -> 18425 | M9: =SUM(M6,M7-M8) -> 14400 | N9: =SUM(N6+N7-N8) -> 289096 | O9: =SUM(F9:M9) -> 103405 | P9: 185691 | Q9: =SUM(O9,P9) -> 289096
C11: PRIME INPUT DETAILS | E11: GRADES | F11: 1799 | G11: 2699 | H11: 588 | I11: 2088 | J11: 2488 | K11: 2688 | L11: 3099 | M11: DENKA | N11: TOTAL | O11: FROM | P11: IMP NO
C12: SRL NO | D12: MAKE | E12: DATE | N12: =SUM(F12:M12) -> 0
C13: 1 | D13: Wanwei
C14: 2 | D14: IM
C15: 3 | D15: IM
C16: 4 | D16: Wanwei
C17: 5 | D17: Denka
C18: TOTAL | F18: =SUM(F12:F17) -> 0 | G18: =SUM(G12:G17) -> 0 | H18: =SUM(H12:H17) -> 0 | I18: =SUM(I12:I17) -> 0 | J18: =SUM(J12:J17) -> 0 | K18: =SUM(K12:K17) -> 0 | L18: =SUM(L12:L17) -> 0 | M18: =SUM(M12:M17) -> 0 | N18: =SUM(F18:M18) -> 0
C20: Srl No | D20: Date | E20: Inv No | F20: Party | G20: Qty | H20: Price | I20: Off Grade | J20: 1799 | K20: 2699 | L20: 588 | M20: 2088 | N20: 2488 | O20: 2688 | P20: 3099 | Q20: DENKA | T20: Off Grade Stocks And Sales
C21: 1 | D21: 45323 | E21: 646 | F21: Popular | G21: 2000 | H21: 145 | J21: 2000 | T21: New Input
C22: 2 | D22: 45324 | E22: 648 | F22: Om Neelkhant | G22: 1500 | H22: 119 | I22: 1900 | T22: Srl No. | U22: Date | V22: Details | W22: Qty
C23: 3 | D23: 45328 | E23: 653 | F23: Mine Chem | G23: 1325 | H23: 148, 160 | J23: 1125 | N23: 200 | T23: 1 | V23: mix JP
C24: 4 | D24: 45328 | E24: 654 | F24: Reliable | G24: 1500 | H24: 165 | K24: 1500 | T24: 2 | V24: mix JP
C25: 5 | D25: 45327 | E25: GC 130 | F25: Veena | G25: 600 | H25: 200 | Q25: 600 | T25: 3 | V25: mix JP
C26: 6 | D26: 45329 | E26: 655 | F26: BSB Indus | G26: 1000 | H26: 155, 158, 168 | M26: 600 | N26: 200 | O26: 200 | T26: 4
C27: 7 | D27: 45328 | E27: GTC 132 | F27: AP Bonding | G27: 5500 | H27: 154, 166 | K27: 1500 | M27: 4000 | T27: 5
C28: 8 | D28: 45330 | E28: 657 | F28: Vasudha | G28: 3000 | H28: 168 | K28: 2000 | O28: 1000 | T28: 6
C29: 9 | D29: 45331 | E29: 658 | F29: Kraft | G29: 1000 | H29: 112 | I29: 1000 | T29: 7
C30: 10 | D30: 45331 | E30: 659 | F30: Fortune | G30: 1120 | H30: 118, 125 | I30: 1120 | T30: 8
C31: 11 | D31: 45331 | E31: 660 | F31: Darshan | G31: 240 | H31: 115 | I31: 240
C32: 12 | D32: 45334 | E32: 661 | F32: Chemi Care | G32: 360 | H32: 167.5 | L32: 360 | T32: Total New Input:- | W32: =SUM(W23:W30) -> 0
C33: 13 | D33: 45334 | E33: 662 | F33: Patel Adhesives | G33: 17000 | H33: 164, 112 | I33: 1000 | O33: 1025 | P33: 14975 | T33: Old Stock C/F:- | W33: 185573
C34: 14 | D34: 45334 | E34: 663 | F34: Guruji | G34: 2000 | H34: 114 | I34: 2000 | T34: Total Stocks New & Old :- | W34: =SUM(W32,W33) -> 185573
C35: 15 | D35: 45335 | E35: 664 | F35: Mine Chem | G35: 200 | H35: 190 | Q35: 200 | T35: LESS SALES: (as per sales sheet) | W35: ='Feb 24'!$I$101 -> 33780
C36: 16 | D36: 45336 | E36: 665 | F36: Mine Chem | G36: 100 | H36: 160 | N36: 100
C37: 17 | D37: 45336 | E37: 666 | F37: Shree Mahalaxmi | G37: 25 | H37: 170 | O37: 25 | T37: NET QTY AVAILABLE: | W37: =SUM(W34-W35) -> 151793
C38: 18 | D38: 45337 | E38: 667 | F38: Mahalaxmi Chemicals | G38: 10000 | H38: 165 | L38: 10000
C39: 19 | D39: 45337 | E39: 668 | F39: Vasudha | G39: 1000 | H39: 171 | L39: 1000
C40: 20 | D40: 45337 | E40: 669 | F40: Mahalaxmi Chemicals | G40: 100 | H40: 167 | L40: 100
C41: 21 | D41: 45335 | E41: GTC 134 | F41: Veena | G41: 500 | H41: 171 | N41: 500
C42: 22 | D42: 45338 | E42: 670 | F42: Om Shakti | G42: 1400 | H42: 119 | I42: 1400
C43: 23 | D43: 45338 | E43: RR | F43: Meet Products | G43: 200 | H43: 189 | Q43: 200
C44: 24 | D44: 45338 | E44: 672 | F44: Can Image | G44: 5000 | H44: 170 | M44: 5000
C45: 26 | D45: 45338 | E45: GTC 135 | F45: Surya | G45: 2000 | H45: 170, 200 | O45: 1000 | Q45: 1000
C46: 27 | D46: 45324 | E46: RR | F46: Meet Products | G46: 800 | H46: 120 | I46: 800
C47: 28 | D47: 45324 | E47: RR | F47: Meet Products | G47: 480 | H47: 148, 189 | J47: 300 | Q47: 180
C48: 29 | D48: 45324 | E48: 651 | F48: Om Shakti | G48: 1500 | H48: 143 | J48: 1500
C49: 30 | D49: 45324 | E49: 652 | F49: Shree Mahalaxmi | G49: 200 | H49: 115 | I49: 200
C50: 31 | D50: 45339 | E50: 675 | F50: Mine Chem | G50: 500 | H50: 128 | I50: 500
C51: 32 | D51: 45339 | E51: GTC 137 | F51: Pragati Enter | G51: 300 | H51: 185 | Q51: 300
C52: 33 | D52: 45339 | E52: GTC 138 | F52: Popular | G52: 1000 | H52: 190, 194 | Q52: 1000
C53: 34 | D53: 45339 | E53: GTC 139 | F53: Growmore | G53: 650 | H53: 155 | J53: 650
C54: 35 | D54: 45339 | E54: GTC 140 | F54: Mine Chem | G54: 300 | H54: 161 | N54: 300
C55: 36 | D55: 45339 | E55: GTC 141 | F55: Doshi Chem | G55: 500 | H55: 185 | Q55: 500
C56: 37 | D56: 45341 | E56: 676 | F56: Can Image | G56: 1000 | H56: 190 | Q56: 1000
C57: 38 | D57: 45342 | E57: 677 | F57: AP Enterprise | G57: 250 | H57: 184 | O57: 250
C58: 39 | D58: 45341 | E58: GTC 142 | F58: Guruji | G58: 625 | H58: 153 | M58: 625
C59: 40 | D59: 45341 | E59: GTC 143 | F59: Aditya | G59: 1000 | H59: 153 | M59: 1000
C60: 41 | D60: 45342 | E60: GTC 144 | F60: Rally Chem | G60: 2000 | H60: 182 | Q60: 2000
C61: 42 | D61: 45342 | E61: GTC 146 | F61: Growmore | G61: 500 | H61: 170 | N61: 500
C62: 43 | D62: 45342 | E62: GTC 147 | F62: Divysai | G62: 600 | H62: 154 | M62: 600
C63: 44 | D63: 45342 | E63: GTC 148 | F63: Vasudha | G63: 1000 | H63: 147 | M63: 1000
C64: 45 | D64: 45343 | E64: 679 | F64: Chandan Synthetic | G64: 4000 | H64: 115 | I64: 4000
C65: 46 | D65: 45344 | E65: 680 | F65: Vinit Polymers | G65: 18000 | H65: 110 | I65: 18000
C66: 47 | D66: 45346 | E66: GTC 149 | F66: Sparkle Inds | G66: 500 | H66: 167.5 | K66: 500
C67: 48 | D67: 45350 | E67: GTC 150 | F67: Growmore | G67: 1000 | H67: 170 | N67: 1000
C68: 49 | D68: 45348 | E68: 681 | F68: Fortune | G68: 1000 | H68: 125 | I68: 1000
C69: 50 | D69: 45348 | E69: 682 | F69: Shree Mahalaxmi | G69: 20 | H69: 115 | I69: 20
C70: 51 | D70: 45348 | E70: 683 | F70: SKS Fine | G70: 200 | H70: 157 | M70: 200
C71: 52 | D71: 45349 | E71: 684 | F71: Popular | G71: 100 | H71: 112 | I71: 100
C72: 53 | D72: 45351 | E72: 686 | F72: KDM | G72: 500 | H72: 117 | I72: 500
C73: 54 | D73: 45351 | E73: GTC 151 | F73: Veena | G73: 500 | H73: 169 | N73: 500
C74: 55 | F74: Divysai | G74: 25 | H74: 162
C75: 56 | F75: Vasudha | G75: 1200 | H75: 172, 120
C76: 57 | F76: Divysai | G76: 500 | H76: 162
C77: 58 | F77: Can Image | G77: 5000 | H77: 170
C78: 59 | F78: Raj Inds | G78: 1000 | H78: 156
C79: 60 | F79: Om Shakti | G79: 2000 | H79: 119
C80: 61 | F80: BSB Indus | G80: 4500 | H80: 113
C81: 62 | F81: Siva | G81: 10000 | H81: 104
C82: 63 | F82: Shri Ganpatye | G82: 300 | H82: 180, 200
C83: 64 | F83: Mine Chem | G83: 250 | H83: 144
C84: 65 | F84: Paresh Pure | G84: 1000 | H84: 117
C85: 66 | F85: Meet Products | G85: 800 | H85: 117, 189
C86: 67 | F86: Popular | G86: 450 | H86: 169, 189
C87: 68 | F87: Fortune | G87: 597 | H87: 125
C88: 69 | F88: Rally Chem | G88: 8000 | H88: 162, 206
C89: 70 | F89: KK Dye | G89: 500 | H89: 209
C90: 71 | F90: Vasudha | G90: 520 | H90: 119, 199
C91: 72 | F91: AP Bonding | G91: 1000 | H91: 162
C92: 73 | F92: Growmore | G92: 500 | H92: 200
C93: 74 | F93: Shri Ganpatye | G93: 300 | H93: 180, 190
C94: 75 | F94: Guruji | G94: 1100 | H94: 162, 200
C95: 76 | F95: Purvi Enterprise | G95: 40 | H95: 195
C96: 77 | F96: Gurpreet | G96: 340 | H96: 205
C97: 78 | F97: Paramount | G97: 4000 | H97: 117, 325
C98: 79 | F98: Fortune | G98: 500 | H98: 125
C99: 80 | F99: Chemi Care | G99: 1000 | H99: 163
C100: 81 | F100: Shree Mahalaxmi | G100: 1000 | H100: 147
C101: TOTAL | G101: =SUM(G21:G100) -> 144117 | I101: =SUM(I21:I100) -> 33780 | J101: =SUM(J21:J100) -> 5575 | K101: =SUM(K21:K100) -> 5500 | L101: =SUM(L21:L100) -> 11460 | M101: =SUM(M21:M100) -> 13025 | N101: =SUM(N21:N100) -> 3300 | O101: =SUM(O21:O100) -> 3500 | P101: =SUM(P21:P100) -> 14975 | Q101: =SUM(Q21:Q100) -> 6980
I103: =SUM('Feb 24'!$I$101:'Feb 24'!$Q$101) -> 98095

Sheet Mar 24
D4: Feb 2024 Sales in Nutsell | O4: Prime | P4: Off Grade | Q4: Total
D5: Grades | E5: Off Grade | F5: 1799 | G5: 2699 | H5: 588 | I5: 2088 | J5: 2488 | K5: 2688 | L5: 3099 | M5: DENKA | N5: TOTAL
D6: Old Stck CF | E6: 185691 | F6: 0 | G6: 3925 | H6: 10120 | I6: 12975 | J6: 26985 | K6: 16550 | L6: 18425 | M6: 14400 | O6: =SUM(F6:M6) -> 103380 | P6: =E6 -> 185691 | Q6: =O6+P6 -> 289071
D7: New Input In Dec | E7: =W32 -> 55474 | F7: 18000 | G7: 18000 | O7: =SUM(F7:M7) -> 36000 | P7: =E7 -> 55474 | Q7: =O7+P7 -> 91474
D8: Sales In March | E8: ='Mar 24'!$I$101 -> 37620 | F8: ='Mar 24'!$J$101 -> 7500 | G8: ='Mar 24'!$K$101 -> 640 | H8: ='Mar 24'!$L$101 -> 5100 | I8: ='Mar 24'!$M$101 -> 12975 | J8: ='Mar 24'!$N$101 -> 5100 | K8: ='Mar 24'!$O$101 -> 3775 | L8: ='Mar 24'!$P$101 -> 1300 | M8: ='Mar 24'!$Q$101 -> 5100 | O8: =SUM(F8:M8) -> 41490 | P8: =E8 -> 37620 | Q8: =SUM(O8,P8) -> 79110
D9: Net Stocks CF | E9: =SUM(E6,E7-E8) -> 203545 | F9: =SUM(F6,F7-F8) -> 10500 | G9: =SUM(G6,G7-G8) -> 21285 | H9: =SUM(H6,H7-H8) -> 5020 | I9: =SUM(I6,I7-I8) -> 0 | J9: =SUM(J6,J7-J8) -> 21885 | K9: =SUM(K6,K7-K8) -> 12775 | L9: =SUM(L6,L7-L8) -> 17125 | M9: =SUM(M6,M7-M8) -> 9300 | N9: =SUM(N6+N7-N8) -> 0 | O9: =SUM(F9:M9) -> 97890 | P9: =E9 -> 203545 | Q9: =SUM(O9,P9) -> 301435
C11: PRIME INPUT DETAILS | E11: GRADES | F11: 1799 | G11: 2699 | H11: 588 | I11: 2088 | J11: 2488 | K11: 2688 | L11: 3099 | M11: DENKA | N11: TOTAL | O11: FROM | P11: IMP NO
C12: SRL NO | D12: MAKE | E12: DATE | N12: =SUM(F12:M12) -> 0
C13: 1 | D13: Wanwei | E13: 45380 | F13: 18000 | G13: 18000
C14: 2 | D14: IM
C15: 3 | D15: IM
C16: 4 | D16: Wanwei
C17: 5 | D17: Denka
C18: TOTAL | F18: =SUM(F12:F17) -> 18000 | G18: =SUM(G12:G17) -> 18000 | H18: =SUM(H12:H17) -> 0 | I18: =SUM(I12:I17) -> 0 | J18: =SUM(J12:J17) -> 0 | K18: =SUM(K12:K17) -> 0 | L18: =SUM(L12:L17) -> 0 | M18: =SUM(M12:M17) -> 0 | N18: =SUM(F18:M18) -> 36000
C20: Srl No | D20: Date | E20: Inv No | F20: Party | G20: Qty | H20: Price | I20: Off Grade | J20: 1799 | K20: 2699 | L20: 588 | M20: 2088 | N20: 2488 | O20: 2688 | P20: 3099 | Q20: DENKA | T20: Off Grade Stocks And Sales
C21: 1 | D21: 45352 | E21: RR | F21: Amritha | G21: 3000 | H21: 110, 200 | I21: 2000 | Q21: 1000 | T21: New Input
C22: 2 | D22: 45353 | E22: RR | F22: Meet Products | G22: 700 | H22: 117 | I22: 700 | T22: Srl No. | U22: Date | V22: Details | W22: Qty
C23: 3 | D23: 45353 | E23: 690 | F23: Om Neelkhant | G23: 1600 | H23: 163 | O23: 1600 | T23: 1 | U23: 45371 | V23: mix JP | W23: 16001
C24: 4 | D24: 45353 | E24: 691 | F24: BSB Indus | G24: 6000 | H24: 116, 156, 164 | I24: 5000 | M24: 600 | O24: 400 | T24: 2 | U24: 45371 | V24: mix JP | W24: 18826
C25: 5 | D25: 45353 | E25: 692 | F25: Akshat | G25: 205 | H25: 119, 179 | I25: 180 | P25: 25 | T25: 3 | U25: 45371 | V25: mix JP | W25: 20647
C26: 6 | D26: 45355 | E26: 693 | F26: Shree Mahalaxmi | G26: 2500 | H26: 115 | I26: 2500 | T26: 4
C27: 7 | D27: 45355 | E27: GTC 152 | F27: Surya | G27: 3000 | H27: 175, 200 | P27: 1000 | Q27: 2000 | T27: 5
C28: 8 | D28: 45355 | E28: GTC 153 | F28: Karnataka | G28: 1000 | H28: 160, 165 | K28: 400 | N28: 600 | T28: 6
C29: 9 | D29: 45356 | E29: 696 | F29: Paresh Pure | G29: 1200 | H29: 120 | I29: 1200 | T29: 7
C30: 10 | D30: 45356 | E30: 703 | F30: RMW | G30: 25 | H30: 175 | L30: 25 | T30: 8
C31: 11 | D31: 45356 | E31: GTC 154 | F31: Popular | G31: 6000 | H31: 158 | M31: 6000
C32: 12 | D32: 45357 | E32: 704 | F32: Atulya Chemicals | G32: 25 | H32: 180 | P32: 25 | T32: Total New Input:- | W32: =SUM(W23:W30) -> 55474
C33: 13 | D33: 45360 | E33: 711 | F33: Vasudha | G33: 775 | H33: 167 | O33: 775 | T33: Old Stock C/F:- | W33: 185691
C34: 14 | D34: 45362 | E34: 713 | F34: Surya | G34: 500 | H34: 199 | Q34: 500 | T34: Total Stocks New & Old :- | W34: =SUM(W32,W33) -> 241165
C35: 15 | D35: 45363 | E35: 714 | F35: Om Shakti | G35: 120 | H35: 4640 | I35: 4640 | T35: LESS SALES: (as per sales sheet) | W35: ='Mar 24'!$I$101 -> 37620
C36: 16 | D36: 45364 | E36: GTC 155 | F36: Popular | G36: 1375 | H36: 157 | M36: 1375
C37: 17 | D37: 45364 | E37: GTC 156 | F37: Divysai | G37: 500 | H37: 160 | N37: 500 | T37: NET QTY AVAILABLE: | W37: =SUM(W34-W35) -> 203545
C38: 18 | D38: 45365 | E38: GTC 157 | F38: Growmore | G38: 1000 | H38: 170 | N38: 1000
C39: 19 | D39: 45366 | E39: 715 | F39: Papyrus | G39: 240 | H39: 170 | K39: 240
C40: 20 | D40: 45367 | E40: 717 | F40: Siva | G40: 10000 | H40: 99 | I40: 10000
C41: 21 | D41: 45369 | E41: 718 | F41: Surya | G41: 500 | H41: 117 | I41: 500
C42: 22 | D42: 45369 | E42: 719 | F42: Can Image | G42: 5000 | H42: 170 | M42: 5000
C43: 23 | D43: 45370 | E43: GTC 159 | F43: Popular | G43: 3075 | H43: 173 | L43: 3075
C44: 24 | D44: 45370 | E44: RR | F44: Fortune | G44: 700 | H44: 125 | I44: 700
C45: 26 | D45: 45371 | E45: GTC 160 | F45: Mahalaxmi Chem | G45: 2000 | H45: 163 | L45: 2000
C46: 27 | D46: 45372 | E46: RR | F46: Gupreet | G46: 650 | H46: 180, 210 | P46: 250 | Q46: 400
C47: 28 | D47: 45372 | E47: RR | F47: Meet Products | G47: 600 | H47: 202 | Q47: 600
C48: 29 | D48: 45372 | E48: GTC 162 | F48: AP Bonding | G48: 2000 | H48: 156 | N48: 2000
C49: 30 | D49: 45372 | E49: GTC 163 | F49: Veena | G49: 600 | H49: 204 | Q49: 600
C50: 31 | D50: 45377 | E50: 726 | F50: Siva | G50: 10000 | H50: 99 | I50: 10000
C51: 32 | D51: 45379 | E51: 727 | F51: Sagar Corp | G51: 100 | H51: 117 | I51: 100
C52: 33 | D52: 45380 | E52: 730 | F52: Chemi Range | G52: 2000 | H52: 146 | J52: 2000
C53: 34 | D53: 45381 | E53: 731 | F53: Orinco | G53: 100 | H53: 110 | I53: 100
C54: 35 | D54: 45372 | E54: GTC 164 | F54: Popular | G54: 1000 | H54: 163 | O54: 1000
C55: 36 | D55: 45380 | E55: GTC 165 | F55: Orinco | G55: 100 | H55: 149 | J55: 100
C56: 37 | D56: 45380 | E56: GTC 166 | F56: Aditya | G56: 2000 | H56: 151 | J56: 2000
C57: 38 | D57: 45380 | E57: GTC 168 | F57: Om Shakti | G57: 1000 | H57: 149 | J57: 1000
C58: 39 | D58: 45380 | E58: GTC 169 | F58: Om Neelkhant | G58: 800 | H58: 149 | J58: 800
C59: 40 | D59: 45380 | E59: GTC 170 | F59: Growmore | G59: 2000 | H59: 156, 170 | J59: 1000 | N59: 1000
C60: 41 | D60: 45381 | E60: GTC 171 | F60: Orinco | G60: 500 | H60: 149 | J60: 100
C61: 42 | D61: 45381 | E61: GTC 172 | F61: Mine Chem | G61: 500 | H61: 151 | J61: 500
C62: 43 | F62: Divysai | G62: 600 | H62: 154
C63: 44 | F63: Vasudha | G63: 1000 | H63: 147
C64: 45 | F64: Chandan Synthetic | G64: 4000 | H64: 115
C65: 46 | F65: Vinit Polymers | G65: 18000 | H65: 110
C66: 47 | F66: Sparkle Inds | G66: 500 | H66: 167.5
C67: 48 | F67: Growmore | G67: 1000 | H67: 170
C68: 49 | F68: Fortune | G68: 1000 | H68: 125
C69: 50 | F69: Shree Mahalaxmi | G69: 20 | H69: 115
C70: 51 | F70: SKS Fine | G70: 200 | H70: 157
C71: 52 | F71: Popular | G71: 100 | H71: 112
C72: 53 | F72: KDM | G72: 500 | H72: 117
C73: 54 | F73: Veena | G73: 500 | H73: 169
C74: 55 | F74: Divysai | G74: 25 | H74: 162
C75: 56 | F75: Vasudha | G75: 1200 | H75: 172, 120
C76: 57 | F76: Divysai | G76: 500 | H76: 162
C77: 58 | F77: Can Image | G77: 5000 | H77: 170
C78: 59 | F78: Raj Inds | G78: 1000 | H78: 156
C79: 60 | F79: Om Shakti | G79: 2000 | H79: 119
C80: 61 | F80: BSB Indus | G80: 4500 | H80: 113
C81: 62 | F81: Siva | G81: 10000 | H81: 104
C82: 63 | F82: Shri Ganpatye | G82: 300 | H82: 180, 200
C83: 64 | F83: Mine Chem | G83: 250 | H83: 144
C84: 65 | F84: Paresh Pure | G84: 1000 | H84: 117
C85: 66 | F85: Meet Products | G85: 800 | H85: 117, 189
C86: 67 | F86: Popular | G86: 450 | H86: 169, 189
C87: 68 | F87: Fortune | G87: 597 | H87: 125
C88: 69 | F88: Rally Chem | G88: 8000 | H88: 162, 206
C89: 70 | F89: KK Dye | G89: 500 | H89: 209
C90: 71 | F90: Vasudha | G90: 520 | H90: 119, 199
C91: 72 | F91: AP Bonding | G91: 1000 | H91: 162
C92: 73 | F92: Growmore | G92: 500 | H92: 200
C93: 74 | F93: Shri Ganpatye | G93: 300 | H93: 180, 190
C94: 75 | F94: Guruji | G94: 1100 | H94: 162, 200
C95: 76 | F95: Purvi Enterprise | G95: 40 | H95: 195
C96: 77 | F96: Gurpreet | G96: 340 | H96: 205
C97: 78 | F97: Paramount | G97: 4000 | H97: 117, 325
C98: 79 | F98: Fortune | G98: 500 | H98: 125
C99: 80 | F99: Chemi Care | G99: 1000 | H99: 163
C100: 81 | F100: Shree Mahalaxmi | G100: 1000 | H100: 147
C101: TOTAL | G101: =SUM(G21:G100) -> 148832 | I101: =SUM(I21:I100) -> 37620 | J101: =SUM(J21:J100) -> 7500 | K101: =SUM(K21:K100) -> 640 | L101: =SUM(L21:L100) -> 5100 | M101: =SUM(M21:M100) -> 12975 | N101: =SUM(N21:N100) -> 5100 | O101: =SUM(O21:O100) -> 3775 | P101: =SUM(P21:P100) -> 1300 | Q101: =SUM(Q21:Q100) -> 5100
I103: =SUM('Mar 24'!$I$101:'Mar 24'!$Q$101) -> 79110

Sheet April 24
D4: Feb 2024 Sales in Nutsell | O4: Prime | P4: Off Grade | Q4: Total
D5: Grades | E5: Off Grade | F5: 1799 | G5: 2699 | H5: 588 | I5: 2088 | J5: 2488 | K5: 2688 | L5: 3099 | M5: DENKA | N5: TOTAL
D6: Old Stck CF | E6: 203545 | F6: 10500 | G6: 21285 | H6: 5020 | I6: 0 | J6: 21885 | K6: 12775 | L6: 17125 | M6: 9300 | N6: =SUM(E6:M6) -> 301435 | O6: =SUM(F6:M6) -> 97890 | P6: =E6 -> 203545 | Q6: =O6+P6 -> 301435
D7: New Input In Dec | E7: =W32 -> 38231 | F7: =F18 -> 18000 | G7: =G18 -> 0 | H7: =H18 -> 0 | I7: =I18 -> 0 | J7: =J18 -> 0 | K7: =K18 -> 0 | L7: =L18 -> 0 | M7: =M18 -> 0 | N7: =SUM(E7:M7) -> 56231 | O7: =SUM(F7:M7) -> 18000 | P7: =E7 -> 38231 | Q7: =O7+P7 -> 56231
D8: Sales In April | E8: ='April 24'!$I$101 -> 69900 | F8: ='April 24'!$J$101 -> 14900 | G8: ='April 24'!$K$101 -> 14500 | H8: ='April 24'!$L$101 -> 1000 | I8: ='April 24'!$M$101 -> 0 | J8: ='April 24'!$N$101 -> 2700 | K8: ='April 24'!$O$101 -> 2500 | L8: ='April 24'!$P$101 -> 0 | M8: ='April 24'!$Q$101 -> 3840 | N8: =SUM(E8:M8) -> 109340 | O8: =SUM(F8:M8) -> 39440 | P8: =E8 -> 69900 | Q8: =SUM(O8,P8) -> 109340
D9: Net Stocks CF | E9: =SUM(E6,E7-E8) -> 171876 | F9: =SUM(F6,F7-F8) -> 13600 | G9: =SUM(G6,G7-G8) -> 6785 | H9: =SUM(H6,H7-H8) -> 4020 | I9: =SUM(I6,I7-I8) -> 0 | J9: =SUM(J6,J7-J8) -> 19185 | K9: =SUM(K6,K7-K8) -> 10275 | L9: =SUM(L6,L7-L8) -> 17125 | M9: =SUM(M6,M7-M8) -> 5460 | N9: =SUM(N6+N7-N8) -> 248326 | O9: =SUM(F9:M9) -> 76450 | P9: =E9 -> 171876 | Q9: =SUM(O9,P9) -> 248326
C11: PRIME INPUT DETAILS | E11: GRADES | F11: 1799 | G11: 2699 | H11: 588 | I11: 2088 | J11: 2488 | K11: 2688 | L11: 3099 | M11: DENKA | N11: TOTAL | O11: FROM | P11: IMP NO
C12: SRL NO | D12: MAKE | E12: DATE | N12: =SUM(F12:M12) -> 0
C13: 1 | D13: Wanwei | E13: 45386 | F13: 18000
C14: 2 | D14: IM
C15: 3 | D15: IM
C16: 4 | D16: Wanwei
C17: 5 | D17: Denka
C18: TOTAL | F18: =SUM(F12:F17) -> 18000 | G18: =SUM(G12:G17) -> 0 | H18: =SUM(H12:H17) -> 0 | I18: =SUM(I12:I17) -> 0 | J18: =SUM(J12:J17) -> 0 | K18: =SUM(K12:K17) -> 0 | L18: =SUM(L12:L17) -> 0 | M18: =SUM(M12:M17) -> 0 | N18: =SUM(F18:M18) -> 18000
C20: Srl No | D20: Date | E20: Inv No | F20: Party | G20: Qty | H20: Price | I20: Off Grade | J20: 1799 | K20: 2699 | L20: 588 | M20: 2088 | N20: 2488 | O20: 2688 | P20: 3099 | Q20: DENKA | T20: Off Grade Stocks And Sales
C21: 3 | D21: 45383 | E21: GTC 1 | F21: Mine Chem | G21: 500 | H21: 151 | J21: 500 | T21: New Input
C22: 4 | D22: 45383 | E22: GTC 2 | F22: Sparkle Inds | G22: 500 | H22: 167 | K22: 500 | T22: Srl No. | U22: Date | V22: Details | W22: Qty
C23: 5 | D23: 45383 | E23: GTC 3 | F23: Aditya | G23: 4000 | H23: 153, 161 | J23: 3000 | K23: 1000 | T23: 1 | U23: 45401 | V23: mix JP | W23: 19114
C24: 1 | D24: 45384 | E24: 1 | F24: Reliable | G24: 1500 | H24: 165 | K24: 1500 | T24: 2 | U24: 45401 | V24: mix JP | W24: 19117
C25: 2 | D25: 45385 | E25: RR | F25: Meet Products | G25: 2000 | H25: 117, 151 | I25: 500 | J25: 1500 | T25: 3 | V25: mix JP
C26: 6 | D26: 45385 | E26: GTC 4 | F26: Panther Adhesives | G26: 10000 | H26: 158 | K26: 10000 | T26: 4
C27: 7 | D27: 45385 | E27: GTC 5 | F27: Mine Chem | G27: 500 | H27: 154 | J27: 500 | T27: 5
C28: 8 | D28: 45386 | E28: GTC 6 | F28: Veena | G28: 500 | H28: 171 | N28: 500 | T28: 6
C29: 9 | D29: 45386 | E29: 3 | F29: Shree Mahalaxmi | G29: 80 | H29: 115 | I29: 80 | T29: 7
C30: 10 | D30: 45386 | E30: 4 | F30: Mangalam Dye | G30: 440 | H30: 120, 158 | I30: 240 | N30: 200 | T30: 8
C31: 11 | D31: 45387 | E31: 5 | F31: A 1 Starch | G31: 240 | H31: 120 | I31: 240
C32: 12 | D32: 45387 | E32: 6 | F32: Reliable | G32: 500 | H32: 120 | I32: 500 | T32: Total New Input:- | W32: =SUM(W23:W30) -> 38231
C33: 13 | D33: 45387 | E33: RR | F33: Meet Products | G33: 500 | H33: 117 | I33: 500 | T33: Old Stock C/F:- | W33: 203545
C34: 14 | D34: 45388 | E34: 8 | F34: Paramount | G34: 7500 | H34: 113 | I34: 7500 | T34: Total Stocks New & Old :- | W34: =SUM(W32,W33) -> 241776
C35: 15 | D35: 45390 | E35: 9, 10 | F35: KDM | G35: 700 | H35: 117 | I35: 700 | T35: LESS SALES: (as per sales sheet) | W35: ='April 24'!$I$101 -> 69900
C36: 19 | D36: 45390 | E36: GTC 8 | F36: Divysai | G36: 500 | H36: 158 | N36: 500
C37: 20 | D37: 45390 | E37: GTC 9 | F37: Aditya | G37: 2000 | H37: 153 | J37: 2000 | T37: NET QTY AVAILABLE: | W37: =SUM(W34-W35) -> 171876
C38: 16 | D38: 45392 | E38: 12 | F38: Shree Mahalaxmi | G38: 1500 | H38: 115 | I38: 1500
C39: 17 | D39: 45393 | E39: 13, 14 | F39: Surya | G39: 4280 | H39: 205, 170, 156 | J39: 1000 | O39: 2000 | Q39: 1280
C40: 18 | D40: 45393 | E40: 15 | F40: Popular | G40: 40 | H40: 109 | I40: 40
C41: 21 | D41: 45395 | E41: 16, 17 | F41: Siva | G41: 105000 | H41: 99 | I41: 10000 | N41: 500
C42: 22 | D42: 45395 | E42: 18 | F42: SKS Fine | G42: 500 | H42: 114 | I42: 500
C43: 23 | D43: 45395 | E43: GTC 11 | F43: Dhanlaxmi Sizing | G43: 1000 | H43: 194 | Q43: 1000
C44: 24 | D44: 45397 | E44: GTC 12 | F44: Aditya | G44: 2000 | H44: 153 | J44: 2000
C45: 26 | D45: 45397 | E45: GTC 13 | F45: Veena | G45: 860 | H45: 204 | Q45: 860
C46: 27 | D46: 45398 | E46: GTC 14 | F46: Growmore | G46: 1500 | H46: 158, 172, 205 | J46: 1000 | N46: 500
C47: 28 | D47: 45398 | E47: GTC 15 | F47: Mine Chem | G47: 500 | H47: 151 | J47: 500
C48: 29 | D48: 45398 | E48: 22 | F48: Shree Mahalaxmi | G48: 10000 | H48: 115 | I48: 10000
C49: 30 | D49: 45399 | E49: GTC 16 | F49: Growmore | G49: 500 | H49: 158, 205 | J49: 400 | Q49: 100
C50: 31 | D50: 45399 | E50: GTC 17 | F50: Aditya | G50: 2000 | H50: 154 | J50: 2000
C51: 32 | D51: 45401 | E51: 23 | F51: Chandan Synthetic | G51: 5000 | H51: 116 | I51: 5000
C52: 33 | D52: 45401 | E52: 24 | F52: Mine Chem | G52: 500 | H52: 128 | I52: 500
C53: 34 | D53: 45402 | E53: 26 | F53: Siva | G53: 10000 | H53: 99 | I53: 10000
C54: 35 | D54: 45402 | E54: 27 | F54: Shree Mahalaxmi | G54: 100 | H54: 115
C55: 36 | D55: 45402 | E55: RR | F55: Shri Ganpatye | G55: 200 | H55: 199 | Q55: 200
C56: 37 | D56: 45402 | E56: RR | F56: Patidar Adhesives | G56: 1500 | H56: 167 | K56: 1000 | O56: 500
C57: 38 | D57: 45402 | E57: RR | F57: Fortune | G57: 500 | H57: 125 | I57: 500
C58: 41 | D58: 45404 | E58: GTC 18 | F58: Sparkle Inds | G58: 500 | H58: 167 | K58: 500
C59: 39 | D59: 45405 | E59: 28 | F59: Vinit Polymers | G59: 21000 | H59: 110 | I59: 21000
C60: 42 | D60: 45405 | E60: GTC 19 | F60: Veena | G60: 500 | H60: 171 | N60: 500
C61: 40 | D61: 45406 | E61: 29 | F61: Mine Chem | G61: 120 | H61: 128, 215 | I61: 20 | Q61: 100
C62: 43 | D62: 45406 | E62: GTC 20 | F62: Growmore | G62: 300 | H62: 205 | Q62: 300
C63: 44 | D63: 45407 | E63: 30 | F63: Mine Chem | G63: 100, 500 | H63: 125, 151 | I63: 100 | J63: 500
C64: 45 | D64: 45411 | E64: 31 | F64: Ankush | G64: 1000 | H64: 164 | L64: 1000
C65: 46 | D65: 45412 | E65: 32 | F65: Shree Mahalaxmi | G65: 80 | H65: 115 | I65: 80
C66: 47 | D66: 45412 | E66: RR | F66: Fortune | G66: 400 | H66: 125 | I66: 400
C67: 48 | F67: Growmore
C68: 49 | F68: Fortune
C69: 50 | F69: Shree Mahalaxmi
C70: 51 | F70: SKS Fine
C71: 52 | F71: Popular
C72: 53 | F72: KDM
C73: 54 | F73: Veena
C74: 55 | F74: Divysai
C75: 56 | F75: Vasudha
C76: 57 | F76: Divysai
C77: 58 | F77: Can Image
C78: 59 | F78: Raj Inds
... C100: 81 | F100: Shree Mahalaxmi
C101: TOTAL | G101: =SUM(G21:G100) -> 203340 | I101: =SUM(I21:I100) -> 69900 | J101: =SUM(J21:J100) -> 14900 | K101: =SUM(K21:K100) -> 14500 | L101: =SUM(L21:L100) -> 1000 | M101: =SUM(M21:M100) -> 0 | N101: =SUM(N21:N100) -> 2700 | O101: =SUM(O21:O100) -> 2500 | P101: =SUM(P21:P100) -> 0 | Q101: =SUM(Q21:Q100) -> 3840
I103: =SUM('April 24'!$I$101:'April 24'!$Q$101) -> 109340

Sheet May 2024
D4: May 2024 Sales in Nutsell | O4: Prime | P4: Off Grade | Q4: Total
D5: Grades | E5: Off Grade | F5: 1799 | G5: 2699 | H5: 588 | I5: 2088 | J5: 2488 | K5: 2688 | L5: 3099 | M5: DENKA | N5: TOTAL
D6: Old Stck CF | E6: 171876 | F6: 13600 | G6: 6785 | H6: 4020 | I6: 0 | J6: 19185 | K6: 10275 | L6: 17125 | M6: 5460 | N6: 248326 | O6: =SUM(F6:M6) -> 76450 | P6: =E6 -> 171876 | Q6: =SUM(E6:M6) -> 248326
D7: New Input In Dec | E7: =W32 -> 90936 | F7: =F18 -> 0 | G7: =G18 -> 0 | H7: =H18 -> 0 | I7: =I18 -> 0 | J7: =J18 -> 0 | K7: =K18 -> 0 | L7: =L18 -> 0 | M7: =M18 -> 0 | N7: =SUM(E7:M7) -> 90936 | O7: =SUM(F7:M7) -> 0 | P7: =E7 -> 90936 | Q7: =O7+P7 -> 90936
D8: Sales In May | E8: ='May 2024'!$I$101 -> 63140 | F8: ='May 2024'!$J$101 -> 12400 | G8: ='May 2024'!$K$101 -> 5540 | H8: ='May 2024'!$L$101 -> 0 | I8: ='May 2024'!$M$101 -> 0 | J8: ='May 2024'!$N$101 -> 13860 | K8: ='May 2024'!$O$101 -> 2000 | L8: ='May 2024'!$P$101 -> 8500 | M8: ='May 2024'!$Q$101 -> 2060 | N8: =SUM(E8:M8) -> 107500 | O8: =SUM(F8:M8) -> 44360 | P8: =E8 -> 63140 | Q8: =SUM(O8,P8) -> 107500
D9: Net Stocks CF | E9: =SUM(E6,E7-E8) -> 199672 | F9: =SUM(F6,F7-F8) -> 1200 | G9: =SUM(G6,G7-G8) -> 1245 | H9: =SUM(H6,H7-H8) -> 4020 | I9: =SUM(I6,I7-I8) -> 0 | J9: =SUM(J6,J7-J8) -> 5325 | K9: =SUM(K6,K7-K8) -> 8275 | L9: =SUM(L6,L7-L8) -> 8625 | M9: =SUM(M6,M7-M8) -> 3400 | N9: =SUM(N6+N7-N8) -> 231762 | O9: =SUM(F9:M9) -> 32090 | P9: =E9 -> 199672 | Q9: =SUM(O9,P9) -> 231762
C11: PRIME INPUT DETAILS | E11: GRADES | F11: 1799 | G11: 2699 | H11: 588 | I11: 2088 | J11: 2488 | K11: 2688 | L11: 3099 | M11: DENKA | N11: TOTAL | O11: FROM | P11: IMP NO
C12: SRL NO | D12: MAKE | E12: DATE | N12: =SUM(F12:M12) -> 0
C13: 1 | D13: Wanwei
C14: 2 | D14: IM
C15: 3 | D15: IM
C16: 4 | D16: Wanwei
C17: 5 | D17: Denka
C18: TOTAL | F18: =SUM(F12:F17) -> 0 | G18: =SUM(G12:G17) -> 0 | H18: =SUM(H12:H17) -> 0 | I18: =SUM(I12:I17) -> 0 | J18: =SUM(J12:J17) -> 0 | K18: =SUM(K12:K17) -> 0 | L18: =SUM(L12:L17) -> 0 | M18: =SUM(M12:M17) -> 0 | N18: =SUM(F18:M18) -> 0
C20: Srl No | D20: Date | E20: Inv No | F20: Party | G20: Qty | H20: Price | I20: Off Grade | J20: 1799 | K20: 2699 | L20: 588 | M20: 2088 | N20: 2488 | O20: 2688 | P20: 3099 | Q20: DENKA | T20: Off Grade Stocks And Sales
C21: 1 | D21: 45414 | E21: 33 | F21: Siva | G21: 10000 | H21: 99 | I21: 10000 | T21: New Input
C22: 2 | D22: 45414 | E22: 34 | F22: Shree Mahalaxmi | G22: 420 | H22: 115 | I22: 420 | T22: Srl No. | U22: Date | V22: Details | W22: Qty | X22: Per Kgs
C23: 3 | D23: 45414 | E23: GTC 23 | F23: AP Bonding | G23: 40000 | H23: 151 | J23: 4000 | T23: 1 | U23: 45426 | V23: mix JP | W23: 16702 | X23: 78
C24: 4 | D24: 45414 | E24: GTC 24 | F24: Popular | G24: 25 | H24: 166 | K24: 25 | T24: 2 | U24: 45427 | V24: mix JP | W24: 18648 | X24: 78
C25: 5 | D25: 45414 | E25: GTC 25 | F25: Growmore | G25: 2500 | H25: 158, 172 | J25: 500 | N25: 2000 | T25: 3 | U25: 45429 | V25: mix JP | W25: 18524 | X25: 78
C26: 6 | D26: 45415 | E26: 36 | F26: Shree Mahalaxmi | G26: 400 | H26: 115 | I26: 400 | T26: 4 | U26: 45423 | V26: temvol | W26: 10120 | X26: 92
C27: 7 | D27: 45416 | E27: 38 | F27: Pappyrus | G27: 500 | H27: 169 | K27: 500 | T27: 5 | U27: 45423 | V27: temvol | W27: 11380 | X27: 92
C28: 8 | D28: 45419 | E28: GTC 28 | F28: Reliable | G28: 1500 | H28: 170 | P28: 1500 | T28: 6 | U28: 45430 | V28: temvol | W28: 8452 | X28: 92
C29: 9 | D29: 45419 | E29: GTC 29 | F29: Mine Chem | G29: 400 | H29: 154 | J29: 400 | T29: 7 | U29: 45430 | V29: temvol | W29: 7110 | X29: 92
C30: 10 | D30: 45418 | E30: RR | F30: Fortune | G30: 400 | H30: 125 | I30: 400 | T30: 8
C31: 11 | D31: 45421 | E31: 41 | F31: Siva | G31: 10000 | H31: 99 | I31: 10000
C32: 12 | D32: 45421 | E32: 42 | F32: Mine Chem | G32: 1000 | H32: 127 | I32: 1000 | T32: Total New Input:- | W32: =SUM(W23:W30) -> 90936
C33: 13 | D33: 45426 | E33: 44 | F33: Siva | G33: 10000 | H33: 99 | I33: 10000 | T33: Old Stock C/F:- | W33: 171876
C34: 14 | D34: 45426 | E34: 45 | F34: Mine Chem | G34: 100 | H34: 120 | I34: 100 | T34: Total Stocks New & Old :- | W34: =SUM(W32,W33) -> 262812
C35: 15 | D35: 45426 | E35: 46 | F35: Bhavya Enterprise | G35: 200 | H35: 114 | I35: 200 | T35: LESS SALES: (as per sales sheet) | W35: ='May 2024'!$I$101 -> 63140
C36: 16 | D36: 45427 | E36: 47 | F36: Paresh Pure | G36: 1000 | H36: 125 | I36: 1000
C37: 17 | D37: 45421 | E37: GTC 30 | F37: Siva | G37: 1000 | H37: 160 | N37: 10000 | T37: NET QTY AVAILABLE: | W37: =SUM(W34-W35) -> 199672
C38: 18 | D38: 45422 | E38: GTC 32 | F38: Patel Adhesives | G38: 10000 | H38: 155, 168 | K38: 3000 | P38: 7000
C39: 19 | D39: 45427 | E39: GTC 34 | F39: Veena | G39: 500 | H39: 171 | N39: 500
C40: 20 | D40: 45427 | E40: GTC 35 | F40: Aditya | G40: 3000 | H40: 151 | J40: 3000
C41: 21 | D41: 45428 | E41: 51 | F41: Dhawan Trading | G41: 15000 | H41: 110 | I41: 15000
C42: 22 | D42: 45428 | E42: 52 | F42: Dhawan Trading | G42: 280 | H42: 208 | Q42: 280
C43: 23 | D43: 45429 | E43: GTC 36 | F43: Aditya | G43: 1000 | H43: 160 | K43: 1000
C44: 24 | D44: 45430 | E44: 54 | F44: Surya Poly | G44: 2000 | H44: 169 | O44: 2000
C45: 26 | D45: 45433 | E45: 55 | F45: Shree Mahalaxmi | G45: 380 | H45: 115 | I45: 380
C46: 27 | D46: 45435 | E46: GTC 37 | F46: AP Bonding | G46: 3975 | H46: 152, 162 | J46: 3000 | K46: 975
C47: 28 | D47: 45435 | E47: GTC 38 | F47: Divysai | G47: 400 | H47: 158 | N47: 400
C48: 29 | D48: 45436 | E48: 56 | F48: Durga Chemicals | G48: 200 | H48: 195 | Q48: 200
C49: 30 | D49: 45437 | E49: GTC 39 | F49: Growmore | G49: 1300 | H49: 158, 205 | J49: 1000 | Q49: 300
C50: 31 | D50: 45437 | E50: 57 | F50: BSB Indus | G50: 11300 | H50: 103 | I50: 11300
C51: 32 | D51: 45437 | E51: 59 | F51: Sagar Corp | G51: 500 | H51: 115 | I51: 500
C52: 33 | D52: 45439 | E52: 61 | F52: Chandan Synthetic | G52: 1000 | H52: 119 | I52: 1000
C53: 34 | D53: 45439 | E53: 62 | F53: Mangalam Dye | G53: 400 | H53: 119, 171, 166 | I53: 200 | K53: 40 | N53: 160
C54: 35 | D54: 45440 | E54: GTC 40 | F54: Mine Chem | G54: 300 | H54: 170 | N54: 300
C55: 36 | D55: 45440 | E55: GTC 41 | F55: Dhanlaxmi Sizing | G55: 1280 | H55: 206 | Q55: 1280
C56: 37 | D56: 45441 | E56: 65 | F56: BSB Indus | G56: 500 | H56: 151 | J56: 500
C57: 38 | D57: 45441 | E57: 66 | F57: Kanha | G57: 40 | H57: 115 | I57: 40
C58: 41 | D58: 45441 | E58: GTC 43 | F58: Veena | G58: 500 | H58: 171 | N58: 500
C59: 39 | D59: 45443 | E59: 70 | F59: KDM | G59: 1200 | H59: 117 | I59: 1200
C60: 42 | F60: Veena
C61: 40 | F61: Mine Chem
C62: 43 | F62: Growmore
C63: 44 | F63: Mine Chem
C64: 45 | F64: Ankush
C65: 46 | F65: Shree Mahalaxmi
C66: 47 | F66: Fortune
C67: 48 | F67: Growmore
C68: 49 | F68: Fortune
C69: 50 | F69: Shree Mahalaxmi
C70: 51 | F70: SKS Fine
C71: 52 | F71: Popular
... C100: 81 | F100: Shree Mahalaxmi
C101: TOTAL | G101: =SUM(G21:G100) -> 134500 | I101: =SUM(I21:I100) -> 63140 | J101: =SUM(J21:J100) -> 12400 | K101: =SUM(K21:K100) -> 5540 | L101: =SUM(L21:L100) -> 0 | M101: =SUM(M21:M100) -> 0 | N101: =SUM(N21:N100) -> 13860 | O101: =SUM(O21:O100) -> 2000 | P101: =SUM(P21:P100) -> 8500 | Q101: =SUM(Q21:Q100) -> 2060
I103: =SUM('May 2024'!$I$101:'May 2024'!$Q$101) -> 107500

Sheet June 24
D4: June 2024 Sales in Nutsell | O4: Prime | P4: Off Grade | Q4: Total
D5: Grades | E5: Off Grade | F5: 1799 | G5: 2699 | H5: 588 | I5: 2088 | J5: 2488 | K5: 2688 | L5: 3099 | M5: DENKA | N5: TOTAL
D6: Old Stck CF | E6: 199672 | F6: 1200 | G6: 1245 | H6: 4020 | I6: 0 | J6: 5325 | K6: 8275 | L6: 8625 | M6: 3400 | N6: 231762 | O6: =SUM(F6:M6) -> 32090 | P6: =E6 -> 199672 | Q6: =SUM(E6:M6) -> 231762
D7: New Input In Dec | E7: =W32 -> 82865 | F7: =F18 -> 36000 | G7: =G18 -> 18000 | H7: =H18 -> 0 | I7: =I18 -> 0 | J7: =J18 -> 0 | K7: =K18 -> 0 | L7: =L18 -> 0 | M7: =M18 -> 0 | N7: =SUM(E7:M7) -> 136865 | O7: =SUM(F7:M7) -> 54000 | P7: =E7 -> 82865 | Q7: =O7+P7 -> 136865
D8: Sales In June | E8: ='June 24'!$I$102 -> 76760 | F8: ='June 24'!$J$102 -> 2300 | G8: ='June 24'!$K$102 -> 2440 | H8: ='June 24'!$L$102 -> 0 | I8: ='June 24'!$M$102 -> 0 | J8: ='June 24'!$N$102 -> 15500 | K8: ='June 24'!$O$102 -> 2200 | L8: ='June 24'!$P$102 -> 1500 | M8: ='June 24'!$Q$102 -> 2100 | N8: =SUM(E8:M8) -> 102800 | O8: =SUM(F8:M8) -> 26040 | P8: =E8 -> 76760 | Q8: =SUM(O8,P8) -> 102800
D9: Net Stocks CF | E9: =SUM(E6,E7-E8) -> 205777 | F9: =SUM(F6,F7-F8) -> 34900 | G9: =SUM(G6,G7-G8) -> 16805 | H9: =SUM(H6,H7-H8) -> 4020 | I9: =SUM(I6,I7-I8) -> 0 | J9: =SUM(J6,J7-J8) -> -10175 | K9: =SUM(K6,K7-K8) -> 6075 | L9: =SUM(L6,L7-L8) -> 7125 | M9: =SUM(M6,M7-M8) -> 1300 | N9: =SUM(N6+N7-N8) -> 265827 | O9: =SUM(F9:M9) -> 60050 | P9: =E9 -> 205777 | Q9: =SUM(O9,P9) -> 265827
C11: PRIME INPUT DETAILS | E11: GRADES | F11: 1799 | G11: 2699 | H11: 588 | I11: 2088 | J11: 2488 | K11: 2688 | L11: 3099 | M11: DENKA | N11: TOTAL | O11: FROM | P11: IMP NO
C12: SRL NO | D12: MAKE | E12: DATE | N12: =SUM(F12:M12) -> 0
C13: 1 | D13: Wanwei | E13: 45444 | F13: 36000 | G13: 18000 | Q13: 8-6-24 & 16-6-24 for 1799
C14: 2 | D14: IM
C15: 3 | D15: IM
C16: 4 | D16: Wanwei
C17: 5 | D17: Denka
C18: TOTAL | F18: =SUM(F12:F17) -> 36000 | G18: =SUM(G12:G17) -> 18000 | H18: =SUM(H12:H17) -> 0 | I18: =SUM(I12:I17) -> 0 | J18: =SUM(J12:J17) -> 0 | K18: =SUM(K12:K17) -> 0 | L18: =SUM(L12:L17) -> 0 | M18: =SUM(M12:M17) -> 0 | N18: =SUM(F18:M18) -> 54000
C20: Srl No | D20: Date | E20: Inv No | F20: Party | G20: Qty | H20: Price | I20: Off Grade | J20: 1799 | K20: 2699 | L20: 588 | M20: 2088 | N20: 2488 | O20: 2688 | P20: 3099 | Q20: DENKA | T20: Off Grade Stocks And Sales
C21: 1 | D21: 45444 | E21: GTC 45 | F21: NewPrism | G21: 1500 | H21: 174 | N21: 1500 | T21: New Input
C22: 2 | D22: 45446 | E22: GTC 46 | F22: Growmore | G22: 800 | H22: 165 | J22: 800 | T22: Srl No. | U22: Date | V22: Details | W22: Qty | X22: Per Kgs | Y22: Imp No | Z22: Total Cost
C23: 3 | D23: 45446 | E23: 73 | F23: Siva | G23: 10000 | H23: 99, 174 | I23: 9500 | N23: 500 | T23: 1 | U23: 45449 | V23: mix JP | W23: 12728 | X23: 77 | Y23: 4 | Z23: =W23*X23 -> 980056
C24: 4 | D24: 45446 | E24: GTC 48 | F24: Om Shakti | G24: 1000 | H24: 170 | N24: 1000 | T24: 2 | U24: 45450 | V24: mix JP | W24: 15089 | X24: 84 | Y24: 11 | Z24: =W24*X24 -> 1267476
C25: 5 | D25: 45447 | E25: 74 | F25: Mine Chem | G25: 1760 | H25: 128 | I25: 1760 | T25: 3 | U25: 45451 | V25: mix JP | W25: 15200 | X25: 78 | Y25: 3 | Z25: =W25*X25 -> 1185600
C26: 6 | D26: 45447 | E26: 75 | F26: SKR | G26: 30000 | H26: 110 | I26: 3000 | T26: 4 | U26: 45459 | V26: mix JP | W26: 20048 | X26: 84 | Y26: 12 | Z26: =W26*X26 -> 1684032
C27: 7 | D27: 45448 | E27: GTC 53 | F27: NewPrism | G27: 1500 | H27: 170 | N27: 1500 | T27: 5 | U27: 45457 | V27: Sanjay | W27: 16500 | X27: 78 | Y27: NA | Z27: =W27*X27 -> 1287000
C28: 8 | D28: 45448 | E28: 76 | F28: Chandan Synthetic | G28: 6000 | H28: 120 | I28: 6000 | T28: 6 | U28: 45463 | V28: Sanjay | W28: 3300 | X28: 91 | Y28: NA | Z28: =W28*X28 -> 300300
C29: 9 | D29: 45449 | E29: 77 | F29: BSB Indus | G29: 500 | H29: 174 | P29: 500 | T29: 7 | V29: temvol | Z29: =W29*X29 -> 0
C30: 10 | D30: 45450 | E30: 78 | F30: Orinco | G30: 2100 | H30: 105 | I30: 2100 | T30: 8 | Z30: =W30*X30 -> 0
C31: 11 | D31: 45451 | E31: 80 | F31: Siva | G31: 10000 | H31: 99 | I31: 10000 | X31: TOTAL COST | Z31: =SUM(Z23:Z30) -> 6704464
C32: 12 | D32: 45451 | E32: GTC 55 | F32: Growmore | G32: 1500 | H32: 170 | J32: 1500 | T32: Total New Input:- | W32: =SUM(W23:W30) -> 82865 | X32: Avg Per Kgs Cost | Z32: =Z31/W32 -> 80.908272
C33: 13 | D33: 45453 | E33: GTC 57 | F33: Veena | G33: 600 | H33: 209 | Q33: 600 | T33: Old Stock C/F:- | W33: 199672
C34: 14 | D34: 45455 | E34: GTC 58 | F34: NewPrism | G34: 1500 | H34: 180 | N34: 1500 | T34: Total Stocks New & Old :- | W34: =SUM(W32,W33) -> 282537
C35: 15 | D35: 45455 | E35: GTC 59 | F35: Sparkle | G35: 940 | H35: 174 | K35: 940 | T35: LESS SALES: (as per sales sheet) | W35: ='June 24'!$I$102 -> 76760
C36: 16 | D36: 45455 | E36: 81 | F36: Siva | G36: 10000 | H36: 99 | I36: 10000
C37: 17 | D37: 45455 | E37: 83 | F37: AP Enterprise | G37: 200 | H37: 184 | O37: 200 | T37: NET QTY AVAILABLE: | W37: =SUM(W34-W35) -> 205777
C38: 18 | D38: 45457 | E38: 87 | F38: Shree Mahalaxmi | G38: 1000 | H38: 115 | I38: 1000
C39: 18 | D39: 45457 | E39: 88 | F39: Jai Aravali | G39: 12600 | H39: 115 | I39: 12600
C40: 19 | D40: 45457 | E40: GTC 62 | F40: RCI | G40: 2500 | H40: 178 | N40: 2500
C41: 20 | D41: 45458 | E41: 89 | F41: SKR | G41: 1020 | H41: 117 | I41: 1020
C42: 21 | D42: 45458 | E42: 90 | F42: SKR | G42: 40 | H42: 117 | I42: 40
C43: 22 | D43: 45458 | E43: GTC 63 | F43: Aditya Impex | G43: 500 | H43: 179 | N43: 500
C44: 23 | D44: 45460 | E44: GTC 64 - SST 91 | F44: Guruji industries | G44: 5000 | H44: 111, 191 | I44: 3500 | Q44: 1500
C45: 24 | D45: 45462 | E45: 92 | F45: Paresh Pure | G45: 1000 | H45: 127 | I45: 1000
C46: 26 | D46: 45432 | E46: 96 | F46: Agarwal Chemical | G46: 300 | H46: 174 | N46: 3000
C47: 27 | D47: 45462 | E47: GTC 65 | F47: Surya | G47: 3000 | H47: 185 | O47: 2000 | P47: 1000
C48: 28 | D48: 45463 | E48: 97 | F48: RCI | G48: 200 | H48: 114 | I48: 200
C49: 29 | D49: 45465 | E49: GTC 66 | F49: Balaji Chem | G49: 1000 | H49: 174 | N49: 1000
C50: 30 | D50: 45465 | E50: 101 | F50: Woodland | G50: 40 | H50: 117 | I50: 40
C51: 31 | D51: 45466 | E51: 103 | F51: Siva | G51: 10000 | H51: 99 | I51: 10000
C52: 32 | D52: 45467 | E52: 105 | F52: BSB Indus | G52: 5000 | H52: 110 | I52: 5000
C53: 33 | D53: 45467 | E53: GTC 67 | F53: Veena | G53: 500 | H53: 184 | N53: 500
C54: 34 | D54: 45467 | E54: GTC 68 | F54: MLJP | G54: 2000 | H54: 175 | N54: 2000
C55: 35 | D55: 45470 | E55: GTC 69 | F55: Aditya Impex | G55: 1500 | H55: 169 | K55: 1500
C56: 36 | F56: Dhanlaxmi Sizing
C57: 37 | F57: BSB Indus
C58: 38 | F58: Kanha
C59: 41 | F59: Veena
C60: 39 | F60: KDM
C61: 42 | F61: Veena
C62: 40 | F62: Mine Chem
C63: 43 | F63: Growmore
C64: 44 | F64: Mine Chem
C65: 45 | F65: Ankush
C66: 46 | F66: Shree Mahalaxmi
C67: 47 | F67: Fortune
... C101: 81 | F101: Shree Mahalaxmi
C102: TOTAL | G102: =SUM(G21:G101) -> 127100 | I102: =SUM(I21:I101) -> 76760 | J102: =SUM(J21:J101) -> 2300 | K102: =SUM(K21:K101) -> 2440 | L102: =SUM(L21:L101) -> 0 | M102: =SUM(M21:M101) -> 0 | N102: =SUM(N21:N101) -> 15500 | O102: =SUM(O21:O101) -> 2200 | P102: =SUM(P21:P101) -> 1500 | Q102: =SUM(Q21:Q101) -> 2100
I104: =SUM('June 24'!$I$102:'June 24'!$Q$102) -> 102800

Sheet July 24
D4: July 2024 Sales in Nutsell | O4: Prime | P4: Off Grade | Q4: Total
D5: Grades | E5: Off Grade | F5: 1799 | G5: 2699 | H5: 588 | I5: 2088 | J5: 2488 | K5: 2688 | L5: 3099 | M5: DENKA | N5: TOTAL
D6: Old Stck CF | E6: 205777 | F6: 34900 | G6: 16805 | H6: 4020 | I6: 0 | J6: 1700 | K6: 6075 | L6: 7125 | M6: 1300 | N6: 262527 | O6: =SUM(F6:M6) -> 71925 | P6: =E6 -> 205777 | Q6: =SUM(E6:M6) -> 277702
D7: New Input In Dec | E7: =W32 -> 73256 | F7: =F18 -> 0 | G7: =G18 -> 0 | H7: =H18 -> 0 | I7: =I18 -> 0 | J7: =J18 -> 0 | K7: =K18 -> 0 | L7: =L18 -> 0 | M7: =M18 -> 0 | N7: =SUM(E7:M7) -> 73256 | O7: =SUM(F7:M7) -> 0 | P7: =E7 -> 73256 | Q7: =O7+P7 -> 73256
D8: Sales In July | E8: ='July 24'!$I$102 -> 67880 | F8: ='July 24'!$J$102 -> 16500 | G8: ='July 24'!$K$102 -> 2000 | H8: ='July 24'!$L$102 -> 3040 | I8: ='July 24'!$M$102 -> 40 | J8: ='July 24'!$N$102 -> 1400 | K8: ='July 24'!$O$102 -> 3400 | L8: ='July 24'!$P$102 -> 6300 | M8: ='July 24'!$Q$102 -> 1200 | N8: =SUM(E8:M8) -> 101760 | O8: =SUM(F8:M8) -> 33880 | P8: =E8 -> 67880 | Q8: =SUM(O8,P8) -> 101760
D9: Net Stocks CF | E9: =SUM(E6,E7-E8) -> 211153 | F9: =SUM(F6,F7-F8) -> 18400 | G9: =SUM(G6,G7-G8) -> 14805 | H9: =SUM(H6,H7-H8) -> 980 | I9: =SUM(I6,I7-I8) -> -40 | J9: =SUM(J6,J7-J8) -> 300 | K9: =SUM(K6,K7-K8) -> 2675 | L9: =SUM(L6,L7-L8) -> 825 | M9: =SUM(M6,M7-M8) -> 100 | N9: =SUM(N6+N7-N8) -> 234023 | O9: =SUM(F9:M9) -> 38045 | P9: =E9 -> 211153 | Q9: =SUM(O9,P9) -> 249198
C11: PRIME INPUT DETAILS | E11: GRADES | F11: 1799 | G11: 2699 | H11: 588 | I11: 2088 | J11: 2488 | K11: 2688 | L11: 3099 | M11: DENKA | N11: TOTAL | O11: FROM | P11: IMP NO
C12: SRL NO | D12: MAKE | E12: DATE | N12: =SUM(F12:M12) -> 0
C13: 1 | D13: Wanwei
C14: 2 | D14: IM
C15: 3 | D15: IM
C16: 4 | D16: Wanwei
C17: 5 | D17: Denka
C18: TOTAL | F18: =SUM(F12:F17) -> 0 | G18: =SUM(G12:G17) -> 0 | H18: =SUM(H12:H17) -> 0 | I18: =SUM(I12:I17) -> 0 | J18: =SUM(J12:J17) -> 0 | K18: =SUM(K12:K17) -> 0 | L18: =SUM(L12:L17) -> 0 | M18: =SUM(M12:M17) -> 0 | N18: =SUM(F18:M18) -> 0
C20: Srl No | D20: Date | E20: Inv No | F20: Party | G20: Qty | H20: Price | I20: Off Grade | J20: 1799 | K20: 2699 | L20: 588 | M20: 2088 | N20: 2488 | O20: 2688 | P20: 3099 | Q20: DENKA | R20: Column1 | T20: Off Grade Stocks And Sales
C21: 1 | D21: 45474 | E21: 115 | F21: Mine Chem | G21: 400 | H21: 128 | I21: 400 | T21: New Input
C22: 2 | D22: 45474 | E22: 116 | F22: Paresh Pure | G22: 1100 | H22: 127 | I22: 1100 | T22: Srl No. | U22: Date | V22: Details | W22: Qty | X22: Per Kgs | Y22: Imp No | Z22: Total Cost
C23: 3 | D23: 45474 | E23: 117 | F23: Seamless | G23: 100 | H23: 190 | O23: 100 | T23: 1 | U23: 45489 | V23: mix JP | W23: 17033 | X23: 75 | Y23: 5 | Z23: =W23*X23 -> 1277475
C24: 4 | D24: 45474 | E24: 118 | F24: RCI | G24: 500 | H24: 114 | I24: 500 | T24: 2 | U24: 45491 | V24: Crystal | W24: 19123 | X24: 85 | Y24: 13 | Z24: =W24*X24 -> 1625455
C25: 5 | D25: 45474 | E25: 119 | F25: Sunil Dye Chem | G25: 100 | H25: 183 | O25: 100 | T25: 3 | U25: 45492 | V25: mix JP | W25: 19438 | X25: 90 | Y25: 8 | Z25: =W25*X25 -> 1749420
C26: 6 | D26: 45474 | E26: 120, 121 | F26: Mangalam | G26: 300 | H26: 120, 180 | I26: 200 | O26: 100 | T26: 4 | U26: 45499 | V26: mix JP | W26: 17662 | X26: 78 | Y26: 12 | Z26: =W26*X26 -> 1377636
C27: 7 | D27: 45476 | E27: RR | F27: Gurpreet | G27: 300 | H27: 189 | P27: 300 | T27: 5 | V27: Sanjay | X27: 78 | Y27: NA | Z27: =W27*X27 -> 0
C28: 8 | D28: 45476 | E28: RR | F28: Shri Ganpatye | G28: 200 | H28: 209 | Q28: 200 | T28: 6 | V28: temvol | Z28: =W28*X28 -> 0
C29: 9 | D29: 45475 | E29: 122 | F29: Siva | G29: 10000 | H29: 99 | I29: 10000 | T29: 7 | V29: temvol | Z29: =W29*X29 -> 0
C30: 10 | D30: 45476 | E30: 123, 124 | F30: SKR | G30: 140 | H30: 117 | I30: 140 | T30: 8 | Z30: =W30*X30 -> 0
C31: 11 | D31: 45476 | E31: GTC 72 | F31: AP Bonding | G31: 7500 | H31: 159, 170, 175 | J31: 5000 | K31: 1000 | L31: 1500 | X31: TOTAL COST | Z31: =SUM(Z23:Z30) -> 6029986
C32: 12 | D32: 45479 | E32: 126 | F32: Siva | G32: 10000 | H32: 99 | I32: 10000 | T32: Total New Input:- | W32: =SUM(W23:W30) -> 73256 | X32: Avg Per Kgs Cost | Z32: =Z31/W32 -> 82.313886
C33: 13 | D33: 45479 | E33: GTC 74 | F33: Siva | G33: 500 | H33: 175 | N33: 500 | T33: Old Stock C/F:- | W33: 205777
C34: 14 | D34: 45481 | E34: GTC 76 | F34: Reliable Adhesives | G34: 1000 | H34: 170 | K34: 1000 | T34: Total Stocks New & Old :- | W34: =SUM(W32,W33) -> 279033
C35: 15 | D35: 45481 | E35: GTC 77 | F35: Aditya | G35: 3000 | H35: 159 | J35: 3000 | T35: LESS SALES: (as per sales sheet) | W35: ='July 24'!$I$102 -> 67880
C36: 16 | D36: 45482 | E36: 128 | F36: Shakti Chem | G36: 80 | H36: 178 | L36: 40 | M36: 40 | R36: 2088 sold which is taken from cj
C37: 17 | D37: 45484 | E37: 130 | F37: Asanand Sons | G37: 1500 | H37: 171 | L37: 1500 | T37: NET QTY AVAILABLE: | W37: =SUM(W34-W35) -> 211153
C38: 18 | D38: 45486 | E38: 134 | F38: Siva | G38: 10000 | H38: 99 | I38: 10000
C39: 18 | D39: 45483 | E39: GTC 78 | F39: Growmore | G39: 1100 | H39: 185, 210 | N39: 900 | Q39: 200
C40: 19 | D40: 45486 | E40: 135 | F40: Pallmer | G40: 800 | H40: 105, 157 | I40: 300 | J40: 500
C41: 20 | D41: 45488 | E41: 136 | F41: SKR | G41: 6000 | H41: 113 | I41: 6000
C42: 21 | D42: 45489 | E42: 138 | F42: SKR | G42: 1040 | H42: 113 | I42: 1040
C43: 22 | D43: 45491 | E43: 139 | F43: Shree Mahalaxmi | G43: 1000 | H43: 115 | I43: 1000
C44: 23 | D44: 45492 | E44: 140 | F44: Siva | G44: 10000 | H44: 99 | I44: 10000
C45: 24 | D45: 45492 | E45: 141 | F45: Asian Solvents | G45: 1000 | H45: 175 | O45: 1000
C46: 26 | D46: 45492 | E46: GTC 93 | F46: Jai Mata Di | G46: 5000 | H46: 158 | J46: 5000
C47: 27 | D47: 45495 | E47: 142 | F47: Apeksha | G47: 500 | H47: 114 | I47: 500
C48: 28 | D48: 45495 | E48: 144 | F48: Seamless | G48: 100 | H48: 187 | O48: 100
C49: 29 | D49: 45496 | E49: 145 | F49: SKR | G49: 1000 | H49: 113 | I49: 1000
C50: 30 | D50: 45498 | E50: GTC 97 | F50: Surya | G50: 20000 | H50: 184 | O50: 2000
C51: 31 | D51: 45498 | E51: GTC 98 | F51: Veena | G51: 800 | H51: 209 | Q51: 800
C52: 32 | D52: 45499 | E52: GTC 99 | F52: Popular | G52: 6000 | H52: 175 | P52: 6000
C53: 33 | D53: 45497 | E53: 146 | F53: Uma Agencies | G53: 2000 | H53: 156 | J53: 2000
C54: 34 | D54: 45499 | E54: 147 | F54: Siva | G54: 10000 | H54: 99 | I54: 10000
C55: 35 | D55: 45500 | E55: RR | F55: Meet Products | G55: 300 | H55: 118 | I55: 300
C56: 36 | D56: 45493 | E56: RR | F56: Fortune | G56: 1600 | H56: 124 | I56: 1600
C57: 37 | D57: 45504 | E57: GTC 100 | F57: Premier | G57: 1000 | H57: 156 | J57: 1000
C58: 38 | D58: 45500 | E58: 148 | F58: SKR | G58: 3000 | H58: 113 | I58: 3000
C59: 41 | D59: 45504 | E59: RR | F59: Fortune | G59: 800 | H59: 125 | I59: 800
C60: 39 | F60: KDM
C61: 42 | F61: Veena
C62: 40 | F62: Mine Chem
C63: 43 | F63: Growmore
C64: 44 | F64: Mine Chem
C65: 45 | F65: Ankush
C66: 46 | F66: Shree Mahalaxmi
C67: 47 | F67: Fortune
C68: 48 | F68: Growmore
C69: 49 | F69: Fortune
C70: 50 | F70: Shree Mahalaxmi
C71: 51 | F71: SKS Fine
... C101: 81 | F101: Shree Mahalaxmi
C102: TOTAL | G102: =SUM(G21:G101) -> 119760 | I102: =SUM(I21:I101) -> 67880 | J102: =SUM(J21:J101) -> 16500 | K102: =SUM(K21:K101) -> 2000 | L102: =SUM(L21:L101) -> 3040 | M102: =SUM(M21:M101) -> 40 | N102: =SUM(N21:N101) -> 1400 | O102: =SUM(O21:O101) -> 3400 | P102: =SUM(P21:P101) -> 6300 | Q102: =SUM(Q21:Q101) -> 1200
I104: =SUM('July 24'!$I$102:'July 24'!$Q$102) -> 101760

Sheet Aug 24
D4: August2024 Sales in Nutsell | O4: Prime | P4: Off Grade | Q4: Total
D5: Grades | E5: Off Grade | F5: 1799 | G5: 2699 | H5: 588 | I5: 2088 | J5: 2488 | K5: 2688 | L5: 3099 | M5: DENKA | N5: TOTAL
D6: Old Stck CF | E6: 211153 | F6: 18400 | G6: 14805 | H6: 860 | I6: 0 | J6: 0 | K6: 3500 | L6: 825 | M6: 0 | N6: 234023 | O6: =SUM(F6:M6) -> 38390 | P6: =E6 -> 211153 | Q6: =SUM(E6:M6) -> 249543
D7: New Input In Dec | E7: =W32 -> 19184 | F7: =F18 -> 0 | G7: =G18 -> 0 | H7: =H18 -> 0 | I7: =I18 -> 0 | J7: =J18 -> 0 | K7: =K18 -> 0 | L7: =L18 -> 0 | M7: =M18 -> 0 | N7: =SUM(E7:M7) -> 19184 | O7: =SUM(F7:M7) -> 0 | P7: =E7 -> 19184 | Q7: =O7+P7 -> 19184
D8: Sales In Aug | E8: ='Aug 24'!$I$102 -> 49780 | F8: ='Aug 24'!$J$102 -> 17700 | G8: ='Aug 24'!$K$102 -> 3000 | H8: ='Aug 24'!$L$102 -> 860 | I8: ='Aug 24'!$M$102 -> 0 | J8: ='Aug 24'!$N$102 -> 0 | K8: ='Aug 24'!$O$102 -> 3185 | L8: ='Aug 24'!$P$102 -> 0 | M8: ='Aug 24'!$Q$102 -> 0 | N8: =SUM(E8:M8) -> 74525 | O8: =SUM(F8:M8) -> 24745 | P8: =E8 -> 49780 | Q8: =SUM(O8,P8) -> 74525
D9: Net Stocks CF | E9: =SUM(E6,E7-E8) -> 180557 | F9: =SUM(F6,F7-F8) -> 700 | G9: =SUM(G6,G7-G8) -> 11805 | H9: =SUM(H6,H7-H8) -> 0 | I9: =SUM(I6,I7-I8) -> 0 | J9: =SUM(J6,J7-J8) -> 0 | K9: =SUM(K6,K7-K8) -> 315 | L9: =SUM(L6,L7-L8) -> 825 | M9: =SUM(M6,M7-M8) -> 0 | N9: =SUM(N6+N7-N8) -> 178682 | O9: =SUM(F9:M9) -> 13645 | P9: =E9 -> 180557 | Q9: =SUM(O9,P9) -> 194202
C11: PRIME INPUT DETAILS | E11: GRADES | F11: 1799 | G11: 2699 | H11: 588 | I11: 2088 | J11: 2488 | K11: 2688 | L11: 3099 | M11: DENKA | N11: TOTAL | O11: FROM | P11: IMP NO
C12: SRL NO | D12: MAKE | E12: DATE | N12: =SUM(F12:M12) -> 0
C13: 1 | D13: Wanwei
C14: 2 | D14: IM
C15: 3 | D15: IM
C16: 4 | D16: Wanwei
C17: 5 | D17: Denka
C18: TOTAL | F18: =SUM(F12:F17) -> 0 | G18: =SUM(G12:G17) -> 0 | H18: =SUM(H12:H17) -> 0 | I18: =SUM(I12:I17) -> 0 | J18: =SUM(J12:J17) -> 0 | K18: =SUM(K12:K17) -> 0 | L18: =SUM(L12:L17) -> 0 | M18: =SUM(M12:M17) -> 0 | N18: =SUM(F18:M18) -> 0
C20: Srl No | D20: Date | E20: Inv No | F20: Party | G20: Qty | H20: Price | I20: Off Grade | J20: 1799 | K20: 2699 | L20: 588 | M20: 2088 | N20: 2488 | O20: 2688 | P20: 3099 | Q20: DENKA | R20: Column1 | T20: Off Grade Stocks And Sales
C21: 1 | D21: 45505 | E21: GTC 103 | F21: Popular | G21: 3000 | H21: 176 | O21: 3000 | T21: New Input
C22: 2 | D22: 45506 | E22: GTC 104 | F22: Mahalaxmi | G22: 860 | H22: 172 | L22: 860 | T22: Srl No. | U22: Date | V22: Details | W22: Qty | X22: Per Kgs | Y22: Imp No | Z22: Total Cost
C23: 3 | D23: 45509 | E23: GTC 106 | F23: Reliable Adhesives | G23: 1200 | H23: 170 | K23: 1200 | T23: 1 | U23: 45534 | V23: mix JP | W23: 19184 | X23: 92 | Z23: =W23*X23 -> 1764928
C24: 4 | D24: 45509 | E24: 152 | F24: Siva | G24: 9500 | H24: 99 | I24: 9500 | T24: 2 | V24: Crystal | W24: 0 | X24: 0 | Z24: =W24*X24 -> 0
C25: 5 | D25: 45510 | E25: 154 | F25: Pappyrus | G25: 100 | H25: 118 | I25: 100 | T25: 3 | V25: mix JP | Z25: =W25*X25 -> 0
C26: 6 | D26: 45511 | E26: 156 | F26: Om Shakti | G26: 100 | H26: 116 | I26: 100 | T26: 4 | V26: mix JP | Z26: =W26*X26 -> 0
C27: 7 | D27: 45511 | E27: 157 | F27: Mine Chem | G27: 200 | H27: 120 | I27: 120 | T27: 5 | V27: Sanjay | Z27: =W27*X27 -> 0
C28: 8 | D28: 45511 | E28: 158 | F28: Karnataka Inds | G28: 400 | H28: 320, 172 | I28: 100 | K28: 300 | T28: 6 | V28: temvol | Z28: =W28*X28 -> 0
C29: 9 | D29: 45513 | E29: GTC 107 | F29: AP Bonding | G29: 4000 | H29: 156 | J29: 4000 | T29: 7 | V29: temvol | Z29: =W29*X29 -> 0
C30: 10 | D30: 45516 | E30: 159 | F30: Shree Mahalaxmi | G30: 100 | H30: 115 | I30: 100 | T30: 8 | Z30: =W30*X30 -> 0
C31: 11 | D31: 45516 | E31: 160 | F31: Chandan Synthetics | G31: 5000 | H31: 120 | I31: 5000 | X31: TOTAL COST | Z31: =SUM(Z23:Z30) -> 1764928
C32: 12 | D32: 45517 | E32: 161 | F32: Om Shakti | G32: 3400 | H32: 118 | I32: 3400 | T32: Total New Input:- | W32: =SUM(W23:W30) -> 19184 | X32: Avg Per Kgs Cost | Z32: =Z31/W32 -> 92
C33: 13 | D33: 45517 | E33: 162 | F33: Shree Gayatri | G33: 2000 | H33: 118 | I33: 2000 | T33: Old Stock C/F:- | W33: 205777
C34: 14 | D34: 45517 | E34: 163 | F34: Om Neelkhant | G34: 800 | H34: 157 | J34: 800 | T34: Total Stocks New & Old :- | W34: =SUM(W32,W33) -> 224961
C35: 15 | D35: 45517 | E35: 164 | F35: Premier | G35: 2000 | H35: 156 | J35: 2000 | T35: LESS SALES: (as per sales sheet) | W35: ='Aug 24'!$I$102 -> 49780
C36: 16 | D36: 45518 | E36: 165 | F36: Siva | G36: 10000 | H36: 99 | I36: 10000
C37: 17 | D37: 45518 | E37: GTC 118 | F37: Vibgyor | G37: 500 | H37: 158 | J37: 500 | T37: NET QTY AVAILABLE: | W37: =SUM(W34-W35) -> 175181
C38: 18 | D38: 45520 | E38: GTC 119 | F38: Jai Aravali | G38: 5000 | H38: 157 | J38: 5000
C39: 18 | D39: 45520 | E39: GTC 123 | F39: Mine Chem | G39: 1000 | H39: 160 | J39: 1000
C40: 19 | D40: 45521 | E40: 166 | F40: Paramount | G40: 6000 | H40: 115 | I40: 6000
C41: 20 | D41: 45521 | E41: 167 | F41: KDM | G41: 200 | H41: 117 | I41: 200
C42: 21 | D42: 45521 | E42: 168 | F42: KDM | G42: 400 | H42: 157 | J42: 400
C43: 22 | D43: 45521 | E43: 169 | F43: Surya | G43: 500 | H43: 171 | K43: 500
C44: 23 | D44: 45521 | E44: 170 | F44: Surya | G44: 1000 | H44: 117 | I44: 1000
C45: 24 | D45: 45521 | E45: 171 | F45: Pallmer | G45: 200 | H45: 105 | I45: 200
C46: 26 | D46: 45523 | E46: 173 | F46: SKR | G46: 60 | H46: 115 | I46: 60
C47: 27 | D47: 45525 | E47: 176 | F47: Mine Chem | G47: 500 | H47: 128 | I47: 500
C48: 28 | D48: 45525 | E48: GTC 129 | F48: AP Bonding | G48: 3000 | H48: 155, 169 | J48: 2000 | K48: 1000
C49: 29 | D49: 45526 | E49: 177 | F49: Premier | G49: 2000 | H49: 156 | J49: 2000
C50: 30 | D50: 45530 | E50: 178 | F50: Siva | G50: 10000 | H50: 99 | I50: 10000
C51: 31 | D51: 45530 | E51: 179 | F51: AP Enterprises | G51: 200 | H51: 118, 185 | I51: 100 | O51: 185
C52: 32 | D52: 45535 | E52: 181 | F52: RCI Chemsol | G52: 500 | H52: 119 | I52: 500
C53: 33 | D53: 45514 | E53: RR | F53: Fortune | G53: 800 | H53: 125 | I53: 800
C54: 34 | F54: Siva
C55: 35 | F55: Meet Products
C56: 36 | F56: Fortune
C57: 37 | F57: Premier
C58: 38 | F58: SKR
C59: 41 | F59: Fortune
C60: 39 | F60: KDM
C61: 42 | F61: Veena
C62: 40 | F62: Mine Chem
C63: 43 | F63: Growmore
C64: 44 | F64: Mine Chem
C65: 45 | F65: Ankush
... C101: 81 | F101: Shree Mahalaxmi
C102: TOTAL | G102: =SUM(G21:G101) -> 74520 | I102: =SUM(I21:I101) -> 49780 | J102: =SUM(J21:J101) -> 17700 | K102: =SUM(K21:K101) -> 3000 | L102: =SUM(L21:L101) -> 860 | M102: =SUM(M21:M101) -> 0 | N102: =SUM(N21:N101) -> 0 | O102: =SUM(O21:O101) -> 3185 | P102: =SUM(P21:P101) -> 0 | Q102: =SUM(Q21:Q101) -> 0
I104: =SUM('Aug 24'!$I$102:'Aug 24'!$Q$102) -> 74525

Sheet Sept 24
D4: Sept 2024 Sales in Nutsell | O4: Prime | P4: Off Grade | Q4: Total
D5: Grades | E5: Off Grade | F5: 1799 | G5: 2699 | H5: 588 | I5: 2088 | J5: 2488 | K5: 2688 | L5: 3099 | M5: DENKA | N5: TOTAL
D6: Old Stck CF | E6: 180557 | F6: 300 | G6: 11800 | H6: 0 | I6: 0 | J6: 0 | K6: 200 | L6: 300 | M6: 0 | N6: 234023 | O6: =SUM(F6:M6) -> 12600 | P6: =E6 -> 180557 | Q6: =SUM(E6:M6) -> 193157
D7: New Input In Dec | E7: =W32 -> 56064 | F7: =F18 -> 0 | G7: =G18 -> 0 | H7: =H18 -> 6000 | I7: =I18 -> 16000 | J7: =J18 -> 6000 | K7: =K18 -> 0 | L7: =L18 -> 0 | M7: =M18 -> 0 | N7: =SUM(E7:M7) -> 84064 | O7: =SUM(F7:M7) -> 28000 | P7: =E7 -> 56064 | Q7: =O7+P7 -> 84064
D8: Sales In Sept | E8: ='Sept 24'!$I$102 -> 40740 | F8: ='Sept 24'!$J$102 -> 0 | G8: ='Sept 24'!$K$102 -> 10900 | H8: ='Sept 24'!$L$102 -> 0 | I8: ='Sept 24'!$M$102 -> 2000 | J8: ='Sept 24'!$N$102 -> 6000 | K8: ='Sept 24'!$O$102 -> 0 | L8: ='Sept 24'!$P$102 -> 300 | M8: ='Sept 24'!$Q$102 -> 0 | N8: =SUM(E8:M8) -> 59940 | O8: =SUM(F8:M8) -> 19200 | P8: =E8 -> 40740 | Q8: =SUM(O8,P8) -> 59940
D9: Net Stocks CF | E9: =SUM(E6,E7-E8) -> 195881 | F9: =SUM(F6,F7-F8) -> 300 | G9: =SUM(G6,G7-G8) -> 900 | H9: =SUM(H6,H7-H8) -> 6000 | I9: =SUM(I6,I7-I8) -> 14000 | J9: =SUM(J6,J7-J8) -> 0 | K9: =SUM(K6,K7-K8) -> 200 | L9: =SUM(L6,L7-L8) -> 0 | M9: =SUM(M6,M7-M8) -> 0 | N9: =SUM(N6+N7-N8) -> 258147 | O9: =SUM(F9:M9) -> 21400 | P9: =E9 -> 195881 | Q9: =SUM(O9,P9) -> 217281
C11: PRIME INPUT DETAILS | E11: GRADES | F11: 1799 | G11: 2699 | H11: 588 | I11: 2088 | J11: 2488 | K11: 2688 | L11: 3099 | M11: DENKA | N11: TOTAL | O11: FROM | P11: IMP NO
C12: SRL NO | D12: MAKE | E12: DATE | N12: =SUM(F12:M12) -> 0
C13: 1 | D13: Wanwei | E13: 45559 | H13: 6000 | I13: 16000 | J13: 6000
C14: 2 | D14: IM
C15: 3 | D15: IM
C16: 4 | D16: Wanwei
C17: 5 | D17: Denka
C18: TOTAL | F18: =SUM(F12:F17) -> 0 | G18: =SUM(G12:G17) -> 0 | H18: =SUM(H12:H17) -> 6000 | I18: =SUM(I12:I17) -> 16000 | J18: =SUM(J12:J17) -> 6000 | K18: =SUM(K12:K17) -> 0 | L18: =SUM(L12:L17) -> 0 | M18: =SUM(M12:M17) -> 0 | N18: =SUM(F18:M18) -> 28000
C20: Srl No | D20: Date | E20: Inv No | F20: Party | G20: Qty | H20: Price | I20: Off Grade | J20: 1799 | K20: 2699 | L20: 588 | M20: 2088 | N20: 2488 | O20: 2688 | P20: 3099 | Q20: DENKA | R20: Column1 | T20: Off Grade Stocks And Sales
C21: 1 | D21: 45537 | E21: 182 | F21: Mine Chem | G21: 500 | H21: 120 | I21: 500 | T21: New Input
C22: 2 | D22: 45537 | E22: RR | F22: Meet Products | G22: 400 | H22: 118 | I22: 500 | T22: Srl No. | U22: Date | V22: Details | W22: Qty | X22: Per Kgs | Y22: Imp No | Z22: Total Cost
C23: 3 | D23: 45538 | E23: 184 | F23: Shree Mahalaxmi | G23: 1500 | H23: 115 | I23: 1500 | T23: 1 | U23: 45537 | V23: powder | W23: 17468 | X23: 76 | Y23: 22 | Z23: =W23*X23 -> 1327568
C24: 4 | D24: 45538 | E24: 185 | F24: Pallmer | G24: 100 | H24: 105 | I24: 100 | T24: 2 | U24: 45542 | V24: 107 / 205 / 3010 | W24: 19985 | X24: 92 | Y24: 24 | Z24: =W24*X24 -> 1838620
C25: 5 | D25: 45538 | E25: 135 | F25: Aditya Polymers | G25: 500 | H25: 168 | K25: 500 | T25: 3 | U25: 45540 | V25: mix JP | W25: 18611 | X25: 76 | Y25: 21 | Z25: =W25*X25 -> 1414436
C26: 6 | D26: 45538 | E26: 136 | F26: AP Bonding | G26: 1500 | H26: 168 | K26: 1500 | T26: 4 | V26: mix JP | Z26: =W26*X26 -> 0
C27: 7 | D27: 45539 | E27: 186 | F27: Om Neelkhant | G27: 800 | H27: 115 | I27: 800 | T27: 5 | V27: Sanjay | Z27: =W27*X27 -> 0
C28: 8 | D28: 45539 | E28: 187 | F28: Om Shakti | G28: 1600 | H28: 115 | I28: 1600 | T28: 6 | V28: temvol | Z28: =W28*X28 -> 0
C29: 9 | D29: 45540 | E29: 188 | F29: Siva | G29: 10000 | H29: 99 | I29: 10000 | T29: 7 | V29: temvol | Z29: =W29*X29 -> 0
C30: 10 | D30: 45540 | E30: RR | F30: Gurpreet | G30: 300 | H30: 188 | P30: 300 | T30: 8 | Z30: =W30*X30 -> 0
C31: 11 | D31: 45541 | E31: 189 | F31: Surya | G31: 2000 | H31: 172 | K31: 2000 | X31: TOTAL COST | Z31: =SUM(Z23:Z30) -> 4580624
C32: 12 | D32: 45541 | E32: 190 | F32: Surya | G32: 2000 | H32: 118 | I32: 2000 | T32: Total New Input:- | W32: =SUM(W23:W30) -> 56064 | X32: Avg Per Kgs Cost | Z32: =Z31/W32 -> 81.703482
C33: 13 | D33: 45544 | E33: 141 GTC | F33: Aditya Polymers | G33: 1000 | H33: 168 | K33: 1000 | T33: Old Stock C/F:- | W33: 205777
C34: 14 | D34: 45546 | E34: 193 | F34: Shree Mahalaxmi | G34: 5000 | H34: 115 | I34: 5000 | T34: Total Stocks New & Old :- | W34: =SUM(W32,W33) -> 261841
C35: 15 | D35: 45548 | E35: 196 | F35: Om Shakti | G35: 2700 | H35: 116 | I35: 2700 | T35: LESS SALES: (as per sales sheet) | W35: ='Sept 24'!$I$102 -> 40740
C36: 16 | D36: 45548 | E36: 197 | F36: Om Neelkhant | G36: 100 | H36: 115 | I36: 100
C37: 17 | D37: 45551 | E37: 198 | F37: Pallmer | G37: 500 | H37: 114 | I37: 500 | T37: NET QTY AVAILABLE: | W37: =SUM(W34-W35) -> 221101
C38: 18 | D38: 45553 | E38: 199 | F38: Eco Inds | G38: 3500 | H38: 127 | I38: 3500
C39: 18 | D39: 45554 | E39: 200 | F39: Pallmer | G39: 300 | H39: 108 | I39: 300
C40: 19 | D40: 45554 | E40: 201 | F40: RCI Chemsol | G40: 200 | H40: 118 | I40: 200
C41: 20 | D41: 45556 | E41: 202 | F41: Mine Chem | G41: 500 | H41: 120 | I41: 500
C42: 21 | D42: 45556 | E42: 204 | F42: SKR | G42: 1040 | H42: 113 | I42: 1040
C43: 22 | D43: 45559 | E43: GTC 143, 144 | F43: Popular | G43: 2500 | H43: 183 | M43: 2000 | N43: 500
C44: 23 | D44: 45558 | E44: 206 | F44: BSB Indus | G44: 5000 | H44: 110 | I44: 5000
C45: 24 | D45: 45558 | E45: 207 | F45: SKR | G45: 100 | H45: 110 | I45: 100
C46: 26 | D46: 45559 | E46: 208 | F46: AP Enterprises | G46: 300 | H46: 118 | I46: 300
C47: 27 | D47: 45560 | E47: GTC 145 | F47: Chandan Synthetic | G47: 4000 | H47: 182 | N47: 4000
C48: 28 | D48: 45560 | E48: GTC 148 | F48: Rally Chem | G48: 5900 | H48: 163 | K48: 5900
C49: 29 | D49: 45562 | E49: GTC 149 | F49: Veekay | G49: 1000 | H49: 184 | N49: 1000
C50: 30 | D50: 45561 | E50: 209 | F50: Om Shakti | G50: 2400 | H50: 112 | I50: 2400
C51: 31 | D51: 45563 | E51: 212 | F51: SKS Fine | G51: 1000 | H51: 112 | I51: 1000
C52: 32 | D52: 45563 | E52: 213 | F52: Woodland Chemicals | G52: 300 | H52: 115 | I52: 300
C53: 33 | D53: 45565 | E53: GTC 153 | F53: Veena | G53: 500 | H53: 187 | N53: 500
C54: 34 | D54: 45555 | E54: RR | F54: Fortune | G54: 800 | H54: 125 | I54: 800
C55: 35 | F55: Meet Products
C56: 36 | F56: Fortune
C57: 37 | F57: Premier
C58: 38 | F58: SKR
C59: 41 | F59: Fortune
C60: 39 | F60: KDM
C61: 42 | F61: Veena
C62: 40 | F62: Mine Chem
C63: 43 | F63: Growmore
C64: 44 | F64: Mine Chem
C65: 45 | F65: Ankush
C66: 46 | F66: Shree Mahalaxmi
... C101: 81 | F101: Shree Mahalaxmi
C102: TOTAL | G102: =SUM(G21:G101) -> 59840 | I102: =SUM(I21:I101) -> 40740 | J102: =SUM(J21:J101) -> 0 | K102: =SUM(K21:K101) -> 10900 | L102: =SUM(L21:L101) -> 0 | M102: =SUM(M21:M101) -> 2000 | N102: =SUM(N21:N101) -> 6000 | O102: =SUM(O21:O101) -> 0 | P102: =SUM(P21:P101) -> 300 | Q102: =SUM(Q21:Q101) -> 0
I104: =SUM('Sept 24'!$I$102:'Sept 24'!$Q$102) -> 59940

Sheet Oct 24
D4: Oct 2024 Sales in Nutsell | O4: Prime | P4: Off Grade | Q4: Total
D5: Grades | E5: Off Grade | F5: 1799 | G5: 2699 | H5: 588 | I5: 2088 | J5: 2488 | K5: 2688 | L5: 3099 | M5: DENKA | N5: TOTAL
D6: Old Stck CF | E6: 195881 | F6: 0 | G6: 0 | H6: 6000 | I6: 14000 | J6: 0 | K6: 0 | L6: 0 | M6: 0 | N6: 215881 | O6: =SUM(F6:M6) -> 20000 | P6: =E6 -> 195881 | Q6: =SUM(E6:M6) -> 215881
D7: New Input In Dec | E7: =W32 -> 58342 | F7: =F18 -> 18000 | G7: =G18 -> 0 | H7: =H18 -> 20000 | I7: =I18 -> 29000 | J7: =J18 -> 4000 | K7: =K18 -> 5000 | L7: =L18 -> 9000 | M7: =M18 -> 0 | N7: =SUM(E7:M7) -> 143342 | O7: =SUM(F7:M7) -> 85000 | P7: =E7 -> 58342 | Q7: =O7+P7 -> 143342
D8: Sales In Oct | E8: ='Oct 24'!$I$102 -> 51580 | F8: ='Oct 24'!$J$102 -> 12000 | G8: ='Oct 24'!$K$102 -> 0 | H8: ='Oct 24'!$L$102 -> 17600 | I8: ='Oct 24'!$M$102 -> 17300 | J8: ='Oct 24'!$N$102 -> 4000 | K8: ='Oct 24'!$O$102 -> 500 | L8: ='Oct 24'!$P$102 -> 0 | M8: ='Oct 24'!$Q$102 -> 0 | N8: =SUM(E8:M8) -> 102980 | O8: =SUM(F8:M8) -> 51400 | P8: =E8 -> 51580 | Q8: =SUM(O8,P8) -> 102980
D9: Net Stocks CF | E9: =SUM(E6,E7-E8) -> 202643 | F9: =SUM(F6,F7-F8) -> 6000 | G9: =SUM(G6,G7-G8) -> 0 | H9: =SUM(H6,H7-H8) -> 8400 | I9: =SUM(I6,I7-I8) -> 25700 | J9: =SUM(J6,J7-J8) -> 0 | K9: =SUM(K6,K7-K8) -> 4500 | L9: =SUM(L6,L7-L8) -> 9000 | M9: =SUM(M6,M7-M8) -> 0 | N9: =SUM(N6+N7-N8) -> 256243 | O9: =SUM(F9:M9) -> 53600 | P9: =E9 -> 202643 | Q9: =SUM(O9,P9) -> 256243
C11: PRIME INPUT DETAILS | E11: GRADES | F11: 1799 | G11: 2699 | H11: 588 | I11: 2088 | J11: 2488 | K11: 2688 | L11: 1788 | M11: DENKA | N11: TOTAL | O11: FROM | P11: IMP NO
C12: SRL NO | D12: MAKE | E12: DATE | N12: =SUM(F12:M12) -> 0
C13: 1 | D13: Wanwei
C14: 2 | D14: IM | E14: 45583 | H14: 20000 | I14: 29000 | J14: 4000 | L14: 4000 | N14: =SUM(F14:M14) -> 57000
C15: 3 | D15: IM
C16: 4 | D16: Wanwei | E16: 45589 | F16: 18000 | K16: 5000 | L16: 5000
C17: 5 | D17: Denka
C18: TOTAL | F18: =SUM(F12:F17) -> 18000 | G18: =SUM(G12:G17) -> 0 | H18: =SUM(H12:H17) -> 20000 | I18: =SUM(I12:I17) -> 29000 | J18: =SUM(J12:J17) -> 4000 | K18: =SUM(K12:K17) -> 5000 | L18: =SUM(L12:L17) -> 9000 | M18: =SUM(M12:M17) -> 0 | N18: =SUM(F18:M18) -> 85000
C20: Srl No | D20: Date | E20: Inv No | F20: Party | G20: Qty | H20: Price | I20: Off Grade | J20: 1799 | K20: 2699 | L20: 588 | M20: 2088 | N20: 2488 | O20: 2688 | P20: 3099 | Q20: DENKA | R20: Column1 | T20: Off Grade Stocks And Sales
C21: 1 | D21: 45567 | E21: 215 | F21: Siva | G21: 10000 | H21: 107 | I21: 10000 | T21: New Input
C22: 2 | D22: 45568 | E22: 216 | F22: Pallmer | G22: 500 | H22: 105 | I22: 500 | T22: Srl No. | U22: Date | V22: Details | W22: Qty | X22: Per Kgs | Y22: Imp No | Z22: Total Cost
C23: 3 | D23: 45568 | E23: 217 | F23: Punav | G23: 1000 | H23: 105 | I23: 1000 | T23: 1 | U23: 45575 | V23: powder + crystal Hexa | W23: 20360 | X23: 76 | Y23: 31 | Z23: =W23*X23 -> 1547360
C24: 4 | D24: 45568 | E24: 219 | F24: Mine Chem | G24: 260 | H24: 110 | I24: 260 | T24: 2 | U24: 45584 | V24: powder | W24: 18896 | X24: 72 | Y24: 28 | Z24: =W24*X24 -> 1360512
C25: 5 | D25: 45568 | E25: 220 | F25: SKR | G25: 1000 | H25: 113 | I25: 1000 | T25: 3 | U25: 45595 | V25: crystal | W25: 19086 | X25: 78 | Y25: 27 | Z25: =W25*X25 -> 1488708
C26: 6 | D26: 45569 | E26: 221 | F26: United Polypack | G26: 1000 | H26: 122 | I26: 1000 | T26: 4 | V26: mix JP | Z26: =W26*X26 -> 0
C27: 0 | D27: 45569 | E27: 222 | F27: SKR | G27: 3000 | H27: 113 | I27: 3000 | T27: 5 | V27: Sanjay | Z27: =W27*X27 -> 0
C28: 8 | D28: 45570 | E28: GTC 157 | F28: Vasudha | G28: 1000 | H28: 183 | M28: 1000 | T28: 6 | V28: temvol | Z28: =W28*X28 -> 0
C29: 9 | D29: 45572 | E29: 223 | F29: Chandan Synthetic | G29: 4500 | H29: 120 | I29: 4500 | T29: 7 | V29: temvol | Z29: =W29*X29 -> 0
C30: 10 | D30: 45566 | E30: GTC 154 | F30: Dhanlaxmee Sizing | G30: 100 | H30: 184 | L30: 100 | T30: 8 | Z30: =W30*X30 -> 0
C31: 11 | D31: 45574 | E31: 225 | F31: Surya | G31: 2000 | H31: 117 | I31: 2000 | X31: TOTAL COST | Z31: =SUM(Z23:Z30) -> 4396580
C32: 12 | D32: 45576 | E32: 226 | F32: Mine Chem | G32: 500 | H32: 110 | I32: 500 | T32: Total New Input:- | W32: =SUM(W23:W30) -> 58342 | X32: Avg Per Kgs Cost | Z32: =Z31/W32 -> 75.358747
C33: 13 | D33: 45576 | E33: 227 | F33: Growmore | G33: 200 | H33: 225 | I33: 200 | T33: Old Stock C/F:- | W33: 205777
C34: 14 | D34: 45579 | E34: 228 | F34: SKR | G34: 2000 | H34: 113 | I34: 2000 | T34: Total Stocks New & Old :- | W34: =SUM(W32,W33) -> 264119
C35: 15 | D35: 45579 | E35: 229 | F35: SKR | G35: 1260 | H35: 113 | I35: 1260 | T35: LESS SALES: (as per sales sheet) | W35: ='Oct 24'!$I$102 -> 51580
C36: 16 | D36: 45580 | E36: 230 | F36: Shree Mahalaxmi | G36: 500 | H36: 115 | I36: 500
C37: 17 | D37: 45580 | E37: 231 | F37: Mine Chem | G37: 1000 | H37: 120 | I37: 1000 | T37: NET QTY AVAILABLE: | W37: =SUM(W34-W35) -> 212539
C38: 18 | D38: 45581 | E38: 233 | F38: Akshat Corp | G38: 160 | H38: 120 | I38: 160
C39: 18 | D39: 45582 | E39: 234 | F39: Vaibhav Chemicals | G39: 500 | H39: 165 | M39: 500
C40: 19 | D40: 45582 | E40: 235 | F40: Darshan | G40: 200 | H40: 172 | N40: 200
C41: 20 | D41: 45583 | E41: 236 | F41: Siva | G41: 10000 | H41: 107 | I41: 10000
C42: 21 | D42: 45582 | E42: RR | F42: Shree Gabpatye | G42: 200 | H42: 181 | M42: 200
C43: 22 | D43: 45583 | E43: 237 | F43: Sunil Dye Chem | G43: 300 | H43: 178 | N43: 300
C44: 23 | D44: 45583 | E44: GTC 163 | F44: Popular | G44: 1100 | H44: 177, 184 | L44: 100 | N44: 1000
D45: 45583 | E45: GTC 164 | F45: Popular | G45: 1000 | H45: 184 | L45: 1000
C46: 24 | D46: 45583 | E46: GTC 165 | F46: Aditya | G46: 1000 | H46: 174 | N46: 1000
C47: 26 | D47: 45583 | E47: GTC 166 | F47: Mine Chem | G47: 1000 | H47: 176 | N47: 1000
C48: 27 | D48: 45583 | E48: GG 1 | F48: Mahalaxmi Chemicals | G48: 7500 | L48: 7500
C49: 28 | D49: 45583 | E49: GG 2 | F49: Gayawala | G49: 2500 | H49: 168 | L49: 2500
C50: 29 | D50: 45583 | E50: GG 3 | F50: Gayawala | G50: 5000 | H50: 168 | L50: 5000
C51: 30 | D51: 45584 | E51: 238 | F51: Sagar Dye Chem | G51: 1000 | H51: 169 | M51: 1000
C52: 32 | D52: 45586 | E52: 239 | F52: Geeta Wrapers | G52: 500 | H52: 115 | I52: 500
C53: 33 | D53: 45587 | E53: 240 | F53: Tejas Enter | G53: 2000 | H53: 162 | J53: 2000
C54: 34 | D54: 45587 | E54: 241 | F54: Pallmer | G54: 1000 | H54: 167 | M54: 1000
C55: 35 | D55: 45587 | E55: GTC 171 | F55: Veekay | G55: 1000 | H55: 173 | M55: 1000
C56: 36 | D56: 45587 | E56: GTC 172 | F56: Chandan Synthetic | G56: 1000 | H56: 169 | M56: 1000
C57: 37 | D57: 45587 | E57: GTC 173 | F57: Divysai | G57: 300 | H57: 165 | M57: 300
C58: 38 | D58: 45588 | E58: GTC 174 | F58: Veena | G58: 500 | H58: 187 | N58: 500
C59: 41 | D59: 45588 | E59: GTC 175 | F59: Aditya | G59: 4000 | H59: 165, 169 | J59: 3000 | M59: 1000
C60: 39 | D60: 45588 | E60: GTC 176 | F60: Aditya | G60: 2000 | H60: 165 | J60: 2000
C61: 42 | D61: 45588 | E61: GTC 177 | F61: Popular | G61: 500 | H61: 181 | O61: 500
C62: 40 | D62: 45589 | E62: 242 | F62: Geeta Wrapers | G62: 500 | H62: 164 | J62: 500
C63: 43 | D63: 45589 | E63: 243 | F63: Sagar Dye Chem | G63: 1000 | H63: 169 | M63: 1000
C64: 44 | D64: 45589 | E64: 244 | F64: Aniket Exports | G64: 1000 | H64: 174 | L64: 1000
C65: 45 | D65: 45589 | E65: 245 | F65: Rci Chemisol | G65: 200 | H65: 120 | I65: 200
C66: 46 | D66: 45589 | E66: 247 | F66: Orbit Overseas | G66: 1250 | H66: 163 | J66: 1250
C67: 47 | D67: 45590 | E67: 248 | F67: Antriksha Chemicals | G67: 250 | H67: 167 | J67: 250
C68: 48 | D68: 45590 | E68: 249 | F68: Shree Mahalaxmi | G68: 500 | H68: 115 | I68: 500
C69: 49 | D69: 45590 | E69: 250 | F69: Siva Chemical | G69: 10000 | H69: 107 | I69: 10000
C70: 50 | D70: 45590 | E70: GTC 178 | F70: Mine Chem | G70: 3000 | H70: 164 | J70: 3000
C71: 51 | D71: 45591 | E71: 251 | F71: Pallmer | G71: 4500 | H71: 165 | M71: 4500
C72: 52 | D72: 45591 | E72: 252 | F72: Pallmer | G72: 1500 | H72: 167 | M72: 1500
C73: 53 | D73: 45591 | E73: 253 | F73: Shree Mahalaxmi | G73: 300 | H73: 166 | M73: 300
C74: 54 | D74: 45593 | E74: 254 | F74: Geeta Wrapers | G74: 1000 | H74: 115 | I74: 1000
C75: 55 | D75: 45593 | E75: 255 | F75: Sagar Dye Chem | G75: 700 | H75: 168 | M75: 700
C76: 56 | D76: 45594 | E76: GTC 180 | F76: Rci Chemisol | G76: 500 | H76: 169 | M76: 500
C77: 57 | D77: 45594 | E77: GTC 181 | F77: Yogini | G77: 400 | H77: 168 | M77: 400
C78: 58 | D78: 45594 | E78: GTC 182 | F78: Popular | G78: 1000 | H78: 169 | M78: 1000
C79: 59 | D79: 45594 | E79: 256 | F79: Mine Chem | G79: 500 | H79: 120 | I79: 500
C80: 60 | D80: 45595 | E80: GTC 183 | F80: Popular | G80: 800 | H80: 174, 179 | L80: 400 | M80: 400
C81: 61 | F81: BSB Indus
C82: 62 | F82: Siva
C83: 63 | F83: Shri Ganpatye
C84: 64 | F84: Mine Chem
C85: 65 | F85: Paresh Pure
C86: 66 | F86: Meet Products
C87: 67 | F87: Popular
C88: 68 | F88: Fortune
C89: 69 | F89: Rally Chem
C90: 70 | F90: KK Dye
C91: 71 | F91: Vasudha
C92: 72 | F92: AP Bonding
... C101: 81 | F101: Shree Mahalaxmi
C102: TOTAL | G102: =SUM(G21:G101) -> 102980 | I102: =SUM(I21:I101) -> 51580 | J102: =SUM(J21:J101) -> 12000 | K102: =SUM(K21:K101) -> 0 | L102: =SUM(L21:L101) -> 17600 | M102: =SUM(M21:M101) -> 17300 | N102: =SUM(N21:N101) -> 4000 | O102: =SUM(O21:O101) -> 500 | P102: =SUM(P21:P101) -> 0 | Q102: =SUM(Q21:Q101) -> 0
I104: =SUM('Oct 24'!$I$102:'Oct 24'!$Q$102) -> 102980

Sheet Nov 24
D4: Nov 2024 Sales in Nutsell | O4: Prime | P4: Off Grade | Q4: Total
D5: Grades | E5: Off Grade | F5: 1799 | G5: 2699 | H5: 588 | I5: 2088 | J5: 2488 | K5: 2688 | L5: 3099+1788 | M5: DENKA | N5: TOTAL
D6: Old Stck CF | E6: 202643 | F6: 6000 | G6: 0 | H6: 8400 | I6: 25700 | J6: 0 | K6: 4500 | L6: 9000 | M6: 0 | N6: 256293 | O6: 53650 | P6: 202643 | Q6: 256293
D7: New Input In Dec | E7: =W32 -> 46581 | F7: =F18 -> 6000 | G7: =G18 -> 5000 | H7: =H18 -> 18000 | I7: =I18 -> 28000 | J7: =J18 -> 0 | K7: =K18 -> 0 | L7: =L18 -> 0 | M7: =M18 -> 0 | N7: =SUM(E7:M7) -> 103581 | O7: =SUM(F7:M7) -> 57000 | P7: =E7 -> 46581 | Q7: =O7+P7 -> 103581
D8: Sales In Nov | E8: ='Nov 24'!$I$102 -> 72220 | F8: ='Nov 24'!$J$102 -> 12000 | G8: ='Nov 24'!$K$102 -> 9000 | H8: ='Nov 24'!$L$102 -> 13940 | I8: ='Nov 24'!$M$102 -> 19280 | J8: ='Nov 24'!$N$102 -> 0 | K8: ='Nov 24'!$O$102 -> 4500 | L8: ='Nov 24'!$P$102 -> 5955 | M8: ='Nov 24'!$Q$102 -> 0 | N8: =SUM(E8:M8) -> 136895 | O8: =SUM(F8:M8) -> 64675 | P8: =E8 -> 72220 | Q8: =SUM(O8,P8) -> 136895
D9: Net Stocks CF | E9: =SUM(E6,E7-E8) -> 177004 | F9: =SUM(F6,F7-F8) -> 0 | G9: =SUM(G6,G7-G8) -> -4000 | H9: =SUM(H6,H7-H8) -> 12460 | I9: =SUM(I6,I7-I8) -> 34420 | J9: =SUM(J6,J7-J8) -> 0 | K9: =SUM(K6,K7-K8) -> 0 | L9: =SUM(L6,L7-L8) -> 3045 | M9: =SUM(M6,M7-M8) -> 0 | N9: =SUM(N6+N7-N8) -> 222979 | O9: =SUM(F9:M9) -> 45925 | P9: =E9 -> 177004 | Q9: =SUM(O9,P9) -> 222929
C11: PRIME INPUT DETAILS | E11: GRADES | F11: 1799 | G11: 2699 | H11: 588 | I11: 2088 | J11: 2488 | K11: 2688 | L11: 1788 | M11: DENKA | N11: TOTAL | O11: FROM | P11: IMP NO
C12: SRL NO | D12: MAKE | E12: DATE | N12: =SUM(F12:M12) -> 0
C13: 1 | D13: Wanwei | N13: =SUM(F13:M13) -> 0
C14: 2 | D14: IM | E14: 45610 | F14: 6000 | G14: 5000 | H14: 18000 | I14: 28000 | N14: =SUM(F14:M14) -> 57000
C15: 3 | D15: IM | N15: =SUM(F15:M15) -> 0
C16: 4 | D16: Wanwei | N16: =SUM(F16:M16) -> 0
C17: 5 | D17: Denka | N17: =SUM(F17:M17) -> 0
C18: TOTAL | F18: =SUM(F12:F17) -> 6000 | G18: =SUM(G12:G17) -> 5000 | H18: =SUM(H12:H17) -> 18000 | I18: =SUM(I12:I17) -> 28000 | J18: =SUM(J12:J17) -> 0 | K18: =SUM(K12:K17) -> 0 | L18: =SUM(L12:L17) -> 0 | M18: =SUM(M12:M17) -> 0 | N18: =SUM(F18:M18) -> 57000
C20: Srl No | D20: Date | E20: Inv No | F20: Party | G20: Qty | H20: Price | I20: Off Grade | J20: 1799 | K20: 2699 | L20: 588 | M20: 2088 | N20: 2488 | O20: 2688 | P20: 3099 / 1788 | Q20: DENKA | R20: Column1 | T20: Off Grade Stocks And Sales
C21: 1 | D21: 45598 | E21: 257 | F21: Pallmer | G21: 1000 | H21: 168 | J21: 1000 | T21: New Input
C22: 2 | D22: 45600 | E22: 258 | F22: United Polypack | G22: 2000 | H22: 122 | I22: 2000 | T22: Srl No. | U22: Date | V22: Details | W22: Qty | X22: Per Kgs | Y22: Imp No | Z22: Total Cost
C23: 3 | D23: 45600 | E23: 259 | F23: Chandan Synthetic | G23: 1500 | H23: 169 | L23: 1500 | T23: 1 | U23: 45609 | V23: powder + crystal Hexa | W23: 9400 | X23: 88 | Y23: 39 | Z23: =W23*X23 -> 827200
C24: 4 | D24: 45600 | E24: 260 | F24: Chandan Synthetic | G24: 3050 | H24: 167 | J24: 3050 | T24: 2 | U24: 45612 | V24: crystal | W24: 20925 | X24: 88 | Y24: 32 | Z24: =W24*X24 -> 1841400
C25: 5 | D25: 45600 | E25: 261 | F25: Growmore | G25: 600 | H25: 325 | I25: 600 | T25: 3 | U25: 45616 | V25: powder | W25: 16256 | X25: 80 | Y25: 29 | Z25: =W25*X25 -> 1300480
C26: 6 | D26: 45600 | E26: 262 | F26: Growmore | G26: 1000 | H26: 170, 186 | J26: 500 | L26: 500 | T26: 4 | V26: mix JP | Z26: =W26*X26 -> 0
C27: 0 | D27: 45600 | E27: GTC 184 | F27: Doshi | G27: 500 | H27: 167 | M27: 500 | T27: 5 | V27: Sanjay | Z27: =W27*X27 -> 0
C28: 8 | D28: 45600 | E28: GTC185 | F28: AP Bonding | G28: 6000 | H28: 174, 167 | L28: 2000 | M28: 4000 | T28: 6 | V28: temvol | Z28: =W28*X28 -> 0
C29: 9 | D29: 45600 | E29: RR | F29: Meet Products | G29: 1000 | H29: 118, 166 | I29: 500 | J29: 500 | T29: 7 | V29: temvol | Z29: =W29*X29 -> 0
C30: 10 | D30: 45602 | E30: 265 | F30: Shree Mahalaxmi | G30: 1880 | H30: 168 | P30: 1880 | T30: 8 | Z30: =W30*X30 -> 0
C31: 11 | D31: 45602 | E31: 266 | F31: Siva Chemical | G31: 10000 | H31: 107 | I31: 10000 | X31: TOTAL COST | Z31: =SUM(Z23:Z30) -> 3969080
C32: 12 | D32: 45602 | E32: GTC 186 | F32: Shreeji Chem | G32: 1500 | H32: 180 | L32: 1500 | T32: Total New Input:- | W32: =SUM(W23:W30) -> 46581 | X32: Avg Per Kgs Cost | Z32: =Z31/W32 -> 85.208132
C33: 13 | D33: 45603 | E33: 267 | F33: Woodland Indus | G33: 500 | H33: 114 | I33: 500 | T33: Old Stock C/F:- | W33: 205777
C34: 14 | D34: 45603 | E34: 268 | F34: Geeta Wrapers | G34: 1950 | H34: 113, 164 | I34: 1000 | J34: 950 | T34: Total Stocks New & Old :- | W34: =SUM(W32,W33) -> 252358
C35: 15 | D35: 45603 | E35: GTC 188 | F35: Doshi | G35: 60 | H35: 167 | M35: 60 | T35: LESS SALES: (as per sales sheet) | W35: ='Nov 24'!$I$102 -> 72220
C36: 16 | D36: 45604 | E36: GG 8 | F36: Popular | G36: 500 | H36: 181 | O36: 500
C37: 17 | D37: 45604 | E37: GG 9 | F37: Popular | G37: 2000 | H37: 181 | O37: 2000 | T37: NET QTY AVAILABLE: | W37: =SUM(W34-W35) -> 180138
C38: 18 | D38: 45604 | E38: 269 | F38: SKR | G38: 600 | H38: 113 | I38: 600
C39: 18 | D39: 45604 | E39: 270 | F39: Shree Mahalaxmi | G39: 2000 | H39: 115 | I39: 2000
C40: 19 | D40: 45604 | E40: 272 | F40: Mine Chem | G40: 1000 | H40: 120 | I40: 1000
C41: 20 | D41: 45605 | E41: GG 10 | F41: Premier | G41: 1440 | H41: 171 | L41: 1440
C42: 21 | D42: 45605 | E42: 273 | F42: AP Enterprise | G42: 200 | H42: 119 | I42: 200
C43: 22 | D43: 45597 | E43: RR | F43: Fortune | G43: 800 | H43: 125 | I43: 800
C44: 23 | D44: 45607 | E44: 274 | F44: Dipali | G44: 140 | H44: 168 | M44: 140
D45: 45607 | E45: GTC 191 | F45: Aditya | G45: 2000 | H45: 169 | M45: 2000
C46: 24 | D46: 45607 | E46: GG 11 | F46: Vijay Rajshree | G46: 500 | H46: 165 | M46: 500
C47: 26 | D47: 45608 | E47: 275 | F47: Siva Chemical | G47: 10000 | H47: 107 | I47: 10000
C48: 27 | D48: 45608 | E48: GG 12 | F48: Popular | G48: 500 | H48: 181 | O48: 500
C49: 28 | D49: 45609 | E49: GG 13 | F49: Popular | G49: 1000 | H49: 171 | P49: 1000
C50: 29 | D50: 45609 | E50: 277 | F50: Surya | G50: 3500 | H50: 182, 185 | O50: 1500 | P50: 2000
C51: 30 | D51: 45609 | E51: 278 | F51: Pallmer | G51: 580 | H51: 169 | M51: 580
C52: 32 | D52: 45610 | E52: GG 14 | F52: KDM | G52: 2000 | H52: 168 | J52: 2000
C53: 33 | D53: 45611 | E53: 279 | F53: SKR | G53: 2000 | H53: 113 | I53: 2000
C54: 34 | D54: 45611 | E54: 280 | F54: Riddhi Impex | G54: 120 | H54: 114 | I54: 120
C55: 35 | D55: 45612 | E55: GG 15 | F55: Pallmer | G55: 4000 | H55: 168 | M55: 4000
C56: 36 | D56: 45612 | E56: GG 16 | F56: Premier | G56: 3000 | H56: 170, 172 | J56: 1000 | L56: 2000
C57: 37 | D57: 45612 | E57: 282 | F57: Chandan Synthetic | G57: 10000 | H57: 120, 174 | I57: 6000 | K57: 4000
C58: 38 | D58: 45612 | E58: 283 | F58: Paramount | G58: 10000 | H58: 111, 325 | I58: 10000
C59: 41 | D59: 45612 | E59: GTC 194 | F59: Dhanlaxmee | G59: 1200 | H59: 181 | L59: 1200
C60: 39 | D60: 45614 | E60: 284 | F60: Siva Chemical | G60: 10000 | H60: 107 | I60: 10000
C61: 42 | D61: 45614 | E61: 285 | F61: Orinco | G61: 120 | H61: 115 | I61: 120
C62: 40 | D62: 45614 | E62: GTC 195 | F62: Reliable | G62: 1000 | H62: 176 | K62: 1000
C63: 43 | D63: 45614 | E63: GTC 197 | F63: Doshi | G63: 2000 | H63: 171 | M63: 2000
C64: 44 | D64: 45617 | E64: 286 | F64: Siva Chemical | G64: 20 | H64: 300 | I64: 20
C65: 45 | D65: 45617 | E65: 287 | F65: Akshat Corp | G65: 235 | H65: 118, 182 | I65: 160 | P65: 75
C66: 46 | D66: 45617 | E66: GTC 198 | F66: Mine Chem | G66: 3000 | H66: 171 | J66: 3000
C67: 47 | D67: 45619 | E67: 288 | F67: Pallmer | G67: 4000 | H67: 169 | K67: 4000
C68: 48 | D68: 45619 | E68: 289 | F68: Siva Chemical | G68: 10000 | H68: 107 | I68: 10000
C69: 49 | D69: 45621 | E69: 290, 291 | F69: Sagar Dye Chem | G69: 1500 | H69: 169 | M69: 1500
C70: 50 | D70: 45621 | E70: RR | F70: Patidar Adhesives | G70: 1000 | H70: 180 | P70: 1000
C71: 51 | D71: 45622 | E71: 292 | F71: Pallmer | G71: 4000 | H71: 170 | M71: 4000
C72: 52 | D72: 45623 | E72: 293 | F72: AP Enterprise | G72: 200 | H72: 118 | I72: 200
C73: 53 | D73: 45623 | E73: 294 | F73: Shree Mahalaxmi | G73: 2000 | H73: 173.5 | L73: 2000
C74: 54 | D74: 45623 | E74: 295 | F74: Geeta Wrapers | G74: 1000 | H74: 113 | I74: 1000
C75: 55 | D75: 45624 | E75: 296 | F75: Pallmer | G75: 300 | H75: 173 | L75: 300
C76: 56 | D76: 45624 | E76: 297 | F76: RCI Chemsol | G76: 400 | H76: 114 | I76: 400
C77: 57 | D77: 45624 | E77: 298 | F77: Orinco | G77: 3000 | H77: 117 | I77: 3000
C78: 58 | D78: 45626 | E78: 299 | F78: Shree Mahalaxmi | G78: 1500 | H78: 171 | L78: 1500
C79: 59 | F79: Mine Chem
C80: 60 | F80: Popular
C81: 61 | F81: BSB Indus
C82: 62 | F82: Siva
C83: 63 | F83: Shri Ganpatye
C84: 64 | F84: Mine Chem
C85: 65 | F85: Paresh Pure
C86: 66 | F86: Meet Products
C87: 67 | F87: Popular
C88: 68 | F88: Fortune
C89: 69 | F89: Rally Chem
C90: 70 | F90: KK Dye
... C101: 81 | F101: Shree Mahalaxmi
C102: TOTAL | G102: =SUM(G21:G101) -> 136895 | I102: =SUM(I21:I101) -> 72220 | J102: =SUM(J21:J101) -> 12000 | K102: =SUM(K21:K101) -> 9000 | L102: =SUM(L21:L101) -> 13940 | M102: =SUM(M21:M101) -> 19280 | N102: =SUM(N21:N101) -> 0 | O102: =SUM(O21:O101) -> 4500 | P102: =SUM(P21:P101) -> 5955 | Q102: =SUM(Q21:Q101) -> 0
I104: =SUM('Nov 24'!$I$102:'Nov 24'!$Q$102) -> 136895

Sheet Dec 24
D4: Dec 2024 Sales in Nutsell | O4: Prime | P4: Off Grade | Q4: Total
D5: Grades | E5: Off Grade | F5: 1799 | G5: 2699 | H5: 588 | I5: 2088 | J5: 2488 | K5: 2688 | L5: 3099+1788 | M5: DENKA | N5: TOTAL
D6: Old Stck CF | E6: 177004 | F6: 0 | H6: 12460 | I6: 34420 | J6: 0 | K6: 0 | L6: 3045 | M6: 0 | N6: 222979 | O6: 45925 | P6: 177004 | Q6: 222929
D7: New Input In Dec | E7: =W32 -> 10000 | F7: =F18 -> 0 | G7: =G18 -> 0 | H7: =H18 -> 0 | I7: =I18 -> 0 | J7: =J18 -> 0 | K7: =K18 -> 0 | L7: =L18 -> 0 | M7: =M18 -> 25000 | N7: =SUM(E7:M7) -> 35000 | O7: =SUM(F7:M7) -> 25000 | P7: =E7 -> 10000 | Q7: =O7+P7 -> 35000
D8: Sales In Dec | E8: ='Dec 24'!$I$104 -> 52620 | F8: ='Dec 24'!$J$104 -> 0 | G8: ='Dec 24'!$K$104 -> 0 | H8: ='Dec 24'!$L$104 -> 11000 | I8: ='Dec 24'!$M$104 -> 18300 | J8: ='Dec 24'!$N$104 -> 0 | K8: ='Dec 24'!$O$104 -> 0 | L8: ='Dec 24'!$P$104 -> 2225 | M8: ='Dec 24'!$Q$104 -> 10550 | N8: =SUM(E8:M8) -> 94695 | O8: =SUM(F8:M8) -> 42075 | P8: =E8 -> 52620 | Q8: =SUM(O8,P8) -> 94695
D9: Net Stocks CF | E9: =SUM(E6,E7-E8) -> 134384 | F9: =SUM(F6,F7-F8) -> 0 | G9: =SUM(G6,G7-G8) -> 0 | H9: =SUM(H6,H7-H8) -> 1460 | I9: =SUM(I6,I7-I8) -> 16120 | J9: =SUM(J6,J7-J8) -> 0 | K9: =SUM(K6,K7-K8) -> 0 | L9: =SUM(L6,L7-L8) -> 820 | M9: =SUM(M6,M7-M8) -> 14450 | N9: =SUM(N6+N7-N8) -> 163284 | O9: =SUM(F9:M9) -> 32850 | P9: =E9 -> 134384 | Q9: =SUM(O9,P9) -> 167234
C11: PRIME INPUT DETAILS | E11: GRADES | F11: 1799 | G11: 2699 | H11: 588 | I11: 2088 | J11: 2488 | K11: 2688 | L11: 1788 | M11: DENKA / CCP | N11: TOTAL | O11: FROM | P11: IMP NO
C12: SRL NO | D12: MAKE | E12: DATE | N12: =SUM(F12:M12) -> 0
C13: 1 | D13: Wanwei | N13: =SUM(F13:M13) -> 0
C14: 2 | D14: IM | N14: =SUM(F14:M14) -> 0
C15: 3 | D15: CCP | E15: 45631 | M15: 25000 | N15: =SUM(F15:M15) -> 25000
C16: 4 | D16: Wanwei | N16: =SUM(F16:M16) -> 0
C17: 5 | D17: Denka | N17: =SUM(F17:M17) -> 0
C18: TOTAL | F18: =SUM(F12:F17) -> 0 | G18: =SUM(G12:G17) -> 0 | H18: =SUM(H12:H17) -> 0 | I18: =SUM(I12:I17) -> 0 | J18: =SUM(J12:J17) -> 0 | K18: =SUM(K12:K17) -> 0 | L18: =SUM(L12:L17) -> 0 | M18: =SUM(M12:M17) -> 25000 | N18: =SUM(F18:M18) -> 25000
C20: Srl No | D20: Date | E20: Inv No | F20: Party | G20: Qty | H20: Price | I20: Off Grade | J20: 1799 | K20: 2699 | L20: 588 | M20: 2088 | N20: 2488 | O20: 2688 | P20: 3099 / 1788 | Q20: DENKA / CCP | R20: CCP | T20: Off Grade Stocks And Sales
C21: 1 | D21: 45628 | E21: 301 | F21: Siva Chemical | G21: 10000 | H21: 107 | I21: 10000 | T21: New Input
C22: 2 | D22: 45628 | E22: 302 | F22: Siva Chemical | G22: 100 | H22: 172 | L22: 100 | T22: Srl No. | U22: Date | V22: Details | W22: Qty | X22: Per Kgs | Y22: Imp No | Z22: Total Cost
C23: 3 | D23: 45628 | E23: 303 | F23: Punav Enterprises | G23: 2000 | H23: 103 | I23: 2000 | T23: 1 | U23: 45645 | V23: powder + crystal Hexa | W23: 10000 | X23: 75 | Y23: 45 | Z23: =W23*X23 -> 750000
C24: 4 | D24: 45629 | E24: GTC 200 | F24: Divysai | G24: 300 | H24: 165 | M24: 300 | T24: 2 | V24: crystal | Y24: 32 | Z24: =W24*X24 -> 0
C25: 5 | D25: 45629 | E25: GTC 201 | F25: AP Bonding | G25: 5000 | H25: 171, 165 | L25: 2000 | M25: 3000 | T25: 3 | V25: powder | Y25: 29 | Z25: =W25*X25 -> 0
C26: 6 | D26: 45628 | E26: GG 21 | F26: Premier | G26: 2000 | H26: 172 | L26: 2000 | T26: 4 | V26: mix JP | Z26: =W26*X26 -> 0
C27: 0 | D27: 45631 | E27: GG 23 | F27: Mahalaxmi | G27: 5000 | H27: 171.5 | L27: 5000 | T27: 5 | V27: Sanjay | Z27: =W27*X27 -> 0
C28: 8 | D28: 45631 | E28: GTC 204 | F28: AP Bonding | G28: 2000 | H28: 185 | Q28: 2000 | T28: 6 | V28: temvol | Z28: =W28*X28 -> 0
C29: 9 | D29: 45631 | E29: GTC 205 | F29: Veena | G29: 760 | H29: 185, 190 | Q29: 760 | T29: 7 | V29: temvol | Z29: =W29*X29 -> 0
C30: 10 | D30: 45633 | E30: 305 | F30: Guruji | G30: 2000 | H30: 112 | I30: 2000 | T30: 8 | Z30: =W30*X30 -> 0
C31: 11 | D31: 45633 | E31: 306 | F31: KDM | G31: 1000 | H31: 115 | I31: 1000 | X31: TOTAL COST | Z31: =SUM(Z23:Z30) -> 750000
C32: 12 | D32: 45635 | E32: 307 | F32: Siva Chemical | G32: 10000 | H32: 107 | I32: 10000 | T32: Total New Input:- | W32: =SUM(W23:W30) -> 10000 | X32: Avg Per Kgs Cost | Z32: =Z31/W32 -> 75
C33: 13 | D33: 45637 | E33: 309 | F33: Geeta Wrapers | G33: 10000 | H33: 113 | I33: 1000 | T33: Old Stock C/F:- | W33: 177004
C34: 14 | D34: 45637 | E34: 310 | F34: SKS Fine | G34: 1000 | H34: 112 | I34: 1000 | T34: Total Stocks New & Old :- | W34: =SUM(W32,W33) -> 187004
C35: 15 | D35: 45635 | E35: GTC 208 | F35: Disha Dye | G35: 500 | H35: 182 | Q35: 500 | T35: LESS SALES: (as per sales sheet) | W35: ='Dec 24'!$I$104 -> 52620
C36: 16 | D36: 45635 | E36: GTC 211 | F36: Can Image | G36: 5000 | H36: 178 | M36: 5000
C37: 17 | D37: 45638 | E37: 311 | F37: Amritha | G37: 2000 | H37: 104 | I37: 2000 | T37: NET QTY AVAILABLE: | W37: =SUM(W34-W35) -> 134384
C38: 18 | D38: 45639 | E38: 314 | F38: BSB Indus | G38: 2000 | H38: 109 | I38: 2000
C39: 18 | D39: 45639 | E39: 315 | F39: Mangalam Dye | G39: 200 | H39: 119 | I39: 200
C40: 19 | D40: 45639 | E40: 316 | F40: Mine Chem | G40: 20 | H40: 120 | I40: 20 | T40: Cost if its 750 PMT = 75
C41: 20 | D41: 45640 | E41: 318 | F41: Sagar Dye Chem | G41: 1500 | H41: 180 | Q41: 2000
C42: 21 | D42: 45640 | E42: 319 | F42: Eco Industries | G42: 10000 | H42: 130 | I42: 10000
C43: 22 | D43: 45640 | E43: 320 | F43: Kraft Bond | G43: 1200 | H43: 114 | I43: 1200
C44: 23 | D44: 45639 | E44: GTC 216 | F44: Shreeji Dye | G44: 500 | H44: 177 | Q44: 500
D45: 45640 | E45: GTC 217 | F45: Mine Chem | G45: 100 | H45: 180 | P45: 100
D46: 45640 | E46: GTC 218 | F46: Mine Chem | G46: 500 | H46: 170 | P46: 500
C47: 24 | D47: 45640 | E47: GTC 220 | F47: Aditya | G47: 1000 | H47: 184 | Q47: 1000
C48: 26 | D48: 45640 | E48: GG 26 | F48: Pallmer | G48: 5000 | H48: 167 | M48: 5000
C49: 27 | D49: 45640 | E49: GG 27 | F49: Pallmer | G49: 5000 | H49: 168 | M49: 5000
D50: 45642 | E50: GTC 221 | F50: Aditya | G50: 1000 | H50: 184 | Q50: 1000
C51: 28 | D51: 45644 | E51: 321 | F51: Arun Enterprise | G51: 200 | H51: 181 | Q51: 200
C52: 29 | D52: 45647 | E52: 323 | F52: Surya | G52: 100 | H52: 118 | I52: 500
C53: 30 | D53: 45647 | E53: RR | F53: Gurpreet | G53: 400 | H53: 188 | Q53: 400
C54: 32 | D54: 45647 | E54: RR | F54: Meet Products | G54: 500 | H54: 119 | I54: 500
C55: 33 | D55: 45650 | E55: 324 | F55: Shree Mahalaxmi | G55: 500 | H55: 115 | I55: 500
C56: 34 | D56: 45650 | E56: GG 30 | F56: Mahalaxmi | G56: 1900 | H56: 172 | L56: 1900
C57: 35 | D57: 45651 | E57: 325 | F57: Pallmer | G57: 1500 | H57: 176
C58: 36 | D58: 45651 | E58: 326 | F58: Growmore | G58: 200 | H58: 190 | Q58: 190
C59: 37 | D59: 45651 | E59: RR | F59: Gurpreet | G59: 200 | H59: 188 | P59: 200
C60: 38 | D60: 45652 | E60: 327 | F60: Surya | G60: 2025 | H60: 117, 181 | I60: 600 | P60: 1425
C61: 41 | D61: 45652 | E61: 329 | F61: Can Image | G61: 2000 | H61: 198 | Q61: 2000
C62: 39 | D62: 45654 | E62: 330 | F62: Mine Chem | G62: 2000 | H62: 118 | I62: 2000
C63: 42 | D63: 45656 | E63: 331 | F63: Shree Mahalaxmi | G63: 2000 | H63: 115 | I63: 2000
C64: 40 | D64: 45657 | E64: 332 | F64: United Polypack | G64: 3000 | H64: 122 | I64: 3000
C65: 43 | D65: 45657 | E65: 333 | F65: Woodland Chemicals | G65: 600 | H65: 114 | I65: 600
C66: 44 | D66: 45657 | E66: 334 | F66: Apeksha | G66: 500 | H66: 114 | I66: 500
C67: 45 | F67: Akshat Corp
C68: 46 | F68: Mine Chem
C69: 47 | F69: Pallmer
C70: 48 | F70: Siva Chemical
C71: 49 | F71: Sagar Dye Chem
C72: 50 | F72: Patidar Adhesives
C73: 51 | F73: Pallmer
C74: 52 | F74: AP Enterprise
C75: 53 | F75: Shree Mahalaxmi
C76: 54 | F76: Geeta Wrapers
C77: 55 | F77: Pallmer
C78: 56 | F78: RCI Chemsol
... C103: 81 | F103: Shree Mahalaxmi
C104: TOTAL | D104: 12 | G104: =SUM(G21:G103) -> 104305 | I104: =SUM(I21:I103) -> 52620 | J104: =SUM(J21:J103) -> 0 | K104: =SUM(K21:K103) -> 0 | L104: =SUM(L21:L103) -> 11000 | M104: =SUM(M21:M103) -> 18300 | N104: =SUM(N21:N103) -> 0 | O104: =SUM(O21:O103) -> 0 | P104: =SUM(P21:P103) -> 2225 | Q104: =SUM(Q21:Q103) -> 10550
I106: =SUM('Dec 24'!$I$104:'Dec 24'!$Q$104) -> 94695

Sheet Jan 25
D4: Dec 2024 Sales in Nutsell | O4: Prime | P4: Off Grade | Q4: Total
D5: Grades | E5: Off Grade | F5: 1799 | G5: 2699 | H5: 588 | I5: 2088 | J5: 2488 | K5: 2688 | L5: 3099+1788 | M5: DENKA / CCP | N5: TOTAL
D6: Old Stck CF | E6: 134384 | F6: 0 | G6: 0 | H6: 1460 | I6: 16120 | J6: 0 | K6: 0 | L6: 820 | M6: 14450 | N6: 163284 | O6: 45925 | P6: 177004 | Q6: 222929
D7: New Input In Dec | E7: =W32 -> 104104 | F7: =F18 -> 18000 | G7: =G18 -> 10000 | H7: =H18 -> 0 | I7: =I18 -> 0 | J7: =J18 -> 0 | K7: =K18 -> 0 | L7: =L18 -> 0 | M7: =M18 -> 88000 | N7: =SUM(E7:M7) -> 220104 | O7: =SUM(F7:M7) -> 116000 | P7: =E7 -> 104104 | Q7: =O7+P7 -> 220104
D8: Sales In Dec | E8: ='Jan 25'!$I$103 -> 40640 | F8: ='Jan 25'!$J$103 -> 18000 | G8: ='Jan 25'!$K$103 -> 1600 | H8: ='Jan 25'!$L$103 -> 1900 | I8: ='Jan 25'!$M$103 -> 9180 | J8: ='Jan 25'!$N$103 -> 0 | K8: ='Jan 25'!$O$103 -> 0 | L8: ='Jan 25'!$P$103 -> 400 | M8: ='Jan 25'!$Q$103 -> 49540 | N8: =SUM(E8:M8) -> 121260 | O8: =SUM(F8:M8) -> 80620 | P8: =E8 -> 40640 | Q8: =SUM(O8,P8) -> 121260
D9: Net Stocks CF | E9: =SUM(E6,E7-E8) -> 197848 | F9: =SUM(F6,F7-F8) -> 0 | G9: =SUM(G6,G7-G8) -> 8400 | H9: =SUM(H6,H7-H8) -> -440 | I9: =SUM(I6,I7-I8) -> 6940 | J9: =SUM(J6,J7-J8) -> 0 | K9: =SUM(K6,K7-K8) -> 0 | L9: =SUM(L6,L7-L8) -> 420 | M9: =SUM(M6,M7-M8) -> 52910 | N9: =SUM(N6+N7-N8) -> 262128 | O9: =SUM(F9:M9) -> 68230 | P9: =E9 -> 197848 | Q9: =SUM(O9,P9) -> 266078
C11: PRIME INPUT DETAILS | E11: GRADES | F11: 1799 | G11: 2699 | H11: 588 | I11: 2088 | J11: 2488 | K11: 2688 | L11: 1788 | M11: DENKA / CCP | N11: TOTAL | O11: FROM | P11: IMP NO
C12: SRL NO | D12: MAKE | E12: DATE | N12: =SUM(F12:M12) -> 0
C13: 1 | D13: Wanwei | E13: 45678 | F13: 18000 | G13: 10000 | N13: =SUM(F13:M13) -> 28000
C14: 2 | D14: IM | N14: =SUM(F14:M14) -> 0
C15: 3 | D15: CCP | E15: 45688 | M15: 25000 | V15: FOR 950 | W15: 98
C16: 4 | D16: CCP | E16: 45674 | M16: 25000 | N16: =SUM(F16:M16) -> 25000 | V16: FOR 750 | W16: 78
C17: 5 | D17: Denka | E17: 45665 | M17: 38000 | N17: =SUM(F17:M17) -> 38000 | V17: FOR 850 | W17: 88
C18: TOTAL | F18: =SUM(F12:F17) -> 18000 | G18: =SUM(G12:G17) -> 10000 | H18: =SUM(H12:H17) -> 0 | I18: =SUM(I12:I17) -> 0 | J18: =SUM(J12:J17) -> 0 | K18: =SUM(K12:K17) -> 0 | L18: =SUM(L12:L17) -> 0 | M18: =SUM(M12:M17) -> 88000 | N18: =SUM(F18:M18) -> 116000 | V18: FOR 775 | W18: 80
V19: FOR 680 | W19: 70
C20: Srl No | D20: Date | E20: Inv No | F20: Party | G20: Qty | H20: Price | I20: Off Grade | J20: 1799 | K20: 2699 | L20: 588 | M20: 2088 | N20: 2488 | O20: 2688 | P20: 3099 / 1788 | Q20: DENKA / CCP | R20: CCP | T20: Off Grade Stocks And Sales
C21: 1 | D21: 45658 | E21: 335 | F21: Sagar Dye Chem | G21: 1500 | H21: 182 | Q21: 1500 | T21: New Input
C22: 2 | D22: 45661 | E22: 338 | F22: RCI Chemsol | G22: 200 | H22: 115 | I22: 200 | T22: Srl No. | U22: Date | V22: Details | W22: Qty | X22: Per Kgs | Y22: Imp No | Z22: Total Cost
C23: 3 | D23: 45663 | E23: 339 | F23: Sagar Dye Chem | G23: 1600 | H23: 166 | M23: 1600 | T23: 1 | U23: 45663 | V23: powder + crystal | W23: 21065 | X23: 98 | Y23: 43 | Z23: =W23*X23 -> 2064370
C24: 4 | D24: 45663 | E24: 340 | F24: SKR | G24: 2000 | H24: 114 | I24: 2000 | T24: 2 | U24: 45663 | V24: mix JP | W24: 17160 | X24: 78 | Y24: 33 | Z24: =W24*X24 -> 1338480
C25: 5 | D25: 45663 | E25: 341 | F25: Siva Chemical | G25: 10000 | H25: 107 | I25: 10000 | T25: 3 | U25: 45666 | V25: HEXA | W25: 19200 | X25: 78 | Y25: 49 | Z25: =W25*X25 -> 1497600
C26: 6 | D26: 45664 | E26: 342 | F26: Geeta Wrapers | G26: 1000 | H26: 113 | I26: 1000 | T26: 4 | U26: 45666 | V26: mix JP | W26: 15072 | X26: 88 | Y26: 34 | Z26: =W26*X26 -> 1326336
C27: 0 | D27: 45664 | E27: 345 | F27: Pallmer | G27: 500 | H27: 179 | I27: 500 | Q27: 500 | T27: 5 | U27: 45678 | V27: mix JP | W27: 15994 | X27: 80 | Y27: 36 | Z27: =W27*X27 -> 1279520
C28: 8 | D28: 45664 | E28: 346 | F28: Adinath | G28: 500 | H28: 181 | Q28: 500 | T28: 6 | U28: 45679 | V28: mix JP | W28: 15613 | X28: 70 | Y28: 37 | Z28: =W28*X28 -> 1092910
C29: 9 | D29: 45664 | E29: 347 | F29: Pallmer | G29: 500 | H29: 107 | I29: 500 | T29: 7 | V29: temvol | Z29: =W29*X29 -> 0
C30: 10 | D30: 45664 | E30: 348 | F30: Arun Enterprise | G30: 200 | H30: 181 | I30: 200 | Q30: 200 | T30: 8 | Z30: =W30*X30 -> 0
C31: 11 | D31: 45658 | E31: GTC 236 | F31: Aditya | G31: 1440 | H31: 184 | Q31: 1440 | X31: TOTAL COST | Z31: =SUM(Z23:Z30) -> 8599216
C32: 12 | D32: 45660 | E32: GTC 238 | F32: Divysai | G32: 360 | H32: 170 | M32: 360 | T32: Total New Input:- | W32: =SUM(W23:W30) -> 104104 | X32: Avg Per Kgs Cost | Z32: =Z31/W32 -> 82.602167
C33: 13 | D33: 45665 | E33: GTC 241 | F33: Jai Aravali | G33: 19000 | H33: 210 | Q33: 19000 | T33: Old Stock C/F:- | W33: 134384
C34: 14 | D34: 45665 | E34: GTC 242 | F34: Aditya | G34: 1000 | H34: 208 | Q34: 1000 | T34: Total Stocks New & Old :- | W34: =SUM(W32,W33) -> 238488
C35: 15 | D35: 45666 | E35: GTC 245 | F35: Veena | G35: 800 | H35: 184, 208 | Q35: 800 | T35: LESS SALES: (as per sales sheet) | W35: ='Jan 25'!$I$103 -> 40640
C36: 16 | D36: 45666 | E36: RR | F36: Fortune | G36: 800 | H36: 125 | I36: 800
C37: 17 | D37: 45667 | E37: 351 | F37: Geeta Wrapers | G37: 1000 | H37: 118 | I37: 1000 | T37: NET QTY AVAILABLE: | W37: =SUM(W34-W35) -> 197848
C38: 18 | D38: 45667 | E38: 352 | F38: Surya | G38: 1500 | H38: 214 | Q38: 1500
C39: 18 | D39: 45667 | E39: 353 | F39: Veekay | G39: 1000 | H39: 109 | I39: 1000
C40: 19 | D40: 45667 | E40: 354 | F40: AP Enterprise | G40: 200 | H40: 118 | I40: 200 | T40: Cost if its 750 PMT = 75
C41: 20 | D41: 45667 | E41: GTC 247 | F41: SD Enterprise | G41: 500 | H41: 212 | Q41: 500
C42: 21 | D42: 45668 | E42: RR | F42: Paresh Salot Broker | G42: 2000 | H42: 206 | Q42: 2000
C43: 22 | D43: 45668 | E43: GTC 248 | F43: Popular | G43: 1500 | H43: 177, 209 | L43: 1000 | Q43: 500
C44: 23 | D44: 45668 | E44: GTC 249 | F44: Yug Décor | G44: 820 | H44: 168 | M44: 820
C45: 24 | D45: 45673 | E45: 358 | F45: Kunal Chem | G45: 440 | H45: 191 | Q45: 440
C46: 25 | D46: 45674 | E46: 359 | F46: Shubham Corp | G46: 300 | H46: 188 | Q46: 300
C47: 26 | D47: 45672 | E47: GTC 251 | F47: Veena | G47: 1000 | H47: 209 | Q47: 1000
C48: 28 | D48: 45674 | E48: GTC 253 | F48: Yogini | G48: 200 | H48: 189 | Q48: 200
C49: 29 | D49: 45675 | E49: GTC 254 | F49: Aditya | G49: 500 | H49: 164 | K49: 500
C50: 30 | D50: 45675 | E50: GTC 255 | F50: Adheswar | G50: 2000 | H50: 181 | Q50: 2000
C51: 29 | D51: 45675 | E51: 360 | F51: Shah & Sons | G51: 340 | H51: 184 | Q51: 800
C52: 30 | D52: 45673 | E52: RR | F52: Shri Ganpatye | G52: 300 | H52: 209 | Q52: 300
C53: 32 | D53: 45670 | E53: RR | F53: Meet Products | G53: 900 | H53: 119, 209 | I53: 600 | Q53: 300
C54: 33 | D54: 45677 | E54: GTC 256 | F54: Dhanlaxmee | G54: 1500 | H54: 214 | Q54: 1500
C55: 34 | D55: 45678 | E55: GTC 258 | F55: Aditya | G55: 4000 | H55: 185, 190 | Q55: 4000
C56: 35 | D56: 45678 | E56: GTC 259 | F56: Aditya | G56: 1000 | H56: 187 | Q56: 1000
C57: 36 | D57: 45679 | E57: GTC 261 | F57: Doshi | G57: 1000 | H57: 193 | Q57: 1000
C58: 37 | D58: 45675 | E58: 361 | F58: Shree Mahalaxmi | G58: 340 | H58: 115, 185 | I58: 40 | Q58: 300
C59: 38 | D59: 45676 | E59: 362 | F59: Chandan Sybthetic | G59: 10000 | H59: 120, 159 | I59: 5000 | J59: 5000
C60: 41 | D60: 45676 | E60: 363 | F60: Kraft Bond | G60: 1000 | H60: 114 | I60: 1000
C61: 39 | D61: 45677 | E61: 364 | F61: Dhiren Enterprise | G61: 2000 | H61: 189 | Q61: 2000
C62: 42 | D62: 45677 | E62: 365 | F62: Pallmer | G62: 4000 | H62: 158 | J62: 4000
C63: 40 | D63: 45677 | E63: 366 | F63: Pallmer | G63: 500 | H63: 182 | Q63: 500
C64: 43 | D64: 45677 | E64: 368 | F64: Sunil Dye | G64: 300 | H64: 185, 193 | Q64: 300
C65: 44 | D65: 45677 | E65: 369 | F65: Shree Mahalaxmi | G65: 260 | H65: 188 | Q65: 260
C66: 45 | D66: 45678 | E66: 371 | F66: Mine Chem | G66: 1000 | H66: 115 | I66: 1000
C67: 46 | D67: 45678 | E67: 372 | F67: SKR | G67: 1000 | H67: 113 | I67: 1000
C68: 47 | D68: 45678 | E68: 374 | F68: Swastik Chem | G68: 100 | H68: 189 | Q68: 100
C69: 48 | D69: 45679 | E69: 375 | F69: SKR | G69: 100 | H69: 112 | I69: 100
C70: 49 | D70: 45679 | E70: 377 | F70: Kunal Chem | G70: 100 | H70: 184 | Q70: 100
C71: 50 | D71: 45679 | E71: 378 | F71: Mine Chem | G71: 100 | H71: 170 | K71: 100
C72: 51 | D72: 45680 | E72: 379 | F72: Pallmer | G72: 1000 | H72: 157 | J72: 1000
C73: 52 | D73: 45680 | E73: 380 | F73: Purvi Enterprise | G73: 1000 | H73: 105 | I73: 1000
C74: 53 | D74: 45680 | E74: 381 | F74: Pallmer | G74: 400 | H74: 174 | M74: 400
C75: 54 | D75: 45680 | E75: 382 | F75: Chandan Sybthetic | G75: 5000 | H75: 159 | J75: 5000
C76: 55 | D76: 45680 | E76: GTC 262 | F76: Alpha Chem | G76: 1500 | H76: 193 | Q76: 1500
C77: 56 | D77: 45681 | E77: 384 | F77: Surya | G77: 2000 | H77: 117 | I77: 2000
C78: 57 | D78: 45681 | E78: 385 | F78: Amritha | G78: 2000 | H78: 105 | I78: 2000
C79: 58 | D79: 45682 | E79: 388 | F79: Devankshi | G79: 200 | H79: 191 | Q79: 200
C80: 59 | D80: 45684 | E80: 390 | F80: Akshat | G80: 200 | H80: 118 | I80: 200
C81: 60 | D81: 45685 | E81: 391 | F81: Growmore | G81: 1200 | H81: 170, 190 | J81: 1000 | Q81: 200
C82: 61 | D82: 45682 | E82: GTC 265 | F82: Mine Chem | G82: 400 | H82: 170 | P82: 400
C83: 62 | D83: 45683 | E83: GTC 266 | F83: Can Image | G83: 5000 | H83: 178 | M83: 5000
C84: 63 | D84: 45684 | E84: GTC 267 | F84: Yogini | G84: 125 | H84: 154 | J84: 125
C85: 64 | D85: 45684 | E85: GTC 268 | F85: Popular | G85: 900 | H85: 179 | L85: 900
C86: 65 | D86: 45684 | E86: GTC 269 | F86: Popular | G86: 1000 | H86: 179 | M86: 1000
C87: 66 | D87: 45685 | E87: GTC 270 | F87: Mine Chem | G87: 500 | H87: 205 | Q87: 500
C88: 67 | D88: 45685 | E88: GTC 271 | F88: Veena | G88: 800 | H88: 187, 209 | Q88: 800
C89: 68 | D89: 45687 | E89: 393 | F89: Paramount | G89: 6000 | H89: 115 | I89: 6000
C90: 69 | D90: 45687 | E90: 394 | F90: Paramount | G90: 1000 | H90: 165 | K90: 1000
C91: 70 | D91: 45687 | E91: 397 | F91: Shree Mahalaxmi | G91: 200 | H91: 115 | I91: 200
C92: 71 | D92: 45687 | E92: 398 | F92: Kanha Trading | G92: 100 | H92: 120 | I92: 100
C93: 72 | D93: 45687 | E93: 399 | F93: SKR | G93: 3000 | H93: 113 | I93: 3000
C94: 73 | D94: 45687 | E94: GTC 273 | F94: Chandan Sybthetic | G94: 1875 | H94: 159 | J94: 1875
C95: 74 | D95: 45688 | E95: GTC 274 | F95: SB Enterprise | G95: 500 | H95: 211 | Q95: 500
C96: 75 | F96: Guruji
C97: 76 | F97: Purvi Enterprise
C98: 77 | F98: Gurpreet
C99: 78 | F99: Paramount
C100: 79 | F100: Fortune
C101: 80 | F101: Chemi Care
C102: 81 | F102: Shree Mahalaxmi
C103: TOTAL | D103: 12 | G103: =SUM(G21:G102) -> 120100 | I103: =SUM(I21:I102) -> 40640 | J103: =SUM(J21:J102) -> 18000 | K103: =SUM(K21:K102) -> 1600 | L103: =SUM(L21:L102) -> 1900 | M103: =SUM(M21:M102) -> 9180 | N103: =SUM(N21:N102) -> 0 | O103: =SUM(O21:O102) -> 0 | P103: =SUM(P21:P102) -> 400 | Q103: =SUM(Q21:Q102) -> 49540
I105: =SUM('Jan 25'!$I$103:'Jan 25'!$Q$103) -> 121260

Sheet Feb 25
D4: Feb 2025 Sales in Nutsell | O4: Prime | P4: Off Grade | Q4: Total
D5: Grades | E5: Off Grade | F5: 1799 | G5: 2699 | H5: 588 | I5: 2088 | J5: 2488 | K5: 2688 | L5: 3099+1788 | M5: DENKA / CCP | N5: TOTAL
D6: Old Stck CF | E6: 197848 | F6: 0 | G6: 8400 | H6: -440 | I6: 6940 | J6: 0 | K6: 0 | L6: 420 | M6: 52910 | N6: =SUM(E6:M6) -> 266078 | O6: 45925 | P6: 177004 | Q6: 222929
D7: New Input In Dec | E7: =W32 -> 18697 | F7: =F18 -> 0 | G7: =G18 -> 0 | H7: =H18 -> 0 | I7: =I18 -> 0 | J7: =J18 -> 0 | K7: =K18 -> 0 | L7: =L18 -> 0 | M7: =M18 -> 0 | N7: =SUM(E7:M7) -> 18697 | O7: =SUM(F7:M7) -> 0 | P7: =E7 -> 18697 | Q7: =O7+P7 -> 18697
D8: Sales In Dec | E8: ='Feb 25'!$I$103 -> 20260 | F8: ='Feb 25'!$J$103 -> 5000 | G8: ='Feb 25'!$K$103 -> 2425 | H8: ='Feb 25'!$L$103 -> 0 | I8: ='Feb 25'!$M$103 -> 1400 | J8: ='Feb 25'!$N$103 -> 0 | K8: ='Feb 25'!$O$103 -> 0 | L8: ='Feb 25'!$P$103 -> 0 | M8: ='Feb 25'!$Q$103 -> 22200 | N8: =SUM(E8:M8) -> 51285 | O8: =SUM(F8:M8) -> 31025 | P8: =E8 -> 20260 | Q8: =SUM(O8,P8) -> 51285
D9: Net Stocks CF | E9: =SUM(E6,E7-E8) -> 196285 | F9: =SUM(F6,F7-F8) -> -5000 | G9: =SUM(G6,G7-G8) -> 5975 | H9: =SUM(H6,H7-H8) -> -440 | I9: =SUM(I6,I7-I8) -> 5540 | J9: =SUM(J6,J7-J8) -> 0 | K9: =SUM(K6,K7-K8) -> 0 | L9: =SUM(L6,L7-L8) -> 420 | M9: =SUM(M6,M7-M8) -> 30710 | N9: =SUM(N6+N7-N8) -> 233490 | O9: =SUM(F9:M9) -> 37205 | P9: =E9 -> 196285 | Q9: =SUM(O9,P9) -> 233490
C11: PRIME INPUT DETAILS | E11: GRADES | F11: 1799 | G11: 2699 | H11: 588 | I11: 2088 | J11: 2488 | K11: 2688 | L11: 1788 | M11: DENKA / CCP | N11: TOTAL | O11: FROM | P11: IMP NO
C12: SRL NO | D12: MAKE | E12: DATE | N12: =SUM(F12:M12) -> 0 | V12: FOR 950 | W12: 98
C13: 1 | D13: Wanwei | V13: FOR 750 | W13: 78
C14: 2 | D14: IM | V14: FOR 850 | W14: 88
C15: 3 | D15: CCP | V15: FOR 775 | W15: 80
C16: 4 | D16: Wanwei | V16: FOR 680 | W16: 70
C17: 5 | D17: Denka | V17: FOR 725 | W17: 75
C18: TOTAL | F18: =SUM(F12:F17) -> 0 | G18: =SUM(G12:G17) -> 0 | H18: =SUM(H12:H17) -> 0 | I18: =SUM(I12:I17) -> 0 | J18: =SUM(J12:J17) -> 0 | K18: =SUM(K12:K17) -> 0 | L18: =SUM(L12:L17) -> 0 | M18: =SUM(M12:M17) -> 0 | N18: =SUM(F18:M18) -> 0
C20: Srl No | D20: Date | E20: Inv No | F20: Party | G20: Qty | H20: Price | I20: Off Grade | J20: 1799 | K20: 2699 | L20: 588 | M20: 2088 | N20: 2488 | O20: 2688 | P20: 3099 / 1788 | Q20: DENKA / CCP | R20: CCP | T20: Off Grade Stocks And Sales
C21: 1 | D21: 45689 | E21: GTC 276 | F21: Surya | G21: 2000 | H21: 169 | K21: 2000 | T21: New Input
C22: 2 | D22: 45689 | E22: GTC 277 | F22: Nikhil Adhesive | G22: 500 | H22: 191 | Q22: 500 | T22: Srl No. | U22: Date | V22: Details | W22: Qty | X22: Per Kgs | Y22: Imp No | Z22: Total Cost
C23: 3 | D23: 45691 | E23: GTC 278 | F23: Yogini | G23: 800 | Q23: 800 | T23: 1 | U23: 45715 | V23: powder + crystal | W23: 18697 | X23: 75 | Y23: 40 | Z23: =W23*X23 -> 1402275
C24: 4 | D24: 45692 | E24: GTC 281 | F24: V B Enterprise | G24: 500 | Q24: 500 | T24: 2 | V24: mix JP | X24: 78 | Z24: =W24*X24 -> 0
C25: 5 | D25: 45689 | E25: 400 | F25: Surya | G25: 1500 | H25: 117 | I25: 1500 | T25: 3 | V25: HEXA | X25: 78 | Z25: =W25*X25 -> 0
C26: 6 | D26: 45691 | E26: 401 | F26: Akshat | G26: 360 | H26: 119 | I26: 360 | T26: 4 | V26: mix JP | X26: 88 | Z26: =W26*X26 -> 0
C27: 7 | D27: 45692 | E27: 402 | F27: Paresh Pure | G27: 2100 | H27: 125 | I27: 2100 | T27: 5 | V27: mix JP | X27: 80 | Z27: =W27*X27 -> 0
C28: 8 | D28: 45692 | E28: 403 | F28: Geeta Wrapers | G28: 1000 | H28: 118 | I28: 1000 | T28: 6 | V28: mix JP | X28: 70 | Z28: =W28*X28 -> 0
C29: 9 | D29: 45692 | E29: 404 | F29: Kunal Dye Chem | G29: 200 | H29: 167 | K29: 200 | T29: 7 | V29: temvol | Z29: =W29*X29 -> 0
C30: 10 | D30: 45694 | E30: 405 | F30: Sagar Corporation | G30: 100 | H30: 115 | I30: 100 | T30: 8 | Z30: =W30*X30 -> 0
C31: 11 | D31: 45693 | E31: GTC 282 | F31: Sagar Corporation | G31: 200 | H31: 181 | Q31: 200 | X31: TOTAL COST | Z31: =SUM(Z23:Z30) -> 1402275
C32: 12 | D32: 45694 | E32: GTC 283 | F32: Popular | G32: 1400 | H32: 179 | M32: 1400 | T32: Total New Input:- | W32: =SUM(W23:W30) -> 18697 | X32: Avg Per Kgs Cost | Z32: =Z31/W32 -> 75
C33: 13 | D33: 45694 | E33: GTC 283 | F33: Popular | G33: 1100 | H33: 185, 186,209 | Q33: 1100 | T33: Old Stock C/F:- | W33: 197848
C34: 14 | D34: 45694 | E34: GTC 284 | F34: Growmore | G34: 1000 | H34: 196 | Q34: 1000 | T34: Total Stocks New & Old :- | W34: =SUM(W32,W33) -> 216545
C35: 15 | D35: 45695 | E35: GTC 285 | F35: Vraj Chem | G35: 200 | H35: 181 | Q35: 200 | T35: LESS SALES: (as per sales sheet) | W35: ='Feb 25'!$I$103 -> 20260
C36: 16 | D36: 45695 | E36: GTC 286 | F36: Alpha Chem | G36: 500 | H36: 191 | Q36: 500
C37: 17 | D37: 45696 | E37: 406 | F37: Swastik Chem | G37: 300 | H37: 183 | Q37: 300 | T37: NET QTY AVAILABLE: | W37: =SUM(W34-W35) -> 196285
C38: 18 | D38: 45696 | E38: 407 | F38: Pallmer | G38: 1000 | H38: 180 | Q38: 1000
C39: 18 | D39: 45698 | E39: 409 | F39: Kraft Bond | G39: 200 | H39: 120 | I39: 200
C40: 19 | D40: 45699 | E40: GTC 290 | F40: AP Bonding | G40: 2000 | H40: 167 | J40: 2000 | T40: Cost if its 750 PMT = 75
C41: 20 | D41: 45699 | E41: GTC 291 | F41: Texto | G41: 500 | H41: 185 | Q41: 500
C42: 21 | D42: 45701 | E42: GTC 293 | F42: Anupam Chem | G42: 1000 | H42: 190 | Q42: 1000
C43: 22 | D43: 45700 | E43: 411 | F43: SKS Fine | G43: 1000 | H43: 112 | I43: 1000
C44: 23 | D44: 45701 | E44: 412 | F44: Abu Traders | G44: 100 | H44: 109 | I44: 100
C45: 24 | D45: 45702 | E45: 417 | F45: RCI | G45: 200 | H45: 114 | I45: 200
C46: 25 | D46: 45702 | E46: 418 | F46: Geeta Wrapers | G46: 1000 | H46: 118 | I46: 1000
C47: 26 | D47: 45702 | E47: 419 | F47: Dhawan | G47: 5000 | H47: 113 | I47: 5000
C48: 28 | D48: 45702 | E48: GTC 295 | F48: Aditya | G48: 1000 | H48: 166 | J48: 1000
C49: 29 | D49: 45702 | E49: GTC 296 | F49: Doshi | G49: 1500 | H49: 179 | Q49: 1000
C50: 30 | D50: 45705 | E50: 421 | F50: Punav | G50: 2000 | H50: 105 | I50: 2000
C51: 29 | D51: 45705 | E51: GTC 297 | F51: Vintage | G51: 1000 | H51: 193 | Q51: 1000
C52: 30 | D52: 45706 | E52: GTC 298 | F52: AP Bonding | G52: 4000 | H52: 187 | Q52: 4000
C53: 32 | D53: 45706 | E53: 422 | F53: Jaspi | G53: 1000 | H53: 205 | Q53: 1000
C54: 33 | D54: 45706 | E54: 424 | F54: Arun | G54: 200 | H54: 181 | Q54: 200
C55: 34 | D55: 45707 | E55: 425 | F55: Kraft Bond | G55: 500 | H55: 115, 168 | I55: 300 | K55: 200
C56: 35 | D56: 45709 | E56: 429 | F56: Woodland | G56: 1000 | H56: 114 | I56: 1000
C57: 36 | D57: 45712 | E57: 431 | F57: AP Enterpise | G57: 200 | H57: 118 | I57: 200
C58: 37 | D58: 45709 | E58: GTC 299 | F58: Pragati Enterprise | G58: 400 | H58: 208 | Q58: 400
C59: 38 | D59: 45712 | E59: GTC 300 | F59: Veena | G59: 1000 | H59: 197 | Q59: 1000
C60: 41 | D60: 45713 | E60: 432 | F60: Ranakpur | G60: 500 | H60: 180, 190 | Q60: 500
C61: 39 | D61: 45713 | E61: 433 | F61: Mangalam | G61: 85 | H61: 118, 168 | I61: 60 | K61: 25
C62: 42 | D62: 45713 | E62: 434 | F62: JMD | G62: 100 | H62: 120 | I62: 100
C63: 40 | D63: 45715 | E63: 435 | F63: Surya | G63: 2000 | H63: 175 | J63: 2000
C64: 43 | D64: 45715 | E64: 436 | F64: BSB Inds | G64: 4000 | H64: 110 | I64: 4000 | Q64: 5000
C65: 44 | D65: 45715 | E65: 438 | F65: Riddhi Chem | G65: 500 | H65: 194 | Q65: 500
C66: 45 | D66: 45716 | E66: 439 | F66: Pallmer | G66: 40 | H66: 110 | I66: 40
C67: 46 | E67: 372 | F67: SKR
C68: 47 | E68: 374 | F68: Swastik Chem
C69: 48 | E69: 375 | F69: SKR
C70: 49 | E70: 377 | F70: Kunal Chem
C71: 50 | E71: 378 | F71: Mine Chem
C72: 51 | E72: 379 | F72: Pallmer
C73: 52 | E73: 380 | F73: Purvi Enterprise
C74: 53 | E74: 381 | F74: Pallmer
C75: 54 | E75: 382 | F75: Chandan Sybthetic
C76: 55 | E76: GTC 262 | F76: Alpha Chem
C77: 56 | E77: 384 | F77: Surya
C78: 57 | E78: 385 | F78: Amritha
C79: 58 | E79: 388 | F79: Devankshi
C80: 59 | E80: 390 | F80: Akshat
C81: 60 | E81: 391 | F81: Growmore
C82: 61 | E82: GTC 265 | F82: Mine Chem
C83: 62 | E83: GTC 266 | F83: Can Image
C84: 63 | E84: GTC 267 | F84: Yogini
C85: 64 | E85: GTC 268 | F85: Popular
C86: 65 | E86: GTC 269 | F86: Popular
C87: 66 | E87: GTC 270 | F87: Mine Chem
C88: 67 | E88: GTC 271 | F88: Veena
C89: 68 | E89: 393 | F89: Paramount
C90: 69 | E90: 394 | F90: Paramount
C91: 70 | E91: 397 | F91: Shree Mahalaxmi
C92: 71 | E92: 398 | F92: Kanha Trading
C93: 72 | E93: 399 | F93: SKR
C94: 73 | E94: GTC 273 | F94: Chandan Sybthetic
C95: 74 | E95: GTC 274 | F95: SB Enterprise
C96: 75 | F96: Guruji
C97: 76 | F97: Purvi Enterprise
C98: 77 | F98: Gurpreet
C99: 78 | F99: Paramount
C100: 79 | F100: Fortune
C101: 80 | F101: Chemi Care
C102: 81 | F102: Shree Mahalaxmi
C103: TOTAL | D103: 12 | G103: =SUM(G21:G102) -> 46785 | I103: =SUM(I21:I102) -> 20260 | J103: =SUM(J21:J102) -> 5000 | K103: =SUM(K21:K102) -> 2425 | L103: =SUM(L21:L102) -> 0 | M103: =SUM(M21:M102) -> 1400 | N103: =SUM(N21:N102) -> 0 | O103: =SUM(O21:O102) -> 0 | P103: =SUM(P21:P102) -> 0 | Q103: =SUM(Q21:Q102) -> 22200
I105: =SUM('Feb 25'!$I$103:'Feb 25'!$Q$103) -> 51285

Sheet March 25
E2: 177588
D4: Jan 2025 Sales in Nutsell | O4: Prime | P4: Off Grade | Q4: Total
D5: Grades | E5: Off Grade | F5: 1799 | G5: 2699 | H5: 588 | I5: 2088 | J5: 2488 | K5: 2688 | L5: 3099+1788 | M5: DENKA / CCP | N5: TOTAL
A6: Prime stock corrected here | D6: Old Stck CF | E6: 196285 | G6: 1125 | L6: 220 | M6: 27700 | N6: =SUM(E6:M6) -> 225330 | O6: 45925 | P6: 177004 | Q6: 222929
D7: New Input In Dec | E7: =W32 -> 151934 | F7: =F18 -> 28000 | G7: =G18 -> 0 | H7: =H18 -> 0 | I7: =I18 -> 0 | J7: =J18 -> 0 | K7: =K18 -> 0 | L7: =L18 -> 0 | M7: =M18 -> 0 | N7: =SUM(E7:M7) -> 179934 | O7: =SUM(F7:M7) -> 28000 | P7: =E7 -> 151934 | Q7: =O7+P7 -> 179934
D8: Sales In March | E8: =I103 -> 74140 | M8: =Q103 -> 9940 | O8: =SUM(F8:M8) -> 9940 | P8: =E8 -> 74140 | Q8: =SUM(O8,P8) -> 84080
D9: Net Stocks CF | E9: =E6+E7-E8 -> 274079 | F9: =F6+F7-F8 -> 28000 | G9: =G6+G7-G8 -> 1125 | H9: =H6+H7-H8 -> 0 | I9: =I6+I7-I8 -> 0 | J9: =J6+J7-J8 -> 0 | K9: =K6+K7-K8 -> 0 | L9: =L6+L7-L8 -> 220 | ... N9: =N6+N7-N8 -> 405264 | O9: =SUM(F9:M9) -> 47105 | P9: =E9 -> 274079 | Q9: =SUM(O9,P9) -> 321184
C11: PRIME INPUT DETAILS | E11: GRADES | F11: 1799 | G11: 2699 | H11: 588 | I11: 2088 | J11: 2488 | K11: 2688 | L11: 1788 | M11: DENKA / CCP | N11: TOTAL | O11: FROM | P11: IMP NO
C12: SRL NO | D12: MAKE | E12: DATE | N12: =SUM(F12:M12) -> 0 | V12: FOR 800 | W12: 82
C13: 1 | D13: Wanwei | V13: FOR 1000 | W13: 101
C14: 2 | D14: IM | V14: FOR 650 | W14: 70
C15: 3 | D15: CCP | V15: FOR 950 | W15: 98
C16: 4 | D16: Wanwei | V16: FOR 750 | W16: 78
C17: 5 | D17: DADI | E17: 45743 | F17: 28000 | O17: LUCKY | P17: 52 | V17: FOR 850 | W17: 88
C18: TOTAL | F18: =SUM(F12:F17) -> 28000 | G18: =SUM(G12:G17) -> 0 | H18: =SUM(H12:H17) -> 0 | I18: =SUM(I12:I17) -> 0 | J18: =SUM(J12:J17) -> 0 | K18: =SUM(K12:K17) -> 0 | L18: =SUM(L12:L17) -> 0 | M18: =SUM(M12:M17) -> 0 | N18: =SUM(F18:M18) -> 28000 | V18: FOR 775 | W18: 80
V19: FOR 680 | W19: 70
C20: Srl No | D20: Date | E20: Inv No | F20: Party | G20: Qty | H20: Price | I20: Off Grade | J20: 1799 | K20: 2699 | L20: 588 | M20: 2088 | N20: 2488 | O20: 2688 | P20: 3099 / 1788 | Q20: DENKA / CCP | R20: CCP | T20: Off Grade Stocks And Sales
C21: 1 | D21: 45719 | E21: 442 | F21: United Polypack | G21: 4500 | H21: 123 | I21: 4500 | K21: 2000 | T21: New Input
C22: 2 | D22: 45780 | E22: 444 | F22: Akshat | G22: 360 | H22: 118 | I22: 360 | T22: Srl No. | U22: Date | V22: Details | W22: Qty | X22: Per Kgs | Y22: Imp No | Z22: Total Cost
C23: 3 | D23: 45780 | E23: RR | F23: Meet | G23: 2000 | H23: 118 | I23: 2000 | T23: 1 | U23: 45728 | V23: powder | W23: 11920 | X23: 70 | Z23: =W23*X23 -> 834400
C24: 4 | D24: 45722 | E24: 445 | F24: Punav | G24: 2500 | H24: 105 | I24: 2500 | T24: 2 | U24: 45729 | V24: crystal | W24: 21659 | X24: 101 | Z24: =W24*X24 -> 2187559
C25: 5 | D25: 45722 | E25: 446 | F25: JMD | G25: 1700 | H25: 126 | I25: 1700 | T25: 3 | U25: 45729 | V25: crystal | W25: 19509 | X25: 101 | Z25: =W25*X25 -> 1970409
C26: 6 | D26: 45724 | E26: 448 | F26: Mine Chem | G26: 100 | H26: 110 | I26: 100 | T26: 4 | U26: 45735 | V26: crystal | W26: 18888 | X26: 101 | Z26: =W26*X26 -> 1907688
